Workbook

Sheet Project Work - Data (Corrupted)
A1: Order Date | B1: Order Number | C1: Product | D1: Quantity | E1: Price Per Unit | F1: Cost per Unit | G1: Revenue | H1: Costs | I1: Profit | J1: Order Survey Response | K1: Customer ID | L1: Customer Category | M1: Customer Tenure
A2: 45554.63 | B2: 24-3624 | C2: P026 | D2: 15 | E2: 280 | F2: 70 | J2: Dissatisfied | K2: CP-2167 | L2: Corporate & Professional | M2: 10.278064
A3: 43388.154 | B3: 18-3596 | C3: P089 | D3: 8 | E3: 102 | F3: 51 | J3: Neither | K3: CP-2216 | L3: Corporate & Professional | M3: 13.299525
A4: 43463.082 | B4: 18-1394 | C4: P100 | D4: 13 | E4: 46 | J4: Dissatisfied | K4: FE-6557 | L4: Facilities & Services | M4: 9.3226776
A5: 44541.778 | B5: 21-2559 | C5: P034 | D5: 4 | E5: 114 | F5: 57 | J5: Neither | K5: FE-6685 | L5: Facilities & Services | M5: 10.06992
A6: 44789.861 | B6: 22-4827 | C6: P064 | D6: 2 | E6: 231 | F6: 77 | J6: Neither | K6: EE-4169 | L6: Education | M6: 15.24191
A7: 44100.48 | B7: 20-3867 | C7: P040 | D7: 3 | E7: 160 | F7: 80 | J7: Satisfied | K7: HS-7790 | L7: Healthcare & Safety | M7: 12.169267
A8: 43152.556 | B8: 18-1317 | C8: P006 | D8: 6 | E8: 38 | J8: Neither | K8: CT-3882 | L8: Creative & Technology | M8: 11.749994
A9: 43842.898 | B9: 20-3505 | C9: P006 | D9: 11 | J9: Neither | K9: HS-7242 | L9: Healthcare & Safety | M9: 11.048445
A10: 44474.758 | B10: 21-4413 | C10: P094 | D10: 4 | E10: 80 | F10: 20 | J10: Neither | K10: SR-9557 | L10: Sports & Recreation | M10: 10.988762
A11: 44218.773 | B11: 21-3023 | C11: P054 | E11: 144 | F11: 48 | J11: Neither | K11: SR-9989 | L11: Sports & Recreation | M11: 15.602184
A12: 43898.47 | B12: 20-4356 | C12: P043 | D12: 20 | E12: 184 | F12: 92 | J12: Satisfied | K12: EE-4770 | L12: Education | M12: 12.957303
A13: 44085.41 | B13: 20-3883 | C13: P052 | D13: 2 | E13: 352 | F13: 88 | J13: Satisfied | K13: CT-3754 | L13: Creative & Technology | M13: 8.2871811
A14: 43671.067 | B14: 19-3629 | C14: P005 | D14: 5 | E14: 76 | F14: 19 | J14: Neither | K14: CT-3949 | L14: Creative & Technology | M14: 9.8384363
A15: 43997.695 | B15: 20-2783 | C15: P076 | D15: 14 | F15: 47 | J15: Neither | K15: SR-9729 | L15: Sports & Recreation | M15: 12.16373
A16: 44224.976 | B16: 21-3864 | C16: P014 | D16: 16 | E16: 166 | F16: 83 | J16: Satisfied | K16: CT-3881 | L16: Creative & Technology | M16: 13.459801
A17: 44117.051 | B17: 20-1968 | C17: P023 | D17: 7 | F17: 42 | J17: Dissatisfied | K17: CG-1547 | L17: Community & Government | M17: 11.631646
A18: 43834.899 | B18: 20-1980 | C18: P071 | D18: 10 | F18: 70 | J18: Neither | K18: SR-9132 | L18: Sports & Recreation | M18: 12.865075
A19: 44320.298 | B19: 21-4557 | C19: P060 | D19: 6 | E19: 300 | F19: 75 | J19: Neither | K19: SR-9989 | L19: Sports & Recreation | M19: 15.602184
A20: 43253.266 | B20: 18-4105 | C20: P091 | D20: 12 | E20: 204 | F20: 51 | J20: Neither | K20: EE-46 | L20: Education | M20: 9.8238489
A21: 43499.755 | B21: 19-4897 | C21: P094 | D21: 3 | E21: 80 | J21: Satisfied | K21: SR-955 | L21: Sports & Recreation | M21: 12.072415
A22: 44125.238 | B22: 20-4960 | C22: P028 | D22: 17 | E22: 156 | F22: 78 | J22: Neither | K22: CG-151 | L22: Community & Government | M22: 15.140904
A23: 44357.627 | B23: 21-2115 | C23: P065 | D23: 9 | E23: 50 | J23: Dissatisfied | K23: EE-4774 | L23: Education | M23: 15.126377
A24: 44807.029 | B24: 22-4758 | C24: P026 | D24: 1 | E24: 280 | J24: Neither | K24: HS-7790 | L24: Healthcare & Safety | M24: 12.169267
A25: 43068.002 | B25: 17-1449 | C25: P098 | D25: 5 | E25: 201 | J25: Satisfied | K25: FE-6410 | L25: Facilities & Services | M25: 13.717776
A26: 44066.937 | B26: 20-2961 | C26: P023 | D26: 3 | E26: 126 | F26: 42 | J26: Dissatisfied | K26: SR-9880 | L26: Sports & Recreation | M26: 9.7467096
A27: 43608.539 | B27: 19-3898 | C27: P002 | D27: 12 | E27: 144 | F27: 36 | J27: Satisfied | K27: HS-7440 | L27: Healthcare & Safety | M27: 13.407341
A28: 43624.553 | B28: 19-4584 | C28: P024 | D28: 5 | E28: 66 | J28: Neither | K28: HS-7440 | L28: Healthcare & Safety | M28: 13.407341
A29: 43952.992 | B29: 20-4784 | C29: P030 | D29: 14 | E29: 81 | F29: 27 | J29: Neither | K29: SR-9497 | L29: Sports & Recreation | M29: 14.697745
A30: 44248.206 | B30: 21-2025 | C30: P043 | D30: 18 | E30: 184 | F30: 92 | J30: Satisfied | K30: SR-9668 | L30: Sports & Recreation | M30: 11.128722
A31: 43717.585 | B31: 19-3656 | C31: P048 | D31: 4 | E31: 252 | F31: 63 | J31: Neither | K31: SR-9563 | L31: Sports & Recreation | M31: 14.163035
A32: 43447.602 | B32: 18-1412 | C32: P071 | D32: 10 | E32: 210 | F32: 70 | J32: Neither | K32: HS-7291 | L32: Healthcare & Safety | M32: 10.42743
A33: 43413.651 | B33: 18-3342 | C33: P087 | D33: 12 | E33: 176 | F33: 88 | J33: Neither | K33: SR-9632 | L33: Sports & Recreation | M33: 11.006398
A34: 44213.146 | B34: 21-2874 | C34: P043 | D34: 15 | F34: 92 | J34: Neither | K34: FE-6617 | L34: Facilities & Services | M34: 15.487214
A35: 43907.019 | B35: 20-1831 | C35: P096 | D35: 17 | J35: Neither | K35: CP-295 | L35: Corporate & Professional | M35: 12.844063
A36: 43704.679 | B36: 19-2562 | C36: P003 | D36: 7 | E36: 189 | F36: 63 | J36: Dissatisfied | K36: CP-2330 | L36: Corporate & Professional | M36: 9.4200113
A37: 44358.082 | B37: 21-4466 | C37: P084 | D37: 7 | J37: Neither | K37: FE-621 | L37: Facilities & Services | M37: 11.410471
A38: 44285.752 | B38: 21-3075 | C38: P085 | D38: 18 | F38: 80 | J38: Satisfied | K38: HS-7220 | L38: Healthcare & Safety | M38: 7.1104128
A39: 44467.408 | B39: 21-3988 | C39: P025 | D39: 11 | F39: 70 | J39: Satisfied | K39: SR-9797 | L39: Sports & Recreation | M39: 11.406234
A40: 43336.7 | B40: 18-2953 | C40: P021 | D40: 1 | E40: 207 | F40: 69 | J40: Neither | K40: SR-9639 | L40: Sports & Recreation | M40: 12.487915
A41: 43690.881 | B41: 19-4687 | C41: P067 | D41: 17 | F41: 36 | J41: Neither | K41: CT-3363 | L41: Creative & Technology | M41: 8.1085103
A42: 43662.097 | B42: 19-2414 | C42: P022 | E42: 153 | F42: 51 | J42: Neither | K42: CP-2962 | L42: Corporate & Professional | M42: 11.749038
A43: 44132.428 | B43: 20-3269 | C43: P019 | D43: 15 | E43: 308 | F43: 77 | J43: Neither | K43: FE-6919 | L43: Facilities & Services | M43: 13.37808
A44: 44320.151 | B44: 21-2837 | C44: P053 | D44: 14 | E44: 50 | F44: 25 | J44: Neither | K44: CT-3600 | L44: Creative & Technology | M44: 11.841064
A45: 44435.703 | B45: 21-3029 | C45: P099 | D45: 15 | E45: 132 | F45: 33 | J45: Neither | K45: CP-2862 | L45: Corporate & Professional | M45: 14.370283
A46: 44005.712 | B46: 20-4975 | C46: P001 | D46: 9 | F46: 36 | J46: Dissatisfied | K46: CG-1606 | L46: Community & Government | M46: 12.452986
A47: 43092.206 | B47: 17-2409 | C47: P001 | D47: 11 | E47: 108 | F47: 36 | J47: Satisfied | K47: SR-9132 | L47: Sports & Recreation | M47: 12.865075
A48: 44486.277 | B48: 21-4384 | C48: P040 | D48: 19 | E48: 160 | F48: 80 | J48: Neither | K48: CG-1762 | L48: Community & Government | M48: 10.216283
A49: 43872.552 | B49: 20-2456 | C49: P005 | D49: 8 | E49: 76 | F49: 19 | J49: Dissatisfied | K49: CP-2204 | L49: Corporate & Professional | M49: 15.121383
A50: 44229.668 | B50: 21-2798 | C50: P008 | D50: 12 | E50: 225 | F50: 75 | J50: Dissatisfied | K50: CP-2101 | L50: Corporate & Professional | M50: 9.9311
A51: 43814.387 | B51: 19-4348 | C51: P006 | D51: 15 | E51: 38 | F51: 19 | J51: Neither | K51: SR-9729 | L51: Sports & Recreation | M51: 12.16373
A52: 44647.579 | B52: 22-1555 | C52: P046 | D52: 1 | E52: 38 | F52: 19 | J52: Neither | K52: SR-9320 | L52: Sports & Recreation | M52: 12.133499
A53: 44185.353 | B53: 20-4454 | C53: P004 | D53: 16 | F53: 63 | J53: Neither | K53: HS-7751 | L53: Healthcare & Safety | M53: 11.36085
A54: 44436.923 | B54: 21-3857 | C54: P071 | D54: 9 | E54: 210 | F54: 70 | J54: Neither | K54: HS-7865 | L54: Healthcare & Safety | M54: 11.727498
A55: 44628.844 | B55: 22-3797 | C55: P026 | D55: 15 | E55: 280 | F55: 70 | J55: Satisfied | K55: CT-3518 | L55: Creative & Technology | M55: 11.939773
A56: 43747.489 | B56: 19-2441 | C56: P031 | D56: 15 | F56: 73 | J56: Neither | K56: CT-3443 | L56: Creative & Technology | M56: 11.312215
A57: 43654.266 | B57: 19-4589 | C57: P044 | D57: 18 | E57: 368 | F57: 92 | J57: Satisfied | K57: CT-317 | L57: Creative & Technology | M57: 12.551204
A58: 44805.17 | B58: 22-1984 | C58: P030 | D58: 11 | E58: 81 | J58: Neither | K58: FE-6323 | L58: Facilities & Services | M58: 10.523528
A59: 43921.083 | B59: 20-3458 | C59: P062 | D59: 16 | E59: 348 | F59: 87 | J59: Satisfied | K59: FE-6562 | L59: Facilities & Services | M59: 14.573178
A60: 43830.8 | B60: 19-3647 | C60: P088 | D60: 9 | E60: 192 | F60: 96 | J60: Neither | K60: EE-4990 | L60: Education | M60: 13.288482
A61: 44001.387 | B61: 20-2780 | C61: P096 | D61: 13 | E61: 144 | F61: 48 | J61: Neither | K61: CG-168 | L61: Community & Government | M61: 13.890275
A62: 44151.647 | B62: 20-3980 | C62: P012 | D62: 15 | E62: 30 | J62: Neither | K62: CT-3608 | L62: Creative & Technology | M62: 13.765798
A63: 43813.774 | B63: 19-3215 | C63: P033 | D63: 13 | E63: 57 | F63: 19 | J63: Neither | K63: CP-2647 | L63: Corporate & Professional | M63: 12.007835
A64: 44758.713 | B64: 22-4552 | C64: P022 | D64: 7 | E64: 153 | F64: 51 | J64: Neither | K64: FE-6639 | L64: Facilities & Services | M64: 12.17771
A65: 43603.022 | B65: 19-3308 | C65: P069 | D65: 17 | E65: 150 | F65: 75 | J65: Neither | K65: CT-3618 | L65: Creative & Technology | M65: 11.995407
A66: 44107.238 | B66: 20-3048 | C66: P029 | D66: 19 | E66: 300 | F66: 75 | J66: Satisfied | K66: CT-3779 | L66: Creative & Technology | M66: 10.980884
A67: 44449.256 | B67: 21-4381 | C67: P015 | D67: 4 | E67: 176 | F67: 88 | J67: Neither | K67: CT-3891 | L67: Creative & Technology | M67: 15.556812
A68: 43166.401 | B68: 18-2659 | C68: P061 | D68: 2 | E68: 264 | F68: 88 | J68: Neither | K68: EE-4565 | L68: Education | M68: 13.697486
A69: 43194.923 | B69: 18-3836 | C69: P089 | D69: 1 | E69: 102 | F69: 51 | J69: Neither | K69: EE-40 | L69: Education | M69: 12.396052
A70: 43849.638 | B70: 20-2983 | C70: P053 | D70: 12 | F70: 25 | J70: Dissatisfied | K70: SR-9536 | L70: Sports & Recreation | M70: 14.030595
A71: 43576.804 | B71: 19-3463 | C71: P008 | D71: 3 | E71: 225 | F71: 75 | J71: Neither | K71: CP-258 | L71: Corporate & Professional | M71: 11.083482
A72: 44221.252 | B72: 21-4937 | C72: P035 | D72: 18 | E72: 144 | F72: 48 | J72: Dissatisfied | K72: HS-7652 | L72: Healthcare & Safety | M72: 14.377134
A73: 43427.368 | B73: 18-4366 | C73: P005 | D73: 16 | E73: 76 | F73: 19 | J73: Satisfied | K73: FE-6999 | L73: Facilities & Services | M73: 12.172923
A74: 43140.297 | B74: 18-1699 | C74: P012 | D74: 6 | E74: 30 | F74: 15 | J74: Neither | K74: CG-1369 | L74: Community & Government | M74: 11.346511
A75: 44322.803 | B75: 21-4584 | C75: P028 | D75: 2 | E75: 156 | F75: 78 | J75: Neither | K75: SR-9872 | L75: Sports & Recreation | M75: 12.200534
A76: 43261.784 | B76: 18-3352 | C76: P098 | D76: 12 | F76: 67 | J76: Satisfied | K76: HS-7827 | L76: Healthcare & Safety | M76: 9.3014286
A77: 44835.616 | B77: 22-4831 | C77: P040 | D77: 20 | E77: 160 | F77: 80 | J77: Dissatisfied | K77: CG-1446 | L77: Community & Government | M77: 14.59367
A78: 43680.736 | B78: 19-4143 | C78: P018 | D78: 18 | E78: 108 | F78: 54 | J78: Neither | K78: CP-2430 | L78: Corporate & Professional | M78: 11.274865
A79: 43726.32 | B79: 19-3106 | C79: P083 | D79: 10 | E79: 90 | F79: 45 | J79: Neither | K79: CG-1316 | L79: Community & Government | M79: 15.45886
A80: 44147.512 | B80: 20-2673 | C80: P054 | D80: 19 | E80: 144 | J80: Dissatisfied | K80: CT-3321 | L80: Creative & Technology | M80: 15.23433
A81: 43751.772 | B81: 19-1622 | C81: P072 | D81: 2 | E81: 132 | F81: 44 | J81: Neither | K81: EE-4569 | L81: Education | M81: 12.699346
A82: 44436.69 | B82: 21-2880 | C82: P099 | D82: 1 | E82: 132 | F82: 33 | J82: Neither | K82: CT-3443 | L82: Creative & Technology | M82: 11.312215
A83: 44420.177 | B83: 21-3439 | C83: P057 | D83: 19 | E83: 252 | F83: 63 | J83: Dissatisfied | K83: HS-7838 | L83: Healthcare & Safety | M83: 13.918154
A84: 44589.354 | B84: 22-4693 | C84: P027 | D84: 1 | E84: 140 | F84: 70 | J84: Neither | K84: SR-9320 | L84: Sports & Recreation | M84: 12.133499
A85: 44117.155 | B85: 20-3308 | C85: P037 | D85: 19 | E85: 160 | F85: 80 | J85: Satisfied | K85: FE-621 | L85: Facilities & Services | M85: 11.410471
A86: 43922.931 | B86: 20-1527 | C86: P039 | D86: 2 | E86: 270 | F86: 90 | J86: Neither | K86: HS-7440 | L86: Healthcare & Safety | M86: 13.407341
A87: 44272.031 | B87: 21-2318 | C87: P032 | D87: 13 | J87: Neither | K87: CG-137 | L87: Community & Government | M87: 12.796588
A88: 43350.492 | B88: 18-2068 | C88: P046 | D88: 11 | E88: 38 | F88: 19 | J88: Satisfied | K88: FE-6898 | L88: Facilities & Services | M88: 12.514998
A89: 44115.807 | B89: 20-4090 | C89: P081 | D89: 4 | E89: 50 | F89: 25 | J89: Neither | K89: CP-2430 | L89: Corporate & Professional | M89: 11.274865
A90: 44055.582 | B90: 20-4835 | C90: P094 | D90: 6 | E90: 80 | F90: 20 | J90: Satisfied | K90: EE-4917 | L90: Education | M90: 11.756375
A91: 44149.646 | B91: 20-4525 | C91: P022 | D91: 18 | E91: 153 | F91: 51 | J91: Neither | K91: FE-6669 | L91: Facilities & Services | M91: 12.661538
A92: 43702.683 | B92: 19-1106 | C92: P061 | D92: 16 | E92: 264 | F92: 88 | J92: Satisfied | K92: EE-423 | L92: Education | M92: 12.503633
A93: 44585.043 | B93: 22-3861 | C93: P037 | D93: 2 | E93: 160 | F93: 80 | J93: Neither | K93: CG-1992 | L93: Community & Government | M93: 9.8218828
A94: 44623.935 | B94: 22-3095 | C94: P090 | D94: 8 | F94: 19 | J94: Dissatisfied | K94: CT-3235 | L94: Creative & Technology | M94: 11.883396
A95: 43747.618 | B95: 19-1753 | C95: P024 | D95: 17 | F95: 33 | J95: Neither | K95: SR-9883 | L95: Sports & Recreation | M95: 11.504887
A96: 44266.901 | B96: 21-4842 | C96: P052 | D96: 1 | E96: 352 | F96: 88 | J96: Satisfied | K96: CP-2582 | L96: Corporate & Professional | M96: 11.428576
A97: 44672.351 | B97: 22-4766 | C97: P041 | D97: 4 | E97: 144 | F97: 36 | J97: Dissatisfied | K97: CT-3971 | L97: Creative & Technology | M97: 10.570474
A98: 43441.398 | B98: 18-3191 | C98: P066 | D98: 7 | E98: 34 | F98: 17 | J98: Dissatisfied | K98: CG-1369 | L98: Community & Government | M98: 11.346511
A99: 43848.38 | B99: 20-4379 | C99: P073 | D99: 14 | F99: 24 | J99: Satisfied | K99: FE-621 | L99: Facilities & Services | M99: 11.410471
A100: 44443.649 | B100: 21-3280 | C100: P073 | D100: 19 | E100: 48 | F100: 24 | J100: Neither | K100: CG-1908 | L100: Community & Government | M100: 12.758431
...

Sheet Price Averages
A3: Row Labels | B3: Average of Price Per Unit
A4: P001 | B4: 108 | D4: P001 | E4: 108
A5: P002 | B5: 144 | D5: P002 | E5: 144
A6: P003 | B6: 189 | D6: P003 | E6: 189
A7: P004 | B7: 189 | D7: P004 | E7: 189
A8: P005 | B8: 76 | D8: P005 | E8: 76
A9: P006 | B9: 38 | D9: P006 | E9: 38
A10: P007 | B10: 225 | D10: P007 | E10: 225
A11: P008 | B11: 225 | D11: P008 | E11: 225
A12: P009 | B12: 255 | D12: P009 | E12: 255
A13: P010 | B13: 144 | D13: P010 | E13: 144
A14: P011 | B14: 264 | D14: P011 | E14: 264
A15: P012 | B15: 30 | D15: P012 | E15: 30
... A103: P100 | B103: 46 | D103: P100 | E103: 46
A104: (blank)
A105: Grand Total | B105: 173.30017

Sheet Cost Averages
A3: Row Labels | B3: Average of Cost per Unit
A4: P001 | B4: 36 | D4: P001 | E4: 36
A5: P002 | B5: 36 | D5: P002 | E5: 36
A6: P003 | B6: 63 | D6: P003 | E6: 63
A7: P004 | B7: 63 | D7: P004 | E7: 63
A8: P005 | B8: 19 | D8: P005 | E8: 19
A9: P006 | B9: 19 | D9: P006 | E9: 19
A10: P007 | B10: 75 | D10: P007 | E10: 75
A11: P008 | B11: 75 | D11: P008 | E11: 75
A12: P009 | B12: 85 | D12: P009 | E12: 85
A13: P010 | B13: 36 | D13: P010 | E13: 36
A14: P011 | B14: 88 | D14: P011 | E14: 88
A15: P012 | B15: 15 | D15: P012 | E15: 15
... A103: P100 | B103: 23 | D103: P100 | E103: 23
A104: (blank)
A105: Grand Total | B105: 57.57266

Sheet PivotTable Full Data
A3: Row Labels | B3: Average of Profit | C3: StdDev of Profit | D3: Count of Profit | E3: Sum of Profit
A4: A | B4: 1448 | C4: 822.85625 | D4: 6 | E4: 8688 | G4: A | H4: 1448 | I4: 822.85625 | J4: 6 | K4: 8688 | M4: =(H4-H5)/SQRT((I4^2/J4)+(I5^2/J5)) -> 0.56264453
A5: B | B5: 1216.9474 | C5: 1029.5546 | D5: 19 | E5: 23122 | G5: B | H5: 1216.9474 | I5: 1029.5546 | J5: 19 | K5: 23122 | M5: =(H5-H6)/SQRT((I5^2/J5)+(I6^2/J6)) -> 0.089139479
A6: C | B6: 1193.6765 | C6: 1123.0273 | D6: 102 | E6: 121755 | G6: C | H6: 1193.6765 | I6: 1123.0273 | J6: 102 | K6: 121755 | M6: =(H6-H7)/SQRT((I6^2/J6)+(I7^2/J7)) -> -0.94857796
A7: D | B7: 1316.4048 | C7: 1212.4246 | D7: 336 | E7: 442312 | G7: D | H7: 1316.4048 | I7: 1212.4246 | J7: 336 | K7: 442312 | M7: =(H7-H8)/SQRT((I7^2/J7)+(I8^2/J8)) -> 1.909998
A8: E | B8: 1169.192 | C8: 1083.6076 | D8: 750 | E8: 876894 | G8: E | H8: 1169.192 | I8: 1083.6076 | J8: 750 | K8: 876894 | M8: =(H8-H9)/SQRT((I8^2/J8)+(I9^2/J9)) -> -0.98120767
A9: F | B9: 1219.6756 | C9: 1116.7021 | D9: 1153 | E9: 1406286 | G9: F | H9: 1219.6756 | I9: 1116.7021 | J9: 1153 | K9: 1406286 | M9: =(H9-H10)/SQRT((I9^2/J9)+(I10^2/J10)) -> 0.091626056
A10: G | B10: 1215.0917 | C10: 1134.1437 | D10: 905 | E10: 1099658 | G10: G | H10: 1215.0917 | I10: 1134.1437 | J10: 905 | K10: 1099658 | M10: =(H10-H11)/SQRT((I10^2/J10)+(I11^2/J11)) -> -0.12973334
A11: H | B11: 1223.3726 | C11: 1122.5755 | D11: 475 | E11: 581102 | G11: H | H11: 1223.3726 | I11: 1122.5755 | J11: 475 | K11: 581102 | M11: =(H11-H12)/SQRT((I11^2/J11)+(I12^2/J12)) -> 2.7333454
A12: I | B12: 910.83929 | C12: 763.91613 | D12: 56 | E12: 51007 | G12: I | H12: 910.83929 | I12: 763.91613 | J12: 56 | K12: 51007 | M12: =(H12-H13)/SQRT((I12^2/J12)+(I13^2/J13)) -> -1.1295798
A13: J | B13: 1407.0909 | C13: 1417.1919 | D13: 11 | E13: 15478 | G13: J | H13: 1407.0909 | I13: 1417.1919 | J13: 11 | K13: 15478 | M13: =(H13-H14)/SQRT((I13^2/J13)+(I14^2/J14)) -> 2.1642064
A14: K | B14: 470 | C14: 98.994949 | D14: 2 | E14: 940 | G14: K | H14: 470 | I14: 98.994949 | J14: 2 | K14: 940
A15: Grand Total | B15: 1212.9075 | C15: 1119.8254 | D15: 3815 | E15: 4627242

Sheet Project Work - Data Del Rows
A1: Order Date | B1: Order Number | C1: Product | D1: Quantity | E1: Price Per Unit | F1: Fixed Price Per Unit | G1: Cost per Unit | H1: Fixed Cost Per Unit | I1: Revenue | J1: Costs | K1: Profit | L1: Order Survey Response | M1: Customer ID | N1: Customer Category | O1: Customer Tenure | P1: Subset Label | Q1: Subset | R1: Subset Check
A2: 42258.411 | B2: 15-4254 | C2: P037 | D2: 1 | E2: 160 | F2: =IF(E2="",_xlfn.XLOOKUP(C2,'Price Averages'!$D$4:$D$103,'Price Averages'!$E$4:$E$103, "FALSE"), E2) -> 160 | G2: 80 | H2: =IF(G2="", _xlfn.XLOOKUP(C2, 'Cost Averages'!$D$4:$D$103,'Cost Averages'!$E$4:$E$103, "FALSE"),G2) -> 80 | I2: =D2*F2 -> 160 | J2: =D2*H2 -> 80 | K2: =I2-J2 -> 80 | L2: Neither | M2: HS-7862 | N2: Healthcare & Safety | O2: 14.423323 | P2: =CHAR(64+(YEAR(A2)-2014)) -> A | Q2: =YEAR(A2) -> 2015 | R2: =IF(P2=CHAR(64 + (YEAR(A2) - 2014)), 0, 1) -> 0
A3: 42178.711 | B3: 15-2073 | C3: P055 | D3: 8 | E3: 360 | F3: =IF(E3="",_xlfn.XLOOKUP(C3,'Price Averages'!$D$4:$D$103,'Price Averages'!$E$4:$E$103, "FALSE"), E3) -> 360 | G3: 90 | H3: =IF(G3="", _xlfn.XLOOKUP(C3, 'Cost Averages'!$D$4:$D$103,'Cost Averages'!$E$4:$E$103, "FALSE"),G3) -> 90 | I3: =D3*F3 -> 2880 | J3: =D3*H3 -> 720 | K3: =I3-J3 -> 2160 | L3: Neither | M3: CP-2960 | N3: Corporate & Professional | O3: 13.062293 | P3: =CHAR(64+(YEAR(A3)-2014)) -> A | Q3: =YEAR(A3) -> 2015 | R3: =IF(P3=CHAR(64 + (YEAR(A3) - 2014)), 0, 1) -> 0
A4: 42368.549 | B4: 15-3490 | C4: P057 | D4: 9 | E4: 252 | F4: =IF(E4="",_xlfn.XLOOKUP(C4,'Price Averages'!$D$4:$D$103,'Price Averages'!$E$4:$E$103, "FALSE"), E4) -> 252 | G4: 63 | H4: =IF(G4="", _xlfn.XLOOKUP(C4, 'Cost Averages'!$D$4:$D$103,'Cost Averages'!$E$4:$E$103, "FALSE"),G4) -> 63 | I4: =D4*F4 -> 2268 | J4: =D4*H4 -> 567 | K4: =I4-J4 -> 1701 | L4: Satisfied | M4: CT-3606 | N4: Creative & Technology | O4: 12.173452 | P4: =CHAR(64+(YEAR(A4)-2014)) -> A | Q4: =YEAR(A4) -> 2015 | R4: =IF(P4=CHAR(64 + (YEAR(A4) - 2014)), 0, 1) -> 0
A5: 42297.389 | B5: 15-3098 | C5: P031 | D5: 13 | F5: =IF(E5="",_xlfn.XLOOKUP(C5,'Price Averages'!$D$4:$D$103,'Price Averages'!$E$4:$E$103, "FALSE"), E5) -> 146 | G5: 73 | H5: =IF(G5="", _xlfn.XLOOKUP(C5, 'Cost Averages'!$D$4:$D$103,'Cost Averages'!$E$4:$E$103, "FALSE"),G5) -> 73 | I5: =D5*F5 -> 1898 | J5: =D5*H5 -> 949 | K5: =I5-J5 -> 949 | L5: Neither | M5: HS-770 | N5: Healthcare & Safety | O5: 12.148237 | P5: =CHAR(64+(YEAR(A5)-2014)) -> A | Q5: =YEAR(A5) -> 2015 | R5: =IF(P5=CHAR(64 + (YEAR(A5) - 2014)), 0, 1) -> 0
A6: 42322.453 | B6: 15-3015 | C6: P098 | D6: 17 | E6: 201 | F6: =IF(E6="",_xlfn.XLOOKUP(C6,'Price Averages'!$D$4:$D$103,'Price Averages'!$E$4:$E$103, "FALSE"), E6) -> 201 | G6: 67 | H6: =IF(G6="", _xlfn.XLOOKUP(C6, 'Cost Averages'!$D$4:$D$103,'Cost Averages'!$E$4:$E$103, "FALSE"),G6) -> 67 | I6: =D6*F6 -> 3417 | J6: =D6*H6 -> 1139 | K6: =I6-J6 -> 2278 | L6: Satisfied | M6: EE-4613 | N6: Education | O6: 15.26855 | P6: =CHAR(64+(YEAR(A6)-2014)) -> A | Q6: =YEAR(A6) -> 2015 | R6: =IF(P6=CHAR(64 + (YEAR(A6) - 2014)), 0, 1) -> 0
A7: 42216.891 | B7: 15-4617 | C7: P075 | D7: 19 | E7: 160 | F7: =IF(E7="",_xlfn.XLOOKUP(C7,'Price Averages'!$D$4:$D$103,'Price Averages'!$E$4:$E$103, "FALSE"), E7) -> 160 | G7: 80 | H7: =IF(G7="", _xlfn.XLOOKUP(C7, 'Cost Averages'!$D$4:$D$103,'Cost Averages'!$E$4:$E$103, "FALSE"),G7) -> 80 | I7: =D7*F7 -> 3040 | J7: =D7*H7 -> 1520 | K7: =I7-J7 -> 1520 | L7: Neither | M7: EE-4917 | N7: Education | O7: 11.756375 | P7: =CHAR(64+(YEAR(A7)-2014)) -> A | Q7: =YEAR(A7) -> 2015 | R7: =IF(P7=CHAR(64 + (YEAR(A7) - 2014)), 0, 1) -> 0
A8: 42720.978 | B8: 16-1451 | C8: P064 | D8: 1 | E8: 231 | F8: =IF(E8="",_xlfn.XLOOKUP(C8,'Price Averages'!$D$4:$D$103,'Price Averages'!$E$4:$E$103, "FALSE"), E8) -> 231 | G8: 77 | H8: =IF(G8="", _xlfn.XLOOKUP(C8, 'Cost Averages'!$D$4:$D$103,'Cost Averages'!$E$4:$E$103, "FALSE"),G8) -> 77 | I8: =D8*F8 -> 231 | J8: =D8*H8 -> 77 | K8: =I8-J8 -> 154 | L8: Neither | M8: CT-3498 | N8: Creative & Technology | O8: 10.588336 | P8: =CHAR(64+(YEAR(A8)-2014)) -> B | Q8: =YEAR(A8) -> 2016 | R8: =IF(P8=CHAR(64 + (YEAR(A8) - 2014)), 0, 1) -> 0
A9: 42673.243 | B9: 16-1836 | C9: P006 | D9: 2 | F9: =IF(E9="",_xlfn.XLOOKUP(C9,'Price Averages'!$D$4:$D$103,'Price Averages'!$E$4:$E$103, "FALSE"), E9) -> 38 | G9: 19 | H9: =IF(G9="", _xlfn.XLOOKUP(C9, 'Cost Averages'!$D$4:$D$103,'Cost Averages'!$E$4:$E$103, "FALSE"),G9) -> 19 | I9: =D9*F9 -> 76 | J9: =D9*H9 -> 38 | K9: =I9-J9 -> 38 | L9: Neither | M9: CG-1672 | N9: Community & Government | O9: 11.655356 | P9: =CHAR(64+(YEAR(A9)-2014)) -> B | Q9: =YEAR(A9) -> 2016 | R9: =IF(P9=CHAR(64 + (YEAR(A9) - 2014)), 0, 1) -> 0
A10: 42673.971 | B10: 16-3460 | C10: P083 | D10: 2 | E10: 90 | F10: =IF(E10="",_xlfn.XLOOKUP(C10,'Price Averages'!$D$4:$D$103,'Price Averages'!$E$4:$E$103, "FALSE"), E10) -> 90 | H10: =IF(G10="", _xlfn.XLOOKUP(C10, 'Cost Averages'!$D$4:$D$103,'Cost Averages'!$E$4:$E$103, "FALSE"),G10) -> 45 | I10: =D10*F10 -> 180 | J10: =D10*H10 -> 90 | K10: =I10-J10 -> 90 | L10: Satisfied | M10: CT-3920 | N10: Creative & Technology | O10: 14.661477 | P10: =CHAR(64+(YEAR(A10)-2014)) -> B | Q10: =YEAR(A10) -> 2016 | R10: =IF(P10=CHAR(64 + (YEAR(A10) - 2014)), 0, 1) -> 0
A11: 42447.175 | B11: 16-2553 | C11: P100 | D11: 5 | E11: 46 | F11: =IF(E11="",_xlfn.XLOOKUP(C11,'Price Averages'!$D$4:$D$103,'Price Averages'!$E$4:$E$103, "FALSE"), E11) -> 46 | G11: 23 | H11: =IF(G11="", _xlfn.XLOOKUP(C11, 'Cost Averages'!$D$4:$D$103,'Cost Averages'!$E$4:$E$103, "FALSE"),G11) -> 23 | I11: =D11*F11 -> 230 | J11: =D11*H11 -> 115 | K11: =I11-J11 -> 115 | L11: Satisfied | M11: EE-46 | N11: Education | O11: 9.8238489 | P11: =CHAR(64+(YEAR(A11)-2014)) -> B | Q11: =YEAR(A11) -> 2016 | R11: =IF(P11=CHAR(64 + (YEAR(A11) - 2014)), 0, 1) -> 0
A12: 42695.685 | B12: 16-4606 | C12: P008 | D12: 6 | E12: 225 | F12: =IF(E12="",_xlfn.XLOOKUP(C12,'Price Averages'!$D$4:$D$103,'Price Averages'!$E$4:$E$103, "FALSE"), E12) -> 225 | G12: 75 | H12: =IF(G12="", _xlfn.XLOOKUP(C12, 'Cost Averages'!$D$4:$D$103,'Cost Averages'!$E$4:$E$103, "FALSE"),G12) -> 75 | I12: =D12*F12 -> 1350 | J12: =D12*H12 -> 450 | K12: =I12-J12 -> 900 | L12: Neither | M12: SR-930 | N12: Sports & Recreation | O12: 14.690199 | P12: =CHAR(64+(YEAR(A12)-2014)) -> B | Q12: =YEAR(A12) -> 2016 | R12: =IF(P12=CHAR(64 + (YEAR(A12) - 2014)), 0, 1) -> 0
A13: 42693.272 | B13: 16-2390 | C13: P043 | D13: 8 | E13: 184 | F13: =IF(E13="",_xlfn.XLOOKUP(C13,'Price Averages'!$D$4:$D$103,'Price Averages'!$E$4:$E$103, "FALSE"), E13) -> 184 | G13: 92 | H13: =IF(G13="", _xlfn.XLOOKUP(C13, 'Cost Averages'!$D$4:$D$103,'Cost Averages'!$E$4:$E$103, "FALSE"),G13) -> 92 | I13: =D13*F13 -> 1472 | J13: =D13*H13 -> 736 | K13: =I13-J13 -> 736 | L13: Neither | M13: HS-712 | N13: Healthcare & Safety | O13: 10.428287 | P13: =CHAR(64+(YEAR(A13)-2014)) -> B | Q13: =YEAR(A13) -> 2016 | R13: =IF(P13=CHAR(64 + (YEAR(A13) - 2014)), 0, 1) -> 0
A14: 42656.038 | B14: 16-1050 | C14: P058 | D14: 8 | F14: =IF(E14="",_xlfn.XLOOKUP(C14,'Price Averages'!$D$4:$D$103,'Price Averages'!$E$4:$E$103, "FALSE"), E14) -> 356 | G14: 89 | H14: =IF(G14="", _xlfn.XLOOKUP(C14, 'Cost Averages'!$D$4:$D$103,'Cost Averages'!$E$4:$E$103, "FALSE"),G14) -> 89 | I14: =D14*F14 -> 2848 | J14: =D14*H14 -> 712 | K14: =I14-J14 -> 2136 | L14: Neither | M14: EE-4357 | N14: Education | O14: 13.466363 | P14: =CHAR(64+(YEAR(A14)-2014)) -> B | Q14: =YEAR(A14) -> 2016 | R14: =IF(P14=CHAR(64 + (YEAR(A14) - 2014)), 0, 1) -> 0
A15: 42720.868 | B15: 16-4872 | C15: P055 | D15: 9 | F15: =IF(E15="",_xlfn.XLOOKUP(C15,'Price Averages'!$D$4:$D$103,'Price Averages'!$E$4:$E$103, "FALSE"), E15) -> 360 | G15: 90 | H15: =IF(G15="", _xlfn.XLOOKUP(C15, 'Cost Averages'!$D$4:$D$103,'Cost Averages'!$E$4:$E$103, "FALSE"),G15) -> 90 | I15: =D15*F15 -> 3240 | J15: =D15*H15 -> 810 | K15: =I15-J15 -> 2430 | L15: Satisfied | M15: SR-9808 | N15: Sports & Recreation | O15: 10.816866 | P15: =CHAR(64+(YEAR(A15)-2014)) -> B | Q15: =YEAR(A15) -> 2016 | R15: =IF(P15=CHAR(64 + (YEAR(A15) - 2014)), 0, 1) -> 0
A16: 42476.479 | B16: 16-2216 | C16: P074 | D16: 10 | E16: 352 | F16: =IF(E16="",_xlfn.XLOOKUP(C16,'Price Averages'!$D$4:$D$103,'Price Averages'!$E$4:$E$103, "FALSE"), E16) -> 352 | H16: =IF(G16="", _xlfn.XLOOKUP(C16, 'Cost Averages'!$D$4:$D$103,'Cost Averages'!$E$4:$E$103, "FALSE"),G16) -> 88 | I16: =D16*F16 -> 3520 | J16: =D16*H16 -> 880 | K16: =I16-J16 -> 2640 | L16: Dissatisfied | M16: HS-7291 | N16: Healthcare & Safety | O16: 10.42743 | P16: =CHAR(64+(YEAR(A16)-2014)) -> B | Q16: =YEAR(A16) -> 2016 | R16: =IF(P16=CHAR(64 + (YEAR(A16) - 2014)), 0, 1) -> 0
A17: 42681.511 | B17: 16-3455 | C17: P013 | D17: 11 | E17: 58 | F17: =IF(E17="",_xlfn.XLOOKUP(C17,'Price Averages'!$D$4:$D$103,'Price Averages'!$E$4:$E$103, "FALSE"), E17) -> 58 | H17: =IF(G17="", _xlfn.XLOOKUP(C17, 'Cost Averages'!$D$4:$D$103,'Cost Averages'!$E$4:$E$103, "FALSE"),G17) -> 29 | I17: =D17*F17 -> 638 | J17: =D17*H17 -> 319 | K17: =I17-J17 -> 319 | L17: Neither | M17: EE-450 | N17: Education | O17: 8.3272838 | P17: =CHAR(64+(YEAR(A17)-2014)) -> B | Q17: =YEAR(A17) -> 2016 | R17: =IF(P17=CHAR(64 + (YEAR(A17) - 2014)), 0, 1) -> 0
A18: 42614.075 | B18: 16-2604 | C18: P067 | D18: 11 | E18: 144 | F18: =IF(E18="",_xlfn.XLOOKUP(C18,'Price Averages'!$D$4:$D$103,'Price Averages'!$E$4:$E$103, "FALSE"), E18) -> 144 | G18: 36 | H18: =IF(G18="", _xlfn.XLOOKUP(C18, 'Cost Averages'!$D$4:$D$103,'Cost Averages'!$E$4:$E$103, "FALSE"),G18) -> 36 | I18: =D18*F18 -> 1584 | J18: =D18*H18 -> 396 | K18: =I18-J18 -> 1188 | L18: Satisfied | M18: CG-137 | N18: Community & Government | O18: 12.796588 | P18: =CHAR(64+(YEAR(A18)-2014)) -> B | Q18: =YEAR(A18) -> 2016 | R18: =IF(P18=CHAR(64 + (YEAR(A18) - 2014)), 0, 1) -> 0
A19: 42615.366 | B19: 16-4442 | C19: P072 | D19: 12 | E19: 132 | F19: =IF(E19="",_xlfn.XLOOKUP(C19,'Price Averages'!$D$4:$D$103,'Price Averages'!$E$4:$E$103, "FALSE"), E19) -> 132 | G19: 44 | H19: =IF(G19="", _xlfn.XLOOKUP(C19, 'Cost Averages'!$D$4:$D$103,'Cost Averages'!$E$4:$E$103, "FALSE"),G19) -> 44 | I19: =D19*F19 -> 1584 | J19: =D19*H19 -> 528 | K19: =I19-J19 -> 1056 | L19: Dissatisfied | M19: FE-6892 | N19: Facilities & Services | O19: 14.817898 | P19: =CHAR(64+(YEAR(A19)-2014)) -> B | Q19: =YEAR(A19) -> 2016 | R19: =IF(P19=CHAR(64 + (YEAR(A19) - 2014)), 0, 1) -> 0
A20: 42614.684 | B20: 16-1985 | C20: P074 | D20: 13 | E20: 352 | F20: =IF(E20="",_xlfn.XLOOKUP(C20,'Price Averages'!$D$4:$D$103,'Price Averages'!$E$4:$E$103, "FALSE"), E20) -> 352 | G20: 88 | H20: =IF(G20="", _xlfn.XLOOKUP(C20, 'Cost Averages'!$D$4:$D$103,'Cost Averages'!$E$4:$E$103, "FALSE"),G20) -> 88 | I20: =D20*F20 -> 4576 | J20: =D20*H20 -> 1144 | K20: =I20-J20 -> 3432 | L20: Satisfied | M20: CP-2325 | N20: Corporate & Professional | O20: 11.701919 | P20: =CHAR(64+(YEAR(A20)-2014)) -> B | Q20: =YEAR(A20) -> 2016 | R20: =IF(P20=CHAR(64 + (YEAR(A20) - 2014)), 0, 1) -> 0
A21: 42709.937 | B21: 16-4839 | C21: P017 | D21: 16 | E21: 120 | F21: =IF(E21="",_xlfn.XLOOKUP(C21,'Price Averages'!$D$4:$D$103,'Price Averages'!$E$4:$E$103, "FALSE"), E21) -> 120 | G21: 30 | H21: =IF(G21="", _xlfn.XLOOKUP(C21, 'Cost Averages'!$D$4:$D$103,'Cost Averages'!$E$4:$E$103, "FALSE"),G21) -> 30 | I21: =D21*F21 -> 1920 | J21: =D21*H21 -> 480 | K21: =I21-J21 -> 1440 | L21: Satisfied | M21: CP-2926 | N21: Corporate & Professional | O21: 8.1743378 | P21: =CHAR(64+(YEAR(A21)-2014)) -> B | Q21: =YEAR(A21) -> 2016 | R21: =IF(P21=CHAR(64 + (YEAR(A21) - 2014)), 0, 1) -> 0
A22: 42676.558 | B22: 16-1558 | C22: P040 | D22: 16 | E22: 160 | F22: =IF(E22="",_xlfn.XLOOKUP(C22,'Price Averages'!$D$4:$D$103,'Price Averages'!$E$4:$E$103, "FALSE"), E22) -> 160 | G22: 80 | H22: =IF(G22="", _xlfn.XLOOKUP(C22, 'Cost Averages'!$D$4:$D$103,'Cost Averages'!$E$4:$E$103, "FALSE"),G22) -> 80 | I22: =D22*F22 -> 2560 | J22: =D22*H22 -> 1280 | K22: =I22-J22 -> 1280 | L22: Neither | M22: FE-6981 | N22: Facilities & Services | O22: 10.517826 | P22: =CHAR(64+(YEAR(A22)-2014)) -> B | Q22: =YEAR(A22) -> 2016 | R22: =IF(P22=CHAR(64 + (YEAR(A22) - 2014)), 0, 1) -> 0
A23: 42686.704 | B23: 16-4049 | C23: P038 | D23: 18 | E23: 240 | F23: =IF(E23="",_xlfn.XLOOKUP(C23,'Price Averages'!$D$4:$D$103,'Price Averages'!$E$4:$E$103, "FALSE"), E23) -> 240 | G23: 80 | H23: =IF(G23="", _xlfn.XLOOKUP(C23, 'Cost Averages'!$D$4:$D$103,'Cost Averages'!$E$4:$E$103, "FALSE"),G23) -> 80 | I23: =D23*F23 -> 4320 | J23: =D23*H23 -> 1440 | K23: =I23-J23 -> 2880 | L23: Neither | M23: SR-9468 | N23: Sports & Recreation | O23: 10.010333 | P23: =CHAR(64+(YEAR(A23)-2014)) -> B | Q23: =YEAR(A23) -> 2016 | R23: =IF(P23=CHAR(64 + (YEAR(A23) - 2014)), 0, 1) -> 0
A24: 42485.261 | B24: 16-3871 | C24: P056 | D24: 18 | F24: =IF(E24="",_xlfn.XLOOKUP(C24,'Price Averages'!$D$4:$D$103,'Price Averages'!$E$4:$E$103, "FALSE"), E24) -> 72 | G24: 36 | H24: =IF(G24="", _xlfn.XLOOKUP(C24, 'Cost Averages'!$D$4:$D$103,'Cost Averages'!$E$4:$E$103, "FALSE"),G24) -> 36 | I24: =D24*F24 -> 1296 | J24: =D24*H24 -> 648 | K24: =I24-J24 -> 648 | L24: Dissatisfied | M24: CT-3881 | N24: Creative & Technology | O24: 13.459801 | P24: =CHAR(64+(YEAR(A24)-2014)) -> B | Q24: =YEAR(A24) -> 2016 | R24: =IF(P24=CHAR(64 + (YEAR(A24) - 2014)), 0, 1) -> 0
A25: 42641.299 | B25: 16-1896 | C25: P005 | D25: 20 | F25: =IF(E25="",_xlfn.XLOOKUP(C25,'Price Averages'!$D$4:$D$103,'Price Averages'!$E$4:$E$103, "FALSE"), E25) -> 76 | G25: 19 | H25: =IF(G25="", _xlfn.XLOOKUP(C25, 'Cost Averages'!$D$4:$D$103,'Cost Averages'!$E$4:$E$103, "FALSE"),G25) -> 19 | I25: =D25*F25 -> 1520 | J25: =D25*H25 -> 380 | K25: =I25-J25 -> 1140 | L25: Neither | M25: CT-3174 | N25: Creative & Technology | O25: 15.187892 | P25: =CHAR(64+(YEAR(A25)-2014)) -> B | Q25: =YEAR(A25) -> 2016 | R25: =IF(P25=CHAR(64 + (YEAR(A25) - 2014)), 0, 1) -> 0
A26: 42720.244 | B26: 16-1417 | C26: P081 | D26: 20 | E26: 50 | F26: =IF(E26="",_xlfn.XLOOKUP(C26,'Price Averages'!$D$4:$D$103,'Price Averages'!$E$4:$E$103, "FALSE"), E26) -> 50 | H26: =IF(G26="", _xlfn.XLOOKUP(C26, 'Cost Averages'!$D$4:$D$103,'Cost Averages'!$E$4:$E$103, "FALSE"),G26) -> 25 | I26: =D26*F26 -> 1000 | J26: =D26*H26 -> 500 | K26: =I26-J26 -> 500 | L26: Neither | M26: CP-2629 | N26: Corporate & Professional | O26: 10.411813 | P26: =CHAR(64+(YEAR(A26)-2014)) -> B | Q26: =YEAR(A26) -> 2016 | R26: =IF(P26=CHAR(64 + (YEAR(A26) - 2014)), 0, 1) -> 0
A27: 43080.739 | B27: 17-2199 | C27: P009 | D27: 1 | E27: 255 | F27: =IF(E27="",_xlfn.XLOOKUP(C27,'Price Averages'!$D$4:$D$103,'Price Averages'!$E$4:$E$103, "FALSE"), E27) -> 255 | G27: 85 | H27: =IF(G27="", _xlfn.XLOOKUP(C27, 'Cost Averages'!$D$4:$D$103,'Cost Averages'!$E$4:$E$103, "FALSE"),G27) -> 85 | I27: =D27*F27 -> 255 | J27: =D27*H27 -> 85 | K27: =I27-J27 -> 170 | L27: Neither | M27: FE-629 | N27: Facilities & Services | O27: 11.311041 | P27: =CHAR(64+(YEAR(A27)-2014)) -> C | Q27: =YEAR(A27) -> 2017 | R27: =IF(P27=CHAR(64 + (YEAR(A27) - 2014)), 0, 1) -> 0
A28: 43008.135 | B28: 17-2606 | C28: P034 | D28: 1 | E28: 114 | F28: =IF(E28="",_xlfn.XLOOKUP(C28,'Price Averages'!$D$4:$D$103,'Price Averages'!$E$4:$E$103, "FALSE"), E28) -> 114 | G28: 57 | H28: =IF(G28="", _xlfn.XLOOKUP(C28, 'Cost Averages'!$D$4:$D$103,'Cost Averages'!$E$4:$E$103, "FALSE"),G28) -> 57 | I28: =D28*F28 -> 114 | J28: =D28*H28 -> 57 | K28: =I28-J28 -> 57 | L28: Neither | M28: CT-3471 | N28: Creative & Technology | O28: 13.537351 | P28: =CHAR(64+(YEAR(A28)-2014)) -> C | Q28: =YEAR(A28) -> 2017 | R28: =IF(P28=CHAR(64 + (YEAR(A28) - 2014)), 0, 1) -> 0
A29: 42990.559 | B29: 17-3371 | C29: P063 | D29: 1 | E29: 261 | F29: =IF(E29="",_xlfn.XLOOKUP(C29,'Price Averages'!$D$4:$D$103,'Price Averages'!$E$4:$E$103, "FALSE"), E29) -> 261 | H29: =IF(G29="", _xlfn.XLOOKUP(C29, 'Cost Averages'!$D$4:$D$103,'Cost Averages'!$E$4:$E$103, "FALSE"),G29) -> 87 | I29: =D29*F29 -> 261 | J29: =D29*H29 -> 87 | K29: =I29-J29 -> 174 | L29: Satisfied | M29: HS-7291 | N29: Healthcare & Safety | O29: 10.42743 | P29: =CHAR(64+(YEAR(A29)-2014)) -> C | Q29: =YEAR(A29) -> 2017 | R29: =IF(P29=CHAR(64 + (YEAR(A29) - 2014)), 0, 1) -> 0
A30: 43028.202 | B30: 17-3360 | C30: P090 | D30: 1 | E30: 57 | F30: =IF(E30="",_xlfn.XLOOKUP(C30,'Price Averages'!$D$4:$D$103,'Price Averages'!$E$4:$E$103, "FALSE"), E30) -> 57 | G30: 19 | H30: =IF(G30="", _xlfn.XLOOKUP(C30, 'Cost Averages'!$D$4:$D$103,'Cost Averages'!$E$4:$E$103, "FALSE"),G30) -> 19 | I30: =D30*F30 -> 57 | J30: =D30*H30 -> 19 | K30: =I30-J30 -> 38 | L30: Satisfied | M30: HS-7827 | N30: Healthcare & Safety | O30: 9.3014286 | P30: =CHAR(64+(YEAR(A30)-2014)) -> C | Q30: =YEAR(A30) -> 2017 | R30: =IF(P30=CHAR(64 + (YEAR(A30) - 2014)), 0, 1) -> 0
A31: 42947.152 | B31: 17-3225 | C31: P100 | D31: 1 | E31: 46 | F31: =IF(E31="",_xlfn.XLOOKUP(C31,'Price Averages'!$D$4:$D$103,'Price Averages'!$E$4:$E$103, "FALSE"), E31) -> 46 | G31: 23 | H31: =IF(G31="", _xlfn.XLOOKUP(C31, 'Cost Averages'!$D$4:$D$103,'Cost Averages'!$E$4:$E$103, "FALSE"),G31) -> 23 | I31: =D31*F31 -> 46 | J31: =D31*H31 -> 23 | K31: =I31-J31 -> 23 | L31: Neither | M31: EE-40 | N31: Education | O31: 12.396052 | P31: =CHAR(64+(YEAR(A31)-2014)) -> C | Q31: =YEAR(A31) -> 2017 | R31: =IF(P31=CHAR(64 + (YEAR(A31) - 2014)), 0, 1) -> 0
A32: 42799.219 | B32: 17-1285 | C32: P011 | D32: 2 | E32: 264 | F32: =IF(E32="",_xlfn.XLOOKUP(C32,'Price Averages'!$D$4:$D$103,'Price Averages'!$E$4:$E$103, "FALSE"), E32) -> 264 | G32: 88 | H32: =IF(G32="", _xlfn.XLOOKUP(C32, 'Cost Averages'!$D$4:$D$103,'Cost Averages'!$E$4:$E$103, "FALSE"),G32) -> 88 | I32: =D32*F32 -> 528 | J32: =D32*H32 -> 176 | K32: =I32-J32 -> 352 | L32: Satisfied | M32: CP-2251 | N32: Corporate & Professional | O32: 11.003497 | P32: =CHAR(64+(YEAR(A32)-2014)) -> C | Q32: =YEAR(A32) -> 2017 | R32: =IF(P32=CHAR(64 + (YEAR(A32) - 2014)), 0, 1) -> 0
A33: 42889.125 | B33: 17-4153 | C33: P027 | D33: 2 | E33: 140 | F33: =IF(E33="",_xlfn.XLOOKUP(C33,'Price Averages'!$D$4:$D$103,'Price Averages'!$E$4:$E$103, "FALSE"), E33) -> 140 | G33: 70 | H33: =IF(G33="", _xlfn.XLOOKUP(C33, 'Cost Averages'!$D$4:$D$103,'Cost Averages'!$E$4:$E$103, "FALSE"),G33) -> 70 | I33: =D33*F33 -> 280 | J33: =D33*H33 -> 140 | K33: =I33-J33 -> 140 | L33: Dissatisfied | M33: CT-3920 | N33: Creative & Technology | O33: 14.661477 | P33: =CHAR(64+(YEAR(A33)-2014)) -> C | Q33: =YEAR(A33) -> 2017 | R33: =IF(P33=CHAR(64 + (YEAR(A33) - 2014)), 0, 1) -> 0
A34: 42968.905 | B34: 17-3578 | C34: P040 | D34: 2 | E34: 160 | F34: =IF(E34="",_xlfn.XLOOKUP(C34,'Price Averages'!$D$4:$D$103,'Price Averages'!$E$4:$E$103, "FALSE"), E34) -> 160 | G34: 80 | H34: =IF(G34="", _xlfn.XLOOKUP(C34, 'Cost Averages'!$D$4:$D$103,'Cost Averages'!$E$4:$E$103, "FALSE"),G34) -> 80 | I34: =D34*F34 -> 320 | J34: =D34*H34 -> 160 | K34: =I34-J34 -> 160 | L34: Neither | M34: FE-6631 | N34: Facilities & Services | O34: 8.1352386 | P34: =CHAR(64+(YEAR(A34)-2014)) -> C | Q34: =YEAR(A34) -> 2017 | R34: =IF(P34=CHAR(64 + (YEAR(A34) - 2014)), 0, 1) -> 0
A35: 43066.994 | B35: 17-2601 | C35: P048 | D35: 2 | F35: =IF(E35="",_xlfn.XLOOKUP(C35,'Price Averages'!$D$4:$D$103,'Price Averages'!$E$4:$E$103, "FALSE"), E35) -> 252 | H35: =IF(G35="", _xlfn.XLOOKUP(C35, 'Cost Averages'!$D$4:$D$103,'Cost Averages'!$E$4:$E$103, "FALSE"),G35) -> 63 | I35: =D35*F35 -> 504 | J35: =D35*H35 -> 126 | K35: =I35-J35 -> 378 | L35: Satisfied | M35: EE-4649 | N35: Education | O35: 13.392447 | P35: =CHAR(64+(YEAR(A35)-2014)) -> C | Q35: =YEAR(A35) -> 2017 | R35: =IF(P35=CHAR(64 + (YEAR(A35) - 2014)), 0, 1) -> 0
A36: 43038.144 | B36: 17-1307 | C36: P088 | D36: 2 | E36: 192 | F36: =IF(E36="",_xlfn.XLOOKUP(C36,'Price Averages'!$D$4:$D$103,'Price Averages'!$E$4:$E$103, "FALSE"), E36) -> 192 | G36: 96 | H36: =IF(G36="", _xlfn.XLOOKUP(C36, 'Cost Averages'!$D$4:$D$103,'Cost Averages'!$E$4:$E$103, "FALSE"),G36) -> 96 | I36: =D36*F36 -> 384 | J36: =D36*H36 -> 192 | K36: =I36-J36 -> 192 | L36: Neither | M36: CT-3796 | N36: Creative & Technology | O36: 15.207986 | P36: =CHAR(64+(YEAR(A36)-2014)) -> C | Q36: =YEAR(A36) -> 2017 | R36: =IF(P36=CHAR(64 + (YEAR(A36) - 2014)), 0, 1) -> 0
A37: 43072.093 | B37: 17-2741 | C37: P013 | D37: 3 | F37: =IF(E37="",_xlfn.XLOOKUP(C37,'Price Averages'!$D$4:$D$103,'Price Averages'!$E$4:$E$103, "FALSE"), E37) -> 58 | G37: 29 | H37: =IF(G37="", _xlfn.XLOOKUP(C37, 'Cost Averages'!$D$4:$D$103,'Cost Averages'!$E$4:$E$103, "FALSE"),G37) -> 29 | I37: =D37*F37 -> 174 | J37: =D37*H37 -> 87 | K37: =I37-J37 -> 87 | L37: Satisfied | M37: EE-4361 | N37: Education | O37: 14.760829 | P37: =CHAR(64+(YEAR(A37)-2014)) -> C | Q37: =YEAR(A37) -> 2017 | R37: =IF(P37=CHAR(64 + (YEAR(A37) - 2014)), 0, 1) -> 0
A38: 43007.042 | B38: 17-1266 | C38: P029 | D38: 3 | F38: =IF(E38="",_xlfn.XLOOKUP(C38,'Price Averages'!$D$4:$D$103,'Price Averages'!$E$4:$E$103, "FALSE"), E38) -> 300 | G38: 75 | H38: =IF(G38="", _xlfn.XLOOKUP(C38, 'Cost Averages'!$D$4:$D$103,'Cost Averages'!$E$4:$E$103, "FALSE"),G38) -> 75 | I38: =D38*F38 -> 900 | J38: =D38*H38 -> 225 | K38: =I38-J38 -> 675 | L38: Dissatisfied | M38: CT-3955 | N38: Creative & Technology | O38: 11.130819 | P38: =CHAR(64+(YEAR(A38)-2014)) -> C | Q38: =YEAR(A38) -> 2017 | R38: =IF(P38=CHAR(64 + (YEAR(A38) - 2014)), 0, 1) -> 0
A39: 43074.481 | B39: 17-4852 | C39: P034 | D39: 3 | F39: =IF(E39="",_xlfn.XLOOKUP(C39,'Price Averages'!$D$4:$D$103,'Price Averages'!$E$4:$E$103, "FALSE"), E39) -> 114 | G39: 57 | H39: =IF(G39="", _xlfn.XLOOKUP(C39, 'Cost Averages'!$D$4:$D$103,'Cost Averages'!$E$4:$E$103, "FALSE"),G39) -> 57 | I39: =D39*F39 -> 342 | J39: =D39*H39 -> 171 | K39: =I39-J39 -> 171 | L39: Satisfied | M39: EE-4140 | N39: Education | O39: 11.710936 | P39: =CHAR(64+(YEAR(A39)-2014)) -> C | Q39: =YEAR(A39) -> 2017 | R39: =IF(P39=CHAR(64 + (YEAR(A39) - 2014)), 0, 1) -> 0
A40: 43069.61 | B40: 17-3345 | C40: P064 | D40: 3 | E40: 231 | F40: =IF(E40="",_xlfn.XLOOKUP(C40,'Price Averages'!$D$4:$D$103,'Price Averages'!$E$4:$E$103, "FALSE"), E40) -> 231 | G40: 77 | H40: =IF(G40="", _xlfn.XLOOKUP(C40, 'Cost Averages'!$D$4:$D$103,'Cost Averages'!$E$4:$E$103, "FALSE"),G40) -> 77 | I40: =D40*F40 -> 693 | J40: =D40*H40 -> 231 | K40: =I40-J40 -> 462 | L40: Dissatisfied | M40: CG-142 | N40: Community & Government | O40: 14.412866 | P40: =CHAR(64+(YEAR(A40)-2014)) -> C | Q40: =YEAR(A40) -> 2017 | R40: =IF(P40=CHAR(64 + (YEAR(A40) - 2014)), 0, 1) -> 0
A41: 42967.742 | B41: 17-3050 | C41: P094 | D41: 3 | E41: 80 | F41: =IF(E41="",_xlfn.XLOOKUP(C41,'Price Averages'!$D$4:$D$103,'Price Averages'!$E$4:$E$103, "FALSE"), E41) -> 80 | G41: 20 | H41: =IF(G41="", _xlfn.XLOOKUP(C41, 'Cost Averages'!$D$4:$D$103,'Cost Averages'!$E$4:$E$103, "FALSE"),G41) -> 20 | I41: =D41*F41 -> 240 | J41: =D41*H41 -> 60 | K41: =I41-J41 -> 180 | L41: Neither | M41: FE-6404 | N41: Facilities & Services | O41: 11.226612 | P41: =CHAR(64+(YEAR(A41)-2014)) -> C | Q41: =YEAR(A41) -> 2017 | R41: =IF(P41=CHAR(64 + (YEAR(A41) - 2014)), 0, 1) -> 0
A42: 42851.022 | B42: 17-1467 | C42: P099 | D42: 3 | E42: 132 | F42: =IF(E42="",_xlfn.XLOOKUP(C42,'Price Averages'!$D$4:$D$103,'Price Averages'!$E$4:$E$103, "FALSE"), E42) -> 132 | G42: 33 | H42: =IF(G42="", _xlfn.XLOOKUP(C42, 'Cost Averages'!$D$4:$D$103,'Cost Averages'!$E$4:$E$103, "FALSE"),G42) -> 33 | I42: =D42*F42 -> 396 | J42: =D42*H42 -> 99 | K42: =I42-J42 -> 297 | L42: Neither | M42: FE-6260 | N42: Facilities & Services | O42: 11.289144 | P42: =CHAR(64+(YEAR(A42)-2014)) -> C | Q42: =YEAR(A42) -> 2017 | R42: =IF(P42=CHAR(64 + (YEAR(A42) - 2014)), 0, 1) -> 0
A43: 43073.676 | B43: 17-3471 | C43: P047 | D43: 4 | E43: 72 | F43: =IF(E43="",_xlfn.XLOOKUP(C43,'Price Averages'!$D$4:$D$103,'Price Averages'!$E$4:$E$103, "FALSE"), E43) -> 72 | G43: 36 | H43: =IF(G43="", _xlfn.XLOOKUP(C43, 'Cost Averages'!$D$4:$D$103,'Cost Averages'!$E$4:$E$103, "FALSE"),G43) -> 36 | I43: =D43*F43 -> 288 | J43: =D43*H43 -> 144 | K43: =I43-J43 -> 144 | L43: Neither | M43: EE-4858 | N43: Education | O43: 12.456741 | P43: =CHAR(64+(YEAR(A43)-2014)) -> C | Q43: =YEAR(A43) -> 2017 | R43: =IF(P43=CHAR(64 + (YEAR(A43) - 2014)), 0, 1) -> 0
A44: 43052.497 | B44: 17-4776 | C44: P007 | D44: 5 | E44: 225 | F44: =IF(E44="",_xlfn.XLOOKUP(C44,'Price Averages'!$D$4:$D$103,'Price Averages'!$E$4:$E$103, "FALSE"), E44) -> 225 | G44: 75 | H44: =IF(G44="", _xlfn.XLOOKUP(C44, 'Cost Averages'!$D$4:$D$103,'Cost Averages'!$E$4:$E$103, "FALSE"),G44) -> 75 | I44: =D44*F44 -> 1125 | J44: =D44*H44 -> 375 | K44: =I44-J44 -> 750 | L44: Neither | M44: CG-1264 | N44: Community & Government | O44: 13.811877 | P44: =CHAR(64+(YEAR(A44)-2014)) -> C | Q44: =YEAR(A44) -> 2017 | R44: =IF(P44=CHAR(64 + (YEAR(A44) - 2014)), 0, 1) -> 0
A45: 42987.056 | B45: 17-4787 | C45: P040 | D45: 5 | E45: 160 | F45: =IF(E45="",_xlfn.XLOOKUP(C45,'Price Averages'!$D$4:$D$103,'Price Averages'!$E$4:$E$103, "FALSE"), E45) -> 160 | G45: 80 | H45: =IF(G45="", _xlfn.XLOOKUP(C45, 'Cost Averages'!$D$4:$D$103,'Cost Averages'!$E$4:$E$103, "FALSE"),G45) -> 80 | I45: =D45*F45 -> 800 | J45: =D45*H45 -> 400 | K45: =I45-J45 -> 400 | L45: Dissatisfied | M45: CG-1580 | N45: Community & Government | O45: 8.8169309 | P45: =CHAR(64+(YEAR(A45)-2014)) -> C | Q45: =YEAR(A45) -> 2017 | R45: =IF(P45=CHAR(64 + (YEAR(A45) - 2014)), 0, 1) -> 0
A46: 43085.794 | B46: 17-2359 | C46: P060 | D46: 5 | E46: 300 | F46: =IF(E46="",_xlfn.XLOOKUP(C46,'Price Averages'!$D$4:$D$103,'Price Averages'!$E$4:$E$103, "FALSE"), E46) -> 300 | G46: 75 | H46: =IF(G46="", _xlfn.XLOOKUP(C46, 'Cost Averages'!$D$4:$D$103,'Cost Averages'!$E$4:$E$103, "FALSE"),G46) -> 75 | I46: =D46*F46 -> 1500 | J46: =D46*H46 -> 375 | K46: =I46-J46 -> 1125 | L46: Neither | M46: SR-9320 | N46: Sports & Recreation | O46: 12.133499 | P46: =CHAR(64+(YEAR(A46)-2014)) -> C | Q46: =YEAR(A46) -> 2017 | R46: =IF(P46=CHAR(64 + (YEAR(A46) - 2014)), 0, 1) -> 0
A47: 43030.842 | B47: 17-4621 | C47: P061 | D47: 5 | E47: 264 | F47: =IF(E47="",_xlfn.XLOOKUP(C47,'Price Averages'!$D$4:$D$103,'Price Averages'!$E$4:$E$103, "FALSE"), E47) -> 264 | H47: =IF(G47="", _xlfn.XLOOKUP(C47, 'Cost Averages'!$D$4:$D$103,'Cost Averages'!$E$4:$E$103, "FALSE"),G47) -> 88 | I47: =D47*F47 -> 1320 | J47: =D47*H47 -> 440 | K47: =I47-J47 -> 880 | L47: Neither | M47: FE-6254 | N47: Facilities & Services | O47: 11.961762 | P47: =CHAR(64+(YEAR(A47)-2014)) -> C | Q47: =YEAR(A47) -> 2017 | R47: =IF(P47=CHAR(64 + (YEAR(A47) - 2014)), 0, 1) -> 0
A48: 43068.002 | B48: 17-1449 | C48: P098 | D48: 5 | E48: 201 | F48: =IF(E48="",_xlfn.XLOOKUP(C48,'Price Averages'!$D$4:$D$103,'Price Averages'!$E$4:$E$103, "FALSE"), E48) -> 201 | H48: =IF(G48="", _xlfn.XLOOKUP(C48, 'Cost Averages'!$D$4:$D$103,'Cost Averages'!$E$4:$E$103, "FALSE"),G48) -> 67 | I48: =D48*F48 -> 1005 | J48: =D48*H48 -> 335 | K48: =I48-J48 -> 670 | L48: Satisfied | M48: FE-6410 | N48: Facilities & Services | O48: 13.717776 | P48: =CHAR(64+(YEAR(A48)-2014)) -> C | Q48: =YEAR(A48) -> 2017 | R48: =IF(P48=CHAR(64 + (YEAR(A48) - 2014)), 0, 1) -> 0
A49: 43061.961 | B49: 17-2765 | C49: P004 | D49: 6 | F49: =IF(E49="",_xlfn.XLOOKUP(C49,'Price Averages'!$D$4:$D$103,'Price Averages'!$E$4:$E$103, "FALSE"), E49) -> 189 | G49: 63 | H49: =IF(G49="", _xlfn.XLOOKUP(C49, 'Cost Averages'!$D$4:$D$103,'Cost Averages'!$E$4:$E$103, "FALSE"),G49) -> 63 | I49: =D49*F49 -> 1134 | J49: =D49*H49 -> 378 | K49: =I49-J49 -> 756 | L49: Satisfied | M49: CG-1804 | N49: Community & Government | O49: 12.045339 | P49: =CHAR(64+(YEAR(A49)-2014)) -> C | Q49: =YEAR(A49) -> 2017 | R49: =IF(P49=CHAR(64 + (YEAR(A49) - 2014)), 0, 1) -> 0
A50: 42980.801 | B50: 17-2114 | C50: P008 | D50: 6 | E50: 225 | F50: =IF(E50="",_xlfn.XLOOKUP(C50,'Price Averages'!$D$4:$D$103,'Price Averages'!$E$4:$E$103, "FALSE"), E50) -> 225 | G50: 75 | H50: =IF(G50="", _xlfn.XLOOKUP(C50, 'Cost Averages'!$D$4:$D$103,'Cost Averages'!$E$4:$E$103, "FALSE"),G50) -> 75 | I50: =D50*F50 -> 1350 | J50: =D50*H50 -> 450 | K50: =I50-J50 -> 900 | L50: Neither | M50: FE-6482 | N50: Facilities & Services | O50: 11.769294 | P50: =CHAR(64+(YEAR(A50)-2014)) -> C | Q50: =YEAR(A50) -> 2017 | R50: =IF(P50=CHAR(64 + (YEAR(A50) - 2014)), 0, 1) -> 0
A51: 43017.553 | B51: 17-1421 | C51: P010 | D51: 6 | E51: 144 | F51: =IF(E51="",_xlfn.XLOOKUP(C51,'Price Averages'!$D$4:$D$103,'Price Averages'!$E$4:$E$103, "FALSE"), E51) -> 144 | G51: 36 | H51: =IF(G51="", _xlfn.XLOOKUP(C51, 'Cost Averages'!$D$4:$D$103,'Cost Averages'!$E$4:$E$103, "FALSE"),G51) -> 36 | I51: =D51*F51 -> 864 | J51: =D51*H51 -> 216 | K51: =I51-J51 -> 648 | L51: Neither | M51: CP-2380 | N51: Corporate & Professional | O51: 15.478388 | P51: =CHAR(64+(YEAR(A51)-2014)) -> C | Q51: =YEAR(A51) -> 2017 | R51: =IF(P51=CHAR(64 + (YEAR(A51) - 2014)), 0, 1) -> 0
A52: 42923.53 | B52: 17-3969 | C52: P019 | D52: 6 | F52: =IF(E52="",_xlfn.XLOOKUP(C52,'Price Averages'!$D$4:$D$103,'Price Averages'!$E$4:$E$103, "FALSE"), E52) -> 308 | G52: 77 | H52: =IF(G52="", _xlfn.XLOOKUP(C52, 'Cost Averages'!$D$4:$D$103,'Cost Averages'!$E$4:$E$103, "FALSE"),G52) -> 77 | I52: =D52*F52 -> 1848 | J52: =D52*H52 -> 462 | K52: =I52-J52 -> 1386 | L52: Neither | M52: CP-2862 | N52: Corporate & Professional | O52: 14.370283 | P52: =CHAR(64+(YEAR(A52)-2014)) -> C | Q52: =YEAR(A52) -> 2017 | R52: =IF(P52=CHAR(64 + (YEAR(A52) - 2014)), 0, 1) -> 0
A53: 42960.917 | B53: 17-3732 | C53: P031 | D53: 6 | E53: 146 | F53: =IF(E53="",_xlfn.XLOOKUP(C53,'Price Averages'!$D$4:$D$103,'Price Averages'!$E$4:$E$103, "FALSE"), E53) -> 146 | G53: 73 | H53: =IF(G53="", _xlfn.XLOOKUP(C53, 'Cost Averages'!$D$4:$D$103,'Cost Averages'!$E$4:$E$103, "FALSE"),G53) -> 73 | I53: =D53*F53 -> 876 | J53: =D53*H53 -> 438 | K53: =I53-J53 -> 438 | L53: Neither | M53: CG-1367 | N53: Community & Government | O53: 15.604305 | P53: =CHAR(64+(YEAR(A53)-2014)) -> C | Q53: =YEAR(A53) -> 2017 | R53: =IF(P53=CHAR(64 + (YEAR(A53) - 2014)), 0, 1) -> 0
A54: 43060.662 | B54: 17-4293 | C54: P040 | D54: 6 | E54: 160 | F54: =IF(E54="",_xlfn.XLOOKUP(C54,'Price Averages'!$D$4:$D$103,'Price Averages'!$E$4:$E$103, "FALSE"), E54) -> 160 | G54: 80 | H54: =IF(G54="", _xlfn.XLOOKUP(C54, 'Cost Averages'!$D$4:$D$103,'Cost Averages'!$E$4:$E$103, "FALSE"),G54) -> 80 | I54: =D54*F54 -> 960 | J54: =D54*H54 -> 480 | K54: =I54-J54 -> 480 | L54: Satisfied | M54: FE-6482 | N54: Facilities & Services | O54: 11.769294 | P54: =CHAR(64+(YEAR(A54)-2014)) -> C | Q54: =YEAR(A54) -> 2017 | R54: =IF(P54=CHAR(64 + (YEAR(A54) - 2014)), 0, 1) -> 0
A55: 43081.342 | B55: 17-2222 | C55: P063 | D55: 6 | E55: 261 | F55: =IF(E55="",_xlfn.XLOOKUP(C55,'Price Averages'!$D$4:$D$103,'Price Averages'!$E$4:$E$103, "FALSE"), E55) -> 261 | G55: 87 | H55: =IF(G55="", _xlfn.XLOOKUP(C55, 'Cost Averages'!$D$4:$D$103,'Cost Averages'!$E$4:$E$103, "FALSE"),G55) -> 87 | I55: =D55*F55 -> 1566 | J55: =D55*H55 -> 522 | K55: =I55-J55 -> 1044 | L55: Dissatisfied | M55: CT-3497 | N55: Creative & Technology | O55: 11.783468 | P55: =CHAR(64+(YEAR(A55)-2014)) -> C | Q55: =YEAR(A55) -> 2017 | R55: =IF(P55=CHAR(64 + (YEAR(A55) - 2014)), 0, 1) -> 0
A56: 42839.351 | B56: 17-2101 | C56: P065 | D56: 6 | E56: 50 | F56: =IF(E56="",_xlfn.XLOOKUP(C56,'Price Averages'!$D$4:$D$103,'Price Averages'!$E$4:$E$103, "FALSE"), E56) -> 50 | G56: 25 | H56: =IF(G56="", _xlfn.XLOOKUP(C56, 'Cost Averages'!$D$4:$D$103,'Cost Averages'!$E$4:$E$103, "FALSE"),G56) -> 25 | I56: =D56*F56 -> 300 | J56: =D56*H56 -> 150 | K56: =I56-J56 -> 150 | L56: Neither | M56: CT-3229 | N56: Creative & Technology | O56: 15.770847 | P56: =CHAR(64+(YEAR(A56)-2014)) -> C | Q56: =YEAR(A56) -> 2017 | R56: =IF(P56=CHAR(64 + (YEAR(A56) - 2014)), 0, 1) -> 0
A57: 42892.376 | B57: 17-4027 | C57: P071 | D57: 6 | E57: 210 | F57: =IF(E57="",_xlfn.XLOOKUP(C57,'Price Averages'!$D$4:$D$103,'Price Averages'!$E$4:$E$103, "FALSE"), E57) -> 210 | G57: 70 | H57: =IF(G57="", _xlfn.XLOOKUP(C57, 'Cost Averages'!$D$4:$D$103,'Cost Averages'!$E$4:$E$103, "FALSE"),G57) -> 70 | I57: =D57*F57 -> 1260 | J57: =D57*H57 -> 420 | K57: =I57-J57 -> 840 | L57: Neither | M57: CT-3796 | N57: Creative & Technology | O57: 15.207986 | P57: =CHAR(64+(YEAR(A57)-2014)) -> C | Q57: =YEAR(A57) -> 2017 | R57: =IF(P57=CHAR(64 + (YEAR(A57) - 2014)), 0, 1) -> 0
A58: 42760.795 | B58: 17-2227 | C58: P078 | D58: 6 | E58: 225 | F58: =IF(E58="",_xlfn.XLOOKUP(C58,'Price Averages'!$D$4:$D$103,'Price Averages'!$E$4:$E$103, "FALSE"), E58) -> 225 | G58: 75 | H58: =IF(G58="", _xlfn.XLOOKUP(C58, 'Cost Averages'!$D$4:$D$103,'Cost Averages'!$E$4:$E$103, "FALSE"),G58) -> 75 | I58: =D58*F58 -> 1350 | J58: =D58*H58 -> 450 | K58: =I58-J58 -> 900 | L58: Satisfied | M58: HS-7291 | N58: Healthcare & Safety | O58: 10.42743 | P58: =CHAR(64+(YEAR(A58)-2014)) -> C | Q58: =YEAR(A58) -> 2017 | R58: =IF(P58=CHAR(64 + (YEAR(A58) - 2014)), 0, 1) -> 0
A59: 43085.324 | B59: 17-4367 | C59: P081 | D59: 6 | F59: =IF(E59="",_xlfn.XLOOKUP(C59,'Price Averages'!$D$4:$D$103,'Price Averages'!$E$4:$E$103, "FALSE"), E59) -> 50 | G59: 25 | H59: =IF(G59="", _xlfn.XLOOKUP(C59, 'Cost Averages'!$D$4:$D$103,'Cost Averages'!$E$4:$E$103, "FALSE"),G59) -> 25 | I59: =D59*F59 -> 300 | J59: =D59*H59 -> 150 | K59: =I59-J59 -> 150 | L59: Neither | M59: CG-1535 | N59: Community & Government | O59: 9.8792825 | P59: =CHAR(64+(YEAR(A59)-2014)) -> C | Q59: =YEAR(A59) -> 2017 | R59: =IF(P59=CHAR(64 + (YEAR(A59) - 2014)), 0, 1) -> 0
A60: 43030.11 | B60: 17-2213 | C60: P087 | D60: 6 | E60: 176 | F60: =IF(E60="",_xlfn.XLOOKUP(C60,'Price Averages'!$D$4:$D$103,'Price Averages'!$E$4:$E$103, "FALSE"), E60) -> 176 | G60: 88 | H60: =IF(G60="", _xlfn.XLOOKUP(C60, 'Cost Averages'!$D$4:$D$103,'Cost Averages'!$E$4:$E$103, "FALSE"),G60) -> 88 | I60: =D60*F60 -> 1056 | J60: =D60*H60 -> 528 | K60: =I60-J60 -> 528 | L60: Dissatisfied | M60: CG-1416 | N60: Community & Government | O60: 12.155895 | P60: =CHAR(64+(YEAR(A60)-2014)) -> C | Q60: =YEAR(A60) -> 2017 | R60: =IF(P60=CHAR(64 + (YEAR(A60) - 2014)), 0, 1) -> 0
A61: 43100.175 | B61: 17-2796 | C61: P092 | D61: 6 | E61: 124 | F61: =IF(E61="",_xlfn.XLOOKUP(C61,'Price Averages'!$D$4:$D$103,'Price Averages'!$E$4:$E$103, "FALSE"), E61) -> 124 | G61: 62 | H61: =IF(G61="", _xlfn.XLOOKUP(C61, 'Cost Averages'!$D$4:$D$103,'Cost Averages'!$E$4:$E$103, "FALSE"),G61) -> 62 | I61: =D61*F61 -> 744 | J61: =D61*H61 -> 372 | K61: =I61-J61 -> 372 | L61: Dissatisfied | M61: CG-1269 | N61: Community & Government | O61: 10.81327 | P61: =CHAR(64+(YEAR(A61)-2014)) -> C | Q61: =YEAR(A61) -> 2017 | R61: =IF(P61=CHAR(64 + (YEAR(A61) - 2014)), 0, 1) -> 0
A62: 43088.828 | B62: 17-3291 | C62: P096 | D62: 6 | E62: 144 | F62: =IF(E62="",_xlfn.XLOOKUP(C62,'Price Averages'!$D$4:$D$103,'Price Averages'!$E$4:$E$103, "FALSE"), E62) -> 144 | G62: 48 | H62: =IF(G62="", _xlfn.XLOOKUP(C62, 'Cost Averages'!$D$4:$D$103,'Cost Averages'!$E$4:$E$103, "FALSE"),G62) -> 48 | I62: =D62*F62 -> 864 | J62: =D62*H62 -> 288 | K62: =I62-J62 -> 576 | L62: Neither | M62: HS-7291 | N62: Healthcare & Safety | O62: 10.42743 | P62: =CHAR(64+(YEAR(A62)-2014)) -> C | Q62: =YEAR(A62) -> 2017 | R62: =IF(P62=CHAR(64 + (YEAR(A62) - 2014)), 0, 1) -> 0
A63: 42995.68 | B63: 17-4912 | C63: P100 | D63: 6 | F63: =IF(E63="",_xlfn.XLOOKUP(C63,'Price Averages'!$D$4:$D$103,'Price Averages'!$E$4:$E$103, "FALSE"), E63) -> 46 | G63: 23 | H63: =IF(G63="", _xlfn.XLOOKUP(C63, 'Cost Averages'!$D$4:$D$103,'Cost Averages'!$E$4:$E$103, "FALSE"),G63) -> 23 | I63: =D63*F63 -> 276 | J63: =D63*H63 -> 138 | K63: =I63-J63 -> 138 | L63: Satisfied | M63: SR-9981 | N63: Sports & Recreation | O63: 10.037136 | P63: =CHAR(64+(YEAR(A63)-2014)) -> C | Q63: =YEAR(A63) -> 2017 | R63: =IF(P63=CHAR(64 + (YEAR(A63) - 2014)), 0, 1) -> 0
A64: 42998.156 | B64: 17-2218 | C64: P021 | D64: 7 | E64: 207 | F64: =IF(E64="",_xlfn.XLOOKUP(C64,'Price Averages'!$D$4:$D$103,'Price Averages'!$E$4:$E$103, "FALSE"), E64) -> 207 | G64: 69 | H64: =IF(G64="", _xlfn.XLOOKUP(C64, 'Cost Averages'!$D$4:$D$103,'Cost Averages'!$E$4:$E$103, "FALSE"),G64) -> 69 | I64: =D64*F64 -> 1449 | J64: =D64*H64 -> 483 | K64: =I64-J64 -> 966 | L64: Dissatisfied | M64: HS-7607 | N64: Healthcare & Safety | O64: 11.563725 | P64: =CHAR(64+(YEAR(A64)-2014)) -> C | Q64: =YEAR(A64) -> 2017 | R64: =IF(P64=CHAR(64 + (YEAR(A64) - 2014)), 0, 1) -> 0
A65: 42911.018 | B65: 17-1860 | C65: P026 | D65: 7 | E65: 280 | F65: =IF(E65="",_xlfn.XLOOKUP(C65,'Price Averages'!$D$4:$D$103,'Price Averages'!$E$4:$E$103, "FALSE"), E65) -> 280 | G65: 70 | H65: =IF(G65="", _xlfn.XLOOKUP(C65, 'Cost Averages'!$D$4:$D$103,'Cost Averages'!$E$4:$E$103, "FALSE"),G65) -> 70 | I65: =D65*F65 -> 1960 | J65: =D65*H65 -> 490 | K65: =I65-J65 -> 1470 | L65: Dissatisfied | M65: FE-6898 | N65: Facilities & Services | O65: 12.514998 | P65: =CHAR(64+(YEAR(A65)-2014)) -> C | Q65: =YEAR(A65) -> 2017 | R65: =IF(P65=CHAR(64 + (YEAR(A65) - 2014)), 0, 1) -> 0
A66: 42974.019 | B66: 17-3997 | C66: P024 | D66: 8 | E66: 66 | F66: =IF(E66="",_xlfn.XLOOKUP(C66,'Price Averages'!$D$4:$D$103,'Price Averages'!$E$4:$E$103, "FALSE"), E66) -> 66 | G66: 33 | H66: =IF(G66="", _xlfn.XLOOKUP(C66, 'Cost Averages'!$D$4:$D$103,'Cost Averages'!$E$4:$E$103, "FALSE"),G66) -> 33 | I66: =D66*F66 -> 528 | J66: =D66*H66 -> 264 | K66: =I66-J66 -> 264 | L66: Neither | M66: FE-6323 | N66: Facilities & Services | O66: 10.523528 | P66: =CHAR(64+(YEAR(A66)-2014)) -> C | Q66: =YEAR(A66) -> 2017 | R66: =IF(P66=CHAR(64 + (YEAR(A66) - 2014)), 0, 1) -> 0
A67: 43010.588 | B67: 17-4392 | C67: P026 | D67: 8 | E67: 280 | F67: =IF(E67="",_xlfn.XLOOKUP(C67,'Price Averages'!$D$4:$D$103,'Price Averages'!$E$4:$E$103, "FALSE"), E67) -> 280 | G67: 70 | H67: =IF(G67="", _xlfn.XLOOKUP(C67, 'Cost Averages'!$D$4:$D$103,'Cost Averages'!$E$4:$E$103, "FALSE"),G67) -> 70 | I67: =D67*F67 -> 2240 | J67: =D67*H67 -> 560 | K67: =I67-J67 -> 1680 | L67: Dissatisfied | M67: FE-6919 | N67: Facilities & Services | O67: 13.37808 | P67: =CHAR(64+(YEAR(A67)-2014)) -> C | Q67: =YEAR(A67) -> 2017 | R67: =IF(P67=CHAR(64 + (YEAR(A67) - 2014)), 0, 1) -> 0
A68: 42986.391 | B68: 17-3063 | C68: P035 | D68: 8 | F68: =IF(E68="",_xlfn.XLOOKUP(C68,'Price Averages'!$D$4:$D$103,'Price Averages'!$E$4:$E$103, "FALSE"), E68) -> 144 | G68: 48 | H68: =IF(G68="", _xlfn.XLOOKUP(C68, 'Cost Averages'!$D$4:$D$103,'Cost Averages'!$E$4:$E$103, "FALSE"),G68) -> 48 | I68: =D68*F68 -> 1152 | J68: =D68*H68 -> 384 | K68: =I68-J68 -> 768 | L68: Neither | M68: SR-9105 | N68: Sports & Recreation | O68: 11.072271 | P68: =CHAR(64+(YEAR(A68)-2014)) -> C | Q68: =YEAR(A68) -> 2017 | R68: =IF(P68=CHAR(64 + (YEAR(A68) - 2014)), 0, 1) -> 0
A69: 42992.182 | B69: 17-4811 | C69: P066 | D69: 8 | F69: =IF(E69="",_xlfn.XLOOKUP(C69,'Price Averages'!$D$4:$D$103,'Price Averages'!$E$4:$E$103, "FALSE"), E69) -> 34 | G69: 17 | H69: =IF(G69="", _xlfn.XLOOKUP(C69, 'Cost Averages'!$D$4:$D$103,'Cost Averages'!$E$4:$E$103, "FALSE"),G69) -> 17 | I69: =D69*F69 -> 272 | J69: =D69*H69 -> 136 | K69: =I69-J69 -> 136 | L69: Dissatisfied | M69: CT-3443 | N69: Creative & Technology | O69: 11.312215 | P69: =CHAR(64+(YEAR(A69)-2014)) -> C | Q69: =YEAR(A69) -> 2017 | R69: =IF(P69=CHAR(64 + (YEAR(A69) - 2014)), 0, 1) -> 0
A70: 42788.212 | B70: 17-3585 | C70: P074 | D70: 8 | E70: 352 | F70: =IF(E70="",_xlfn.XLOOKUP(C70,'Price Averages'!$D$4:$D$103,'Price Averages'!$E$4:$E$103, "FALSE"), E70) -> 352 | H70: =IF(G70="", _xlfn.XLOOKUP(C70, 'Cost Averages'!$D$4:$D$103,'Cost Averages'!$E$4:$E$103, "FALSE"),G70) -> 88 | I70: =D70*F70 -> 2816 | J70: =D70*H70 -> 704 | K70: =I70-J70 -> 2112 | L70: Neither | M70: CT-3618 | N70: Creative & Technology | O70: 11.995407 | P70: =CHAR(64+(YEAR(A70)-2014)) -> C | Q70: =YEAR(A70) -> 2017 | R70: =IF(P70=CHAR(64 + (YEAR(A70) - 2014)), 0, 1) -> 0
A71: 43034.675 | B71: 17-4864 | C71: P086 | D71: 8 | F71: =IF(E71="",_xlfn.XLOOKUP(C71,'Price Averages'!$D$4:$D$103,'Price Averages'!$E$4:$E$103, "FALSE"), E71) -> 352 | G71: 88 | H71: =IF(G71="", _xlfn.XLOOKUP(C71, 'Cost Averages'!$D$4:$D$103,'Cost Averages'!$E$4:$E$103, "FALSE"),G71) -> 88 | I71: =D71*F71 -> 2816 | J71: =D71*H71 -> 704 | K71: =I71-J71 -> 2112 | L71: Dissatisfied | M71: SR-9393 | N71: Sports & Recreation | O71: 13.115598 | P71: =CHAR(64+(YEAR(A71)-2014)) -> C | Q71: =YEAR(A71) -> 2017 | R71: =IF(P71=CHAR(64 + (YEAR(A71) - 2014)), 0, 1) -> 0
A72: 42930.42 | B72: 17-2584 | C72: P015 | D72: 9 | E72: 176 | F72: =IF(E72="",_xlfn.XLOOKUP(C72,'Price Averages'!$D$4:$D$103,'Price Averages'!$E$4:$E$103, "FALSE"), E72) -> 176 | G72: 88 | H72: =IF(G72="", _xlfn.XLOOKUP(C72, 'Cost Averages'!$D$4:$D$103,'Cost Averages'!$E$4:$E$103, "FALSE"),G72) -> 88 | I72: =D72*F72 -> 1584 | J72: =D72*H72 -> 792 | K72: =I72-J72 -> 792 | L72: Dissatisfied | M72: SR-9989 | N72: Sports & Recreation | O72: 15.602184 | P72: =CHAR(64+(YEAR(A72)-2014)) -> C | Q72: =YEAR(A72) -> 2017 | R72: =IF(P72=CHAR(64 + (YEAR(A72) - 2014)), 0, 1) -> 0
A73: 42946.785 | B73: 17-2486 | C73: P040 | D73: 9 | E73: 160 | F73: =IF(E73="",_xlfn.XLOOKUP(C73,'Price Averages'!$D$4:$D$103,'Price Averages'!$E$4:$E$103, "FALSE"), E73) -> 160 | G73: 80 | H73: =IF(G73="", _xlfn.XLOOKUP(C73, 'Cost Averages'!$D$4:$D$103,'Cost Averages'!$E$4:$E$103, "FALSE"),G73) -> 80 | I73: =D73*F73 -> 1440 | J73: =D73*H73 -> 720 | K73: =I73-J73 -> 720 | L73: Dissatisfied | M73: FE-6944 | N73: Facilities & Services | O73: 13.518413 | P73: =CHAR(64+(YEAR(A73)-2014)) -> C | Q73: =YEAR(A73) -> 2017 | R73: =IF(P73=CHAR(64 + (YEAR(A73) - 2014)), 0, 1) -> 0
A74: 42985.107 | B74: 17-3805 | C74: P051 | D74: 9 | E74: 135 | F74: =IF(E74="",_xlfn.XLOOKUP(C74,'Price Averages'!$D$4:$D$103,'Price Averages'!$E$4:$E$103, "FALSE"), E74) -> 135 | G74: 45 | H74: =IF(G74="", _xlfn.XLOOKUP(C74, 'Cost Averages'!$D$4:$D$103,'Cost Averages'!$E$4:$E$103, "FALSE"),G74) -> 45 | I74: =D74*F74 -> 1215 | J74: =D74*H74 -> 405 | K74: =I74-J74 -> 810 | L74: Neither | M74: HS-7475 | N74: Healthcare & Safety | O74: 13.005538 | P74: =CHAR(64+(YEAR(A74)-2014)) -> C | Q74: =YEAR(A74) -> 2017 | R74: =IF(P74=CHAR(64 + (YEAR(A74) - 2014)), 0, 1) -> 0
A75: 42913.739 | B75: 17-4529 | C75: P052 | D75: 9 | E75: 352 | F75: =IF(E75="",_xlfn.XLOOKUP(C75,'Price Averages'!$D$4:$D$103,'Price Averages'!$E$4:$E$103, "FALSE"), E75) -> 352 | G75: 88 | H75: =IF(G75="", _xlfn.XLOOKUP(C75, 'Cost Averages'!$D$4:$D$103,'Cost Averages'!$E$4:$E$103, "FALSE"),G75) -> 88 | I75: =D75*F75 -> 3168 | J75: =D75*H75 -> 792 | K75: =I75-J75 -> 2376 | L75: Satisfied | M75: FE-6981 | N75: Facilities & Services | O75: 10.517826 | P75: =CHAR(64+(YEAR(A75)-2014)) -> C | Q75: =YEAR(A75) -> 2017 | R75: =IF(P75=CHAR(64 + (YEAR(A75) - 2014)), 0, 1) -> 0
A76: 43076.454 | B76: 17-2090 | C76: P019 | D76: 10 | F76: =IF(E76="",_xlfn.XLOOKUP(C76,'Price Averages'!$D$4:$D$103,'Price Averages'!$E$4:$E$103, "FALSE"), E76) -> 308 | G76: 77 | H76: =IF(G76="", _xlfn.XLOOKUP(C76, 'Cost Averages'!$D$4:$D$103,'Cost Averages'!$E$4:$E$103, "FALSE"),G76) -> 77 | I76: =D76*F76 -> 3080 | J76: =D76*H76 -> 770 | K76: =I76-J76 -> 2310 | L76: Neither | M76: FE-685 | N76: Facilities & Services | O76: 10.95659 | P76: =CHAR(64+(YEAR(A76)-2014)) -> C | Q76: =YEAR(A76) -> 2017 | R76: =IF(P76=CHAR(64 + (YEAR(A76) - 2014)), 0, 1) -> 0
A77: 42871.471 | B77: 17-2421 | C77: P050 | D77: 10 | E77: 108 | F77: =IF(E77="",_xlfn.XLOOKUP(C77,'Price Averages'!$D$4:$D$103,'Price Averages'!$E$4:$E$103, "FALSE"), E77) -> 108 | G77: 36 | H77: =IF(G77="", _xlfn.XLOOKUP(C77, 'Cost Averages'!$D$4:$D$103,'Cost Averages'!$E$4:$E$103, "FALSE"),G77) -> 36 | I77: =D77*F77 -> 1080 | J77: =D77*H77 -> 360 | K77: =I77-J77 -> 720 | L77: Neither | M77: CP-2758 | N77: Corporate & Professional | O77: 11.816654 | P77: =CHAR(64+(YEAR(A77)-2014)) -> C | Q77: =YEAR(A77) -> 2017 | R77: =IF(P77=CHAR(64 + (YEAR(A77) - 2014)), 0, 1) -> 0
A78: 42962.447 | B78: 17-2640 | C78: P090 | D78: 10 | E78: 57 | F78: =IF(E78="",_xlfn.XLOOKUP(C78,'Price Averages'!$D$4:$D$103,'Price Averages'!$E$4:$E$103, "FALSE"), E78) -> 57 | G78: 19 | H78: =IF(G78="", _xlfn.XLOOKUP(C78, 'Cost Averages'!$D$4:$D$103,'Cost Averages'!$E$4:$E$103, "FALSE"),G78) -> 19 | I78: =D78*F78 -> 570 | J78: =D78*H78 -> 190 | K78: =I78-J78 -> 380 | L78: Neither | M78: CP-260 | N78: Corporate & Professional | O78: 12.557744 | P78: =CHAR(64+(YEAR(A78)-2014)) -> C | Q78: =YEAR(A78) -> 2017 | R78: =IF(P78=CHAR(64 + (YEAR(A78) - 2014)), 0, 1) -> 0
A79: 43092.206 | B79: 17-2409 | C79: P001 | D79: 11 | E79: 108 | F79: =IF(E79="",_xlfn.XLOOKUP(C79,'Price Averages'!$D$4:$D$103,'Price Averages'!$E$4:$E$103, "FALSE"), E79) -> 108 | G79: 36 | H79: =IF(G79="", _xlfn.XLOOKUP(C79, 'Cost Averages'!$D$4:$D$103,'Cost Averages'!$E$4:$E$103, "FALSE"),G79) -> 36 | I79: =D79*F79 -> 1188 | J79: =D79*H79 -> 396 | K79: =I79-J79 -> 792 | L79: Satisfied | M79: SR-9132 | N79: Sports & Recreation | O79: 12.865075 | P79: =CHAR(64+(YEAR(A79)-2014)) -> C | Q79: =YEAR(A79) -> 2017 | R79: =IF(P79=CHAR(64 + (YEAR(A79) - 2014)), 0, 1) -> 0
A80: 43004.07 | B80: 17-4829 | C80: P069 | D80: 11 | F80: =IF(E80="",_xlfn.XLOOKUP(C80,'Price Averages'!$D$4:$D$103,'Price Averages'!$E$4:$E$103, "FALSE"), E80) -> 150 | G80: 75 | H80: =IF(G80="", _xlfn.XLOOKUP(C80, 'Cost Averages'!$D$4:$D$103,'Cost Averages'!$E$4:$E$103, "FALSE"),G80) -> 75 | I80: =D80*F80 -> 1650 | J80: =D80*H80 -> 825 | K80: =I80-J80 -> 825 | L80: Satisfied | M80: CT-3613 | N80: Creative & Technology | O80: 14.064517 | P80: =CHAR(64+(YEAR(A80)-2014)) -> C | Q80: =YEAR(A80) -> 2017 | R80: =IF(P80=CHAR(64 + (YEAR(A80) - 2014)), 0, 1) -> 0
A81: 42837.299 | B81: 17-4344 | C81: P083 | D81: 11 | E81: 90 | F81: =IF(E81="",_xlfn.XLOOKUP(C81,'Price Averages'!$D$4:$D$103,'Price Averages'!$E$4:$E$103, "FALSE"), E81) -> 90 | G81: 45 | H81: =IF(G81="", _xlfn.XLOOKUP(C81, 'Cost Averages'!$D$4:$D$103,'Cost Averages'!$E$4:$E$103, "FALSE"),G81) -> 45 | I81: =D81*F81 -> 990 | J81: =D81*H81 -> 495 | K81: =I81-J81 -> 495 | L81: Neither | M81: SR-9566 | N81: Sports & Recreation | O81: 12.564315 | P81: =CHAR(64+(YEAR(A81)-2014)) -> C | Q81: =YEAR(A81) -> 2017 | R81: =IF(P81=CHAR(64 + (YEAR(A81) - 2014)), 0, 1) -> 0
A82: 42911.837 | B82: 17-1345 | C82: P011 | D82: 12 | E82: 264 | F82: =IF(E82="",_xlfn.XLOOKUP(C82,'Price Averages'!$D$4:$D$103,'Price Averages'!$E$4:$E$103, "FALSE"), E82) -> 264 | G82: 88 | H82: =IF(G82="", _xlfn.XLOOKUP(C82, 'Cost Averages'!$D$4:$D$103,'Cost Averages'!$E$4:$E$103, "FALSE"),G82) -> 88 | I82: =D82*F82 -> 3168 | J82: =D82*H82 -> 1056 | K82: =I82-J82 -> 2112 | L82: Satisfied | M82: CT-3737 | N82: Creative & Technology | O82: 8.0758316 | P82: =CHAR(64+(YEAR(A82)-2014)) -> C | Q82: =YEAR(A82) -> 2017 | R82: =IF(P82=CHAR(64 + (YEAR(A82) - 2014)), 0, 1) -> 0
A83: 42922.594 | B83: 17-4707 | C83: P023 | D83: 12 | E83: 126 | F83: =IF(E83="",_xlfn.XLOOKUP(C83,'Price Averages'!$D$4:$D$103,'Price Averages'!$E$4:$E$103, "FALSE"), E83) -> 126 | G83: 42 | H83: =IF(G83="", _xlfn.XLOOKUP(C83, 'Cost Averages'!$D$4:$D$103,'Cost Averages'!$E$4:$E$103, "FALSE"),G83) -> 42 | I83: =D83*F83 -> 1512 | J83: =D83*H83 -> 504 | K83: =I83-J83 -> 1008 | L83: Satisfied | M83: CG-1316 | N83: Community & Government | O83: 15.45886 | P83: =CHAR(64+(YEAR(A83)-2014)) -> C | Q83: =YEAR(A83) -> 2017 | R83: =IF(P83=CHAR(64 + (YEAR(A83) - 2014)), 0, 1) -> 0
A84: 42852.304 | B84: 17-2258 | C84: P047 | D84: 12 | E84: 72 | F84: =IF(E84="",_xlfn.XLOOKUP(C84,'Price Averages'!$D$4:$D$103,'Price Averages'!$E$4:$E$103, "FALSE"), E84) -> 72 | G84: 36 | H84: =IF(G84="", _xlfn.XLOOKUP(C84, 'Cost Averages'!$D$4:$D$103,'Cost Averages'!$E$4:$E$103, "FALSE"),G84) -> 36 | I84: =D84*F84 -> 864 | J84: =D84*H84 -> 432 | K84: =I84-J84 -> 432 | L84: Dissatisfied | M84: SR-9639 | N84: Sports & Recreation | O84: 12.487915 | P84: =CHAR(64+(YEAR(A84)-2014)) -> C | Q84: =YEAR(A84) -> 2017 | R84: =IF(P84=CHAR(64 + (YEAR(A84) - 2014)), 0, 1) -> 0
A85: 43061.027 | B85: 17-4263 | C85: P006 | D85: 13 | E85: 38 | F85: =IF(E85="",_xlfn.XLOOKUP(C85,'Price Averages'!$D$4:$D$103,'Price Averages'!$E$4:$E$103, "FALSE"), E85) -> 38 | G85: 19 | H85: =IF(G85="", _xlfn.XLOOKUP(C85, 'Cost Averages'!$D$4:$D$103,'Cost Averages'!$E$4:$E$103, "FALSE"),G85) -> 19 | I85: =D85*F85 -> 494 | J85: =D85*H85 -> 247 | K85: =I85-J85 -> 247 | L85: Neither | M85: SR-9332 | N85: Sports & Recreation | O85: 12.701326 | P85: =CHAR(64+(YEAR(A85)-2014)) -> C | Q85: =YEAR(A85) -> 2017 | R85: =IF(P85=CHAR(64 + (YEAR(A85) - 2014)), 0, 1) -> 0
A86: 42913.57 | B86: 17-2043 | C86: P012 | D86: 13 | E86: 30 | F86: =IF(E86="",_xlfn.XLOOKUP(C86,'Price Averages'!$D$4:$D$103,'Price Averages'!$E$4:$E$103, "FALSE"), E86) -> 30 | H86: =IF(G86="", _xlfn.XLOOKUP(C86, 'Cost Averages'!$D$4:$D$103,'Cost Averages'!$E$4:$E$103, "FALSE"),G86) -> 15 | I86: =D86*F86 -> 390 | J86: =D86*H86 -> 195 | K86: =I86-J86 -> 195 | L86: Satisfied | M86: HS-735 | N86: Healthcare & Safety | O86: 9.8892508 | P86: =CHAR(64+(YEAR(A86)-2014)) -> C | Q86: =YEAR(A86) -> 2017 | R86: =IF(P86=CHAR(64 + (YEAR(A86) - 2014)), 0, 1) -> 0
A87: 43014.745 | B87: 17-4372 | C87: P020 | D87: 13 | E87: 180 | F87: =IF(E87="",_xlfn.XLOOKUP(C87,'Price Averages'!$D$4:$D$103,'Price Averages'!$E$4:$E$103, "FALSE"), E87) -> 180 | G87: 45 | H87: =IF(G87="", _xlfn.XLOOKUP(C87, 'Cost Averages'!$D$4:$D$103,'Cost Averages'!$E$4:$E$103, "FALSE"),G87) -> 45 | I87: =D87*F87 -> 2340 | J87: =D87*H87 -> 585 | K87: =I87-J87 -> 1755 | L87: Dissatisfied | M87: EE-4917 | N87: Education | O87: 11.756375 | P87: =CHAR(64+(YEAR(A87)-2014)) -> C | Q87: =YEAR(A87) -> 2017 | R87: =IF(P87=CHAR(64 + (YEAR(A87) - 2014)), 0, 1) -> 0
A88: 43069.717 | B88: 17-3724 | C88: P041 | D88: 13 | F88: =IF(E88="",_xlfn.XLOOKUP(C88,'Price Averages'!$D$4:$D$103,'Price Averages'!$E$4:$E$103, "FALSE"), E88) -> 144 | H88: =IF(G88="", _xlfn.XLOOKUP(C88, 'Cost Averages'!$D$4:$D$103,'Cost Averages'!$E$4:$E$103, "FALSE"),G88) -> 36 | I88: =D88*F88 -> 1872 | J88: =D88*H88 -> 468 | K88: =I88-J88 -> 1404 | L88: Dissatisfied | M88: CG-1618 | N88: Community & Government | O88: 8.1628931 | P88: =CHAR(64+(YEAR(A88)-2014)) -> C | Q88: =YEAR(A88) -> 2017 | R88: =IF(P88=CHAR(64 + (YEAR(A88) - 2014)), 0, 1) -> 0
A89: 43087.79 | B89: 17-3553 | C89: P061 | D89: 13 | E89: 264 | F89: =IF(E89="",_xlfn.XLOOKUP(C89,'Price Averages'!$D$4:$D$103,'Price Averages'!$E$4:$E$103, "FALSE"), E89) -> 264 | G89: 88 | H89: =IF(G89="", _xlfn.XLOOKUP(C89, 'Cost Averages'!$D$4:$D$103,'Cost Averages'!$E$4:$E$103, "FALSE"),G89) -> 88 | I89: =D89*F89 -> 3432 | J89: =D89*H89 -> 1144 | K89: =I89-J89 -> 2288 | L89: Satisfied | M89: CT-3932 | N89: Creative & Technology | O89: 13.929237 | P89: =CHAR(64+(YEAR(A89)-2014)) -> C | Q89: =YEAR(A89) -> 2017 | R89: =IF(P89=CHAR(64 + (YEAR(A89) - 2014)), 0, 1) -> 0
A90: 42873.804 | B90: 17-1857 | C90: P063 | D90: 13 | E90: 261 | F90: =IF(E90="",_xlfn.XLOOKUP(C90,'Price Averages'!$D$4:$D$103,'Price Averages'!$E$4:$E$103, "FALSE"), E90) -> 261 | G90: 87 | H90: =IF(G90="", _xlfn.XLOOKUP(C90, 'Cost Averages'!$D$4:$D$103,'Cost Averages'!$E$4:$E$103, "FALSE"),G90) -> 87 | I90: =D90*F90 -> 3393 | J90: =D90*H90 -> 1131 | K90: =I90-J90 -> 2262 | L90: Neither | M90: EE-46 | N90: Education | O90: 9.8238489 | P90: =CHAR(64+(YEAR(A90)-2014)) -> C | Q90: =YEAR(A90) -> 2017 | R90: =IF(P90=CHAR(64 + (YEAR(A90) - 2014)), 0, 1) -> 0
A91: 43068.791 | B91: 17-1916 | C91: P067 | D91: 13 | E91: 144 | F91: =IF(E91="",_xlfn.XLOOKUP(C91,'Price Averages'!$D$4:$D$103,'Price Averages'!$E$4:$E$103, "FALSE"), E91) -> 144 | G91: 36 | H91: =IF(G91="", _xlfn.XLOOKUP(C91, 'Cost Averages'!$D$4:$D$103,'Cost Averages'!$E$4:$E$103, "FALSE"),G91) -> 36 | I91: =D91*F91 -> 1872 | J91: =D91*H91 -> 468 | K91: =I91-J91 -> 1404 | L91: Neither | M91: CG-1416 | N91: Community & Government | O91: 12.155895 | P91: =CHAR(64+(YEAR(A91)-2014)) -> C | Q91: =YEAR(A91) -> 2017 | R91: =IF(P91=CHAR(64 + (YEAR(A91) - 2014)), 0, 1) -> 0
A92: 42936.191 | B92: 17-4660 | C92: P095 | D92: 13 | E92: 116 | F92: =IF(E92="",_xlfn.XLOOKUP(C92,'Price Averages'!$D$4:$D$103,'Price Averages'!$E$4:$E$103, "FALSE"), E92) -> 116 | G92: 29 | H92: =IF(G92="", _xlfn.XLOOKUP(C92, 'Cost Averages'!$D$4:$D$103,'Cost Averages'!$E$4:$E$103, "FALSE"),G92) -> 29 | I92: =D92*F92 -> 1508 | J92: =D92*H92 -> 377 | K92: =I92-J92 -> 1131 | L92: Neither | M92: CG-1367 | N92: Community & Government | O92: 15.604305 | P92: =CHAR(64+(YEAR(A92)-2014)) -> C | Q92: =YEAR(A92) -> 2017 | R92: =IF(P92=CHAR(64 + (YEAR(A92) - 2014)), 0, 1) -> 0
A93: 43068.673 | B93: 17-4764 | C93: P005 | D93: 14 | F93: =IF(E93="",_xlfn.XLOOKUP(C93,'Price Averages'!$D$4:$D$103,'Price Averages'!$E$4:$E$103, "FALSE"), E93) -> 76 | G93: 19 | H93: =IF(G93="", _xlfn.XLOOKUP(C93, 'Cost Averages'!$D$4:$D$103,'Cost Averages'!$E$4:$E$103, "FALSE"),G93) -> 19 | I93: =D93*F93 -> 1064 | J93: =D93*H93 -> 266 | K93: =I93-J93 -> 798 | L93: Satisfied | M93: CP-2846 | N93: Corporate & Professional | O93: 16.254955 | P93: =CHAR(64+(YEAR(A93)-2014)) -> C | Q93: =YEAR(A93) -> 2017 | R93: =IF(P93=CHAR(64 + (YEAR(A93) - 2014)), 0, 1) -> 0
A94: 43006.7 | B94: 17-1767 | C94: P031 | D94: 14 | E94: 146 | F94: =IF(E94="",_xlfn.XLOOKUP(C94,'Price Averages'!$D$4:$D$103,'Price Averages'!$E$4:$E$103, "FALSE"), E94) -> 146 | G94: 73 | H94: =IF(G94="", _xlfn.XLOOKUP(C94, 'Cost Averages'!$D$4:$D$103,'Cost Averages'!$E$4:$E$103, "FALSE"),G94) -> 73 | I94: =D94*F94 -> 2044 | J94: =D94*H94 -> 1022 | K94: =I94-J94 -> 1022 | L94: Neither | M94: FE-621 | N94: Facilities & Services | O94: 11.410471 | P94: =CHAR(64+(YEAR(A94)-2014)) -> C | Q94: =YEAR(A94) -> 2017 | R94: =IF(P94=CHAR(64 + (YEAR(A94) - 2014)), 0, 1) -> 0
A95: 43042.65 | B95: 17-1955 | C95: P032 | D95: 14 | E95: 92 | F95: =IF(E95="",_xlfn.XLOOKUP(C95,'Price Averages'!$D$4:$D$103,'Price Averages'!$E$4:$E$103, "FALSE"), E95) -> 92 | G95: 46 | H95: =IF(G95="", _xlfn.XLOOKUP(C95, 'Cost Averages'!$D$4:$D$103,'Cost Averages'!$E$4:$E$103, "FALSE"),G95) -> 46 | I95: =D95*F95 -> 1288 | J95: =D95*H95 -> 644 | K95: =I95-J95 -> 644 | L95: Satisfied | M95: CP-2889 | N95: Corporate & Professional | O95: 10.248947 | P95: =CHAR(64+(YEAR(A95)-2014)) -> C | Q95: =YEAR(A95) -> 2017 | R95: =IF(P95=CHAR(64 + (YEAR(A95) - 2014)), 0, 1) -> 0
A96: 43097.141 | B96: 17-4532 | C96: P059 | D96: 14 | F96: =IF(E96="",_xlfn.XLOOKUP(C96,'Price Averages'!$D$4:$D$103,'Price Averages'!$E$4:$E$103, "FALSE"), E96) -> 267 | G96: 89 | H96: =IF(G96="", _xlfn.XLOOKUP(C96, 'Cost Averages'!$D$4:$D$103,'Cost Averages'!$E$4:$E$103, "FALSE"),G96) -> 89 | I96: =D96*F96 -> 3738 | J96: =D96*H96 -> 1246 | K96: =I96-J96 -> 2492 | L96: Neither | M96: FE-6339 | N96: Facilities & Services | O96: 13.853439 | P96: =CHAR(64+(YEAR(A96)-2014)) -> C | Q96: =YEAR(A96) -> 2017 | R96: =IF(P96=CHAR(64 + (YEAR(A96) - 2014)), 0, 1) -> 0
A97: 43003.013 | B97: 17-4257 | C97: P093 | D97: 14 | F97: =IF(E97="",_xlfn.XLOOKUP(C97,'Price Averages'!$D$4:$D$103,'Price Averages'!$E$4:$E$103, "FALSE"), E97) -> 384 | G97: 96 | H97: =IF(G97="", _xlfn.XLOOKUP(C97, 'Cost Averages'!$D$4:$D$103,'Cost Averages'!$E$4:$E$103, "FALSE"),G97) -> 96 | I97: =D97*F97 -> 5376 | J97: =D97*H97 -> 1344 | K97: =I97-J97 -> 4032 | L97: Neither | M97: SR-9639 | N97: Sports & Recreation | O97: 12.487915 | P97: =CHAR(64+(YEAR(A97)-2014)) -> C | Q97: =YEAR(A97) -> 2017 | R97: =IF(P97=CHAR(64 + (YEAR(A97) - 2014)), 0, 1) -> 0
A98: 42868.389 | B98: 17-1371 | C98: P009 | D98: 15 | E98: 255 | F98: =IF(E98="",_xlfn.XLOOKUP(C98,'Price Averages'!$D$4:$D$103,'Price Averages'!$E$4:$E$103, "FALSE"), E98) -> 255 | G98: 85 | H98: =IF(G98="", _xlfn.XLOOKUP(C98, 'Cost Averages'!$D$4:$D$103,'Cost Averages'!$E$4:$E$103, "FALSE"),G98) -> 85 | I98: =D98*F98 -> 3825 | J98: =D98*H98 -> 1275 | K98: =I98-J98 -> 2550 | L98: Satisfied | M98: SR-9198 | N98: Sports & Recreation | O98: 11.443504 | P98: =CHAR(64+(YEAR(A98)-2014)) -> C | Q98: =YEAR(A98) -> 2017 | R98: =IF(P98=CHAR(64 + (YEAR(A98) - 2014)), 0, 1) -> 0
A99: 43044.409 | B99: 17-4758 | C99: P055 | D99: 15 | E99: 360 | F99: =IF(E99="",_xlfn.XLOOKUP(C99,'Price Averages'!$D$4:$D$103,'Price Averages'!$E$4:$E$103, "FALSE"), E99) -> 360 | G99: 90 | H99: =IF(G99="", _xlfn.XLOOKUP(C99, 'Cost Averages'!$D$4:$D$103,'Cost Averages'!$E$4:$E$103, "FALSE"),G99) -> 90 | I99: =D99*F99 -> 5400 | J99: =D99*H99 -> 1350 | K99: =I99-J99 -> 4050 | L99: Satisfied | M99: EE-4649 | N99: Education | O99: 13.392447 | P99: =CHAR(64+(YEAR(A99)-2014)) -> C | Q99: =YEAR(A99) -> 2017 | R99: =IF(P99=CHAR(64 + (YEAR(A99) - 2014)), 0, 1) -> 0
A100: 42798.41 | B100: 17-1042 | C100: P066 | D100: 15 | F100: =IF(E100="",_xlfn.XLOOKUP(C100,'Price Averages'!$D$4:$D$103,'Price Averages'!$E$4:$E$103, "FALSE"), E100) -> 34 | H100: =IF(G100="", _xlfn.XLOOKUP(C100, 'Cost Averages'!$D$4:$D$103,'Cost Averages'!$E$4:$E$103, "FALSE"),G100) -> 17 | I100: =D100*F100 -> 510 | J100: =D100*H100 -> 255 | K100: =I100-J100 -> 255 | L100: Satisfied | M100: HS-7652 | N100: Healthcare & Safety | O100: 14.377134 | P100: =CHAR(64+(YEAR(A100)-2014)) -> C | Q100: =YEAR(A100) -> 2017 | R100: =IF(P100=CHAR(64 + (YEAR(A100) - 2014)), 0, 1) -> 0
...

Sheet Stats Testing
B6: Profits
B7: A | C7: B | D7: C | E7: D | F7: E | G7: F | H7: G | I7: H | J7: I | K7: J | L7: K | O7: t-Test: Two-Sample Assuming Unequal Variances | S7: t-Test: Two-Sample Assuming Unequal Variances
B8: 80 | C8: 154 | D8: 170 | E8: 150 | F8: 150 | G8: 108 | H8: 57 | I8: 176 | J8: 210 | K8: 63 | L8: 540 | O8: Not Significant | S8: Not Significant
B9: 2160 | C9: 38 | D9: 57 | E9: 90 | F9: 55 | G9: 126 | H9: 57 | I9: 15 | J9: 267 | K9: 720 | L9: 400 | P9: A = 2015 | Q9: B = 2016 | T9: B = 2016 | U9: C = 2017
B10: 1701 | C10: 90 | D10: 174 | E10: 231 | F10: 90 | G10: 19 | H10: 108 | I10: 210 | J10: 17 | K10: 384 | O10: Mean | P10: 1448 | Q10: 1216.9474 | S10: Mean | T10: 1216.9474 | U10: 1193.6765
B11: 949 | C11: 115 | D11: 38 | E11: 138 | F11: 135 | G11: 88 | H11: 29 | I11: 70 | J11: 240 | K11: 1170 | O11: Variance | P11: 677092.4 | Q11: 1059982.7 | S11: Variance | T11: 1059982.7 | U11: 1261190.3
B12: 2278 | C12: 900 | D12: 23 | E12: 84 | F12: 102 | G12: 88 | H12: 83 | I12: 225 | J12: 264 | K12: 495 | O12: Observations | P12: 6 | Q12: 19 | S12: Observations | T12: 19 | U12: 102
B13: 1520 | C13: 736 | D13: 352 | E13: 80 | F13: 140 | G13: 55 | H13: 55 | I13: 73 | J13: 216 | K13: 282 | O13: Hypothesized Mean Difference | P13: 0 | S13: Hypothesized Mean Difference | T13: 0
C14: 2136 | D14: 140 | E14: 180 | F14: 78 | G14: 54 | H14: 54 | I14: 57 | J14: 450 | K14: 672 | O14: df | P14: 10 | S14: df | T14: 27
C15: 2430 | D15: 160 | E15: 25 | F15: 54 | G15: 54 | H15: 135 | I15: 96 | J15: 72 | K15: 1408 | O15: t Stat | P15: 0.56264453 | S15: t Stat | T15: 0.089139479
C16: 2640 | D16: 378 | E16: 276 | F16: 73 | G16: 138 | H16: 135 | I16: 80 | J16: 528 | K16: 2646 | O16: P(T<=t) one-tail | P16: 0.29303422 | S16: P(T<=t) one-tail | T16: 0.4648145
C17: 319 | D17: 192 | E17: 19 | F17: 73 | G17: 84 | H17: 135 | I17: 276 | J17: 102 | K17: 3150 | O17: t Critical one-tail | P17: 1.8124611 | S17: t Critical one-tail | T17: 1.7032884
C18: 1188 | D18: 87 | E18: 36 | F18: 38 | G18: 84 | H18: 102 | I18: 75 | J18: 420 | K18: 4488 | O18: P(T<=t) two-tail | P18: 0.58606844 | S18: P(T<=t) two-tail | T18: 0.92962899
C19: 1056 | D19: 675 | E19: 189 | F19: 210 | G19: 210 | H19: 84 | I19: 19 | J19: 297 | O19: t Critical two-tail | P19: 2.2281389 | S19: t Critical two-tail | T19: 2.0518305
C20: 3432 | D20: 171 | E20: 25 | F20: 80 | G20: 210 | H20: 84 | I20: 19 | J20: 280
C21: 1440 | D21: 462 | E21: 36 | F21: 160 | G21: 70 | H21: 210 | I21: 72 | J21: 228 | O21: t-Test: Two-Sample Assuming Unequal Variances | S21: t-Test: Two-Sample Assuming Unequal Variances
C22: 1280 | D22: 180 | E22: 267 | F22: 180 | G22: 54 | H22: 78 | I22: 264 | J22: 100 | O22: Not Significant | S22: Not Significant
C23: 2880 | D23: 297 | E23: 63 | F23: 25 | G23: 54 | H23: 78 | I23: 178 | J23: 384 | P23: C = 2017 | Q23: D = 2018 | T23: D = 2018 | U23: E = 2019
C24: 648 | D24: 144 | E24: 47 | F24: 276 | G24: 73 | H24: 225 | I24: 225 | J24: 184 | O24: Mean | P24: 1193.6765 | Q24: 1316.4048 | S24: Mean | T24: 1316.4048 | U24: 1169.192
C25: 1140 | D25: 750 | E25: 150 | F25: 276 | G25: 38 | H25: 38 | I25: 80 | J25: 690 | O25: Variance | P25: 1261190.3 | Q25: 1469973.5 | S25: Variance | T25: 1469973.5 | U25: 1174205.5
C26: 500 | D26: 400 | E26: 234 | F26: 75 | G26: 210 | H26: 57 | I26: 108 | J26: 1125 | O26: Observations | P26: 102 | Q26: 336 | S26: Observations | T26: 336 | U26: 750
D27: 1125 | E27: 51 | F27: 90 | G27: 180 | H27: 96 | I27: 150 | J27: 495 | O27: Hypothesized Mean Difference | P27: 0 | S27: Hypothesized Mean Difference | T27: 0
D28: 880 | E28: 216 | F28: 264 | G28: 25 | H28: 210 | I28: 38 | J28: 648 | O28: df | P28: 178 | S28: df | T28: 584
D29: 670 | E29: 252 | F29: 36 | G29: 75 | H29: 180 | I29: 96 | J29: 576 | O29: t Stat | P29: -0.94857796 | S29: t Stat | T29: 1.909998
D30: 756 | E30: 110 | F30: 36 | G30: 19 | H30: 108 | I30: 38 | J30: 644 | O30: P(T<=t) one-tail | P30: 0.17206068 | S30: P(T<=t) one-tail | T30: 0.028311514
D31: 900 | E31: 108 | F31: 36 | G31: 19 | H31: 25 | I31: 153 | J31: 1071 | O31: t Critical one-tail | P31: 1.6534591 | S31: t Critical one-tail | T31: 1.647467
D32: 648 | E32: 192 | F32: 176 | G32: 189 | H32: 276 | I32: 60 | J32: 768 | O32: P(T<=t) two-tail | P32: 0.34412137 | S32: P(T<=t) two-tail | T32: 0.056623029
D33: 1386 | E33: 360 | F33: 176 | G33: 267 | H33: 36 | I33: 96 | J33: 1200 | O33: t Critical two-tail | P33: 1.9733809 | S33: t Critical two-tail | T33: 1.9640344
D34: 438 | E34: 180 | F34: 25 | G34: 72 | H34: 264 | I34: 134 | J34: 810
D35: 480 | E35: 534 | F35: 17 | G35: 264 | H35: 264 | I35: 216 | J35: 720 | O35: t-Test: Two-Sample Assuming Unequal Variances | S35: t-Test: Two-Sample Assuming Unequal Variances
D36: 1044 | E36: 352 | F36: 108 | G36: 264 | H36: 25 | I36: 352 | J36: 153
D37: 150 | E37: 522 | F37: 225 | G37: 25 | H37: 189 | I37: 352 | J37: 423 | P37: E = 2019 | Q37: F = 2020 | T37: F = 2020 | U37: G = 2021
D38: 840 | E38: 522 | F38: 63 | G38: 96 | H38: 267 | I38: 110 | J38: 780 | O38: Mean | P38: 1169.192 | Q38: 1219.6756 | S38: Mean | T38: 1219.6756 | U38: 1215.0917
D39: 900 | E39: 216 | F39: 264 | G39: 36 | H39: 25 | I39: 180 | J39: 960 | O39: Variance | P39: 1174205.5 | Q39: 1247023.7 | S39: Variance | T39: 1247023.7 | U39: 1286281.9
D40: 150 | E40: 50 | F40: 216 | G40: 36 | H40: 108 | I40: 276 | J40: 1530 | O40: Observations | P40: 750 | Q40: 1153 | S40: Observations | T40: 1153 | U40: 905
D41: 528 | E41: 171 | F41: 216 | G41: 189 | H41: 225 | I41: 280 | J41: 2079 | O41: Hypothesized Mean Difference | P41: 0 | S41: Hypothesized Mean Difference | T41: 0
D42: 372 | E42: 264 | F42: 114 | G42: 189 | H42: 75 | I42: 450 | J42: 1540 | O42: df | P42: 1634 | S42: df | T42: 1927
D43: 576 | E43: 162 | F43: 38 | G43: 267 | H43: 75 | I43: 146 | J43: 1683 | O43: t Stat | P43: -0.98120767 | S43: t Stat | T43: 0.091626056
D44: 138 | E44: 99 | F44: 300 | G44: 267 | H44: 264 | I44: 92 | J44: 960 | O44: P(T<=t) one-tail | P44: 0.1633178 | S44: P(T<=t) one-tail | T44: 0.46350234
D45: 966 | E45: 138 | F45: 216 | G45: 267 | H45: 80 | I45: 76 | J45: 540 | O45: t Critical one-tail | P45: 1.6457867 | S45: t Critical one-tail | T45: 1.6456448
D46: 1470 | E46: 288 | F46: 216 | G46: 267 | H46: 94 | I46: 192 | J46: 819 | O46: P(T<=t) two-tail | P46: 0.3266356 | S46: P(T<=t) two-tail | T46: 0.92700467
D47: 264 | E47: 810 | F47: 58 | G47: 225 | H47: 234 | I47: 160 | J47: 406 | O47: t Critical two-tail | P47: 1.9614169 | S47: t Critical two-tail | T47: 1.9611958
D48: 1680 | E48: 675 | F48: 166 | G48: 174 | H48: 45 | I48: 160 | J48: 1120
D49: 768 | E49: 522 | F49: 276 | G49: 174 | H49: 38 | I49: 160 | J49: 225 | O49: t-Test: Two-Sample Assuming Unequal Variances | S49: t-Test: Two-Sample Assuming Unequal Variances
D50: 136 | E50: 420 | F50: 420 | G50: 17 | H50: 38 | I50: 150 | J50: 1350
D51: 2112 | E51: 264 | F51: 156 | G51: 17 | H51: 46 | I51: 180 | J51: 2295 | P51: G = 2021 | Q51: H = 2022 | T51: H = 2022 | U51: I = 2023
D52: 2112 | E52: 72 | F52: 450 | G52: 75 | H52: 46 | I52: 540 | J52: 2295 | O52: Mean | P52: 1215.0917 | Q52: 1223.3726 | S52: Mean | T52: 1223.3726 | U52: 910.83929
D53: 792 | E53: 282 | F53: 146 | G53: 75 | H53: 46 | I53: 72 | J53: 2560 | O53: Variance | P53: 1286281.9 | Q53: 1260175.9 | S53: Variance | T53: 1260175.9 | U53: 583567.85
D54: 720 | E54: 720 | F54: 92 | G54: 75 | H54: 99 | I54: 534 | J54: 3600 | O54: Observations | P54: 905 | Q54: 475 | S54: Observations | T54: 475 | U54: 56
D55: 810 | E55: 264 | F55: 420 | G55: 80 | H55: 23 | I55: 308 | J55: 1584 | O55: Hypothesized Mean Difference | P55: 0 | S55: Hypothesized Mean Difference | T55: 0
D56: 2376 | E56: 288 | F56: 38 | G56: 108 | H56: 23 | I56: 280 | J56: 2142 | O56: df | P56: 972 | S56: df | T56: 86
D57: 2310 | E57: 114 | F57: 378 | G57: 25 | H57: 144 | I57: 576 | J57: 969 | O57: t Stat | P57: -0.12973334 | S57: t Stat | T57: 2.7333454
D58: 720 | E58: 864 | F58: 534 | G58: 45 | H58: 252 | I58: 192 | J58: 1944 | O58: P(T<=t) one-tail | P58: 0.44840212 | S58: P(T<=t) one-tail | T58: 0.0038049381
D59: 380 | E59: 864 | F59: 180 | G59: 77 | H59: 252 | I59: 268 | J59: 306 | O59: t Critical one-tail | P59: 1.6464228 | S59: t Critical one-tail | T59: 1.6627654
D60: 792 | E60: 220 | F60: 540 | G60: 240 | H60: 114 | I60: 46 | J60: 722 | O60: P(T<=t) two-tail | P60: 0.89680424 | S60: P(T<=t) two-tail | T60: 0.0076098761
D61: 825 | E61: 552 | F61: 540 | G61: 88 | H61: 216 | I61: 450 | J61: 1520 | O61: t Critical two-tail | P61: 1.9624076 | S61: t Critical two-tail | T61: 1.9879342
D62: 495 | E62: 280 | F62: 72 | G62: 88 | H62: 352 | I62: 450 | J62: 1710
D63: 2112 | E63: 100 | F63: 356 | G63: 88 | H63: 30 | I63: 450 | J63: 1786 | O63: t-Test: Two-Sample Assuming Unequal Variances | S63: t-Test: Two-Sample Assuming Unequal Variances
D64: 1008 | E64: 1056 | F64: 348 | G64: 51 | H64: 30 | I64: 165
D65: 432 | E65: 1080 | F65: 34 | G65: 38 | H65: 176 | I65: 270 | P65: I = 2023 | Q65: J = 2024 | T65: J = 2024 | U65: K = 2025
D66: 247 | E66: 300 | F66: 150 | G66: 153 | H66: 180 | I66: 162 | O66: Mean | P66: 910.83929 | Q66: 1407.0909 | S66: Mean | T66: 1407.0909 | U66: 470
D67: 195 | E67: 376 | F67: 176 | G67: 62 | H67: 462 | I67: 57 | O67: Variance | P67: 583567.85 | Q67: 2008432.9 | S67: Variance | T67: 2008432.9 | U67: 9800
D68: 1755 | E68: 936 | F68: 48 | G68: 62 | H68: 270 | I68: 567 | O68: Observations | P68: 56 | Q68: 11 | S68: Observations | T68: 11 | U68: 2
D69: 1404 | E69: 204 | F69: 48 | G69: 288 | H69: 270 | I69: 216 | O69: Hypothesized Mean Difference | P69: 0 | S69: Hypothesized Mean Difference | T69: 0
D70: 2288 | E70: 248 | F70: 48 | G70: 46 | H70: 156 | I70: 792 | O70: df | P70: 11 | S70: df | T70: 10
D71: 2262 | E71: 248 | F71: 528 | G71: 134 | H71: 450 | I71: 567 | O71: t Stat | P71: -1.1295798 | S71: t Stat | T71: 2.1642064
D72: 1404 | E72: 384 | F72: 528 | G72: 252 | H72: 192 | I72: 225 | O72: P(T<=t) one-tail | P72: 0.14134196 | S72: P(T<=t) one-tail | T72: 0.027856224
D73: 1131 | E73: 536 | F73: 50 | G73: 252 | H73: 192 | I73: 264 | O73: t Critical one-tail | P73: 1.7958848 | S73: t Critical one-tail | T73: 1.8124611
D74: 798 | E74: 95 | F74: 50 | G74: 252 | H74: 160 | I74: 792 | O74: P(T<=t) two-tail | P74: 0.28268391 | S74: P(T<=t) two-tail | T74: 0.055712449
D75: 1022 | E75: 75 | F75: 154 | G75: 38 | H75: 320 | I75: 180 | O75: t Critical two-tail | P75: 2.2009852 | S75: t Critical two-tail | T75: 2.2281389
D76: 644 | E76: 1125 | F76: 480 | G76: 38 | H76: 50 | I76: 288
D77: 2492 | E77: 480 | F77: 480 | G77: 300 | H77: 72 | I77: 402
D78: 4032 | E78: 1125 | F78: 176 | G78: 340 | H78: 534 | I78: 402
D79: 2550 | E79: 870 | F79: 306 | G79: 352 | H79: 534 | I79: 432
D80: 4050 | E80: 870 | F80: 576 | G80: 166 | H80: 528 | I80: 504
D81: 255 | E81: 870 | F81: 192 | G81: 108 | H81: 528 | I81: 504
D82: 1620 | E82: 125 | F82: 268 | G82: 108 | H82: 192 | I82: 76
D83: 570 | E83: 480 | F83: 268 | G83: 270 | H83: 540 | I83: 680
D84: 2720 | E84: 114 | F84: 198 | G84: 168 | H84: 378 | I84: 680
D85: 2816 | E85: 90 | F85: 324 | G85: 420 | H85: 450 | I85: 432
D86: 240 | E86: 1386 | F86: 57 | G86: 450 | H86: 522 | I86: 408
D87: 464 | E87: 342 | F87: 450 | G87: 108 | H87: 348 | I87: 336
... D109: 1920 | E109: 1617 | F109: 675 | G109: 216 | H109: 45 | I109: 180
E110: 966 | F110: 72 | G110: 450 | H110: 165 | I110: 180
E111: 231 | F111: 72 | G111: 126 | H111: 693 | I111: 384
E112: 266 | F112: 792 | G112: 176 | H112: 306 | I112: 204
E113: 560 | F113: 792 | G113: 176 | H113: 252 | I113: 248
E114: 1120 | F114: 288 | G114: 176 | H114: 99 | I114: 92
E115: 756 | F115: 459 | G115: 528 | H115: 219 | I115: 750
E116: 525 | F116: 864 | G116: 216 | H116: 114 | I116: 75
E117: 525 | F117: 180 | G117: 300 | H117: 480 | I117: 510
E118: 630 | F118: 288 | G118: 76 | H118: 324 | I118: 350
E119: 1848 | F119: 288 | G119: 76 | H119: 828 | I119: 270
E120: 1869 | F120: 69 | G120: 76 | H120: 225 | I120: 365
E121: 119 | F121: 288 | G121: 468 | H121: 57 | I121: 1050
... E343: 1920 | F343: 864 | G343: 306 | H343: 264 | I343: 3465
F344: 864 | G344: 228 | H344: 1800 | I344: 3150
F345: 864 | G345: 228 | H345: 584 | I345: 3150
F346: 1377 | G346: 360 | H346: 584 | I346: 1050
F347: 2592 | G347: 576 | H347: 304 | I347: 1050
...

Sheet Project Work - Analysis Notes
B1: Exercise -Data | C1: Project Work
A2: Data Discovery and Exploration | B2: Specify the Question and scope the answer, Obtain the Data | C2: Price = Profit + Cost Which consecutive Years had significantly different Profits?
A3: Pre-Processing | B3: Data Summaries (Categorical, Numeric), Identification and Summarization of Data Issues (Null, Missing, Corrutped values,etc.), Feature Selection, Dimensionality Reduction, Normalization, Data Subsetting | C3: Data Issues Discovered Fiscal Dates from Order Dates, Profit by Order, Cost by Order Dimensional Reduction not necessary for analysis Normalization not necessary but Transormation is due to dollars compared to dollars Subsets by Year used in Analysis (Each Year is applied a Name A , B, and C)
A4: Data Mining | B4: Resolving Data Issues, Performing Analysis | C4: Data Corruption - Six Columns have corrupted data
A5: Post-Processing | B5: Statistical Testing, Significance Testing, Sampling of Instances, Hypothesis Testing | C5: T- Tests between Years for Profit across Years
A6: Information Development | B6: Analysis Outcomes, Data Review, Data Issue Summary, | C6: Test Results and Regression Summary Univariate Analysis for Profit and Cost for each Year, Bivariate Analysis for each year of Cost and Profit, Data Issues, Resolution Steps, and Effects of Resolution
A7: Outcome Communication | B7: Answering the Specific Questions, Report formation, and messaging | C7: Which onsecutive Years had significantly different Profits? Report Formation (Analysis Outcome Review) Messaging (2 Minute Talk about answer and julstificaiton - 175 words)

Sheet Data Dictionary
A1: Variables | B1: Data Type
A2: Order Date | B2: Interval | C2: Discrete
A3: Order Number | B3: Nominal | C3: Discrete
A4: Product | B4: Nominal | C4: Discrete
A5: Quantity | B5: Ratio | C5: Continuous
A6: Price Per Unit | B6: Ratio | C6: Continuous
A7: Cost per Unit | B7: Ratio | C7: Continuous
A8: Revenue | B8: Ratio | C8: Continuous
A9: Costs | B9: Ratio | C9: Continuous
A10: Profit | B10: Ratio | C10: Continuous
A11: Order Survey Response | B11: Ordinal | C11: Discrete
A12: Customer ID | B12: Nominal | C12: Discrete
A13: Customer Category | B13: Nominal | C13: Discrete
... A16: Subset | B16: Ordinal | C16: Discrete

Sheet Project Work - Data wrows
A1: Order Date | B1: Order Number | C1: Product | D1: Quantity | E1: Fixed Quantity | F1: Price Per Unit | G1: Fixed Price Per Unit | H1: Cost per Unit | I1: Fixed Cost Per Unit | J1: Revenue | K1: Costs | L1: Profit | M1: Order Survey Response | N1: Customer ID | O1: Customer Category | P1: Customer Tenure | Q1: Subset Label | R1: Subset | S1: Subset Check
A2: 42297.389 | B2: 15-3098 | C2: P031 | D2: 13 | E2: =IF(D2="", _xlfn.XLOOKUP(C2,'Median Quantity per product'!$D$4:$D$103,'Median Quantity per product'!$E$4:$E$103, "NA"),'Project Work - Data wrows'!D2) -> 13 | G2: =IF(F2="",_xlfn.XLOOKUP(C2,'Price Averages'!$D$4:$D$103,'Price Averages'!$E$4:$E$103, "FALSE"), F2) -> 146 | H2: 73 | I2: =IF(H2="", _xlfn.XLOOKUP(C2, 'Cost Averages'!$D$4:$D$103,'Cost Averages'!$E$4:$E$103, "FALSE"),H2) -> 73 | J2: =E2*G2 -> 1898 | K2: =E2*I2 -> 949 | L2: =J2-K2 -> 949 | M2: Neither | N2: HS-770 | O2: Healthcare & Safety | P2: 12.148237 | Q2: =CHAR(64+(YEAR(A2)-2014)) -> A | R2: =YEAR(A2) -> 2015 | S2: =IF(Q2=CHAR(64 + (YEAR(A2) - 2014)), 0, 1) -> 0
A3: 42258.411 | B3: 15-4254 | C3: P037 | D3: 1 | E3: =IF(D3="", _xlfn.XLOOKUP(C3,'Median Quantity per product'!$D$4:$D$103,'Median Quantity per product'!$E$4:$E$103, "NA"),'Project Work - Data wrows'!D3) -> 1 | F3: 160 | G3: =IF(F3="",_xlfn.XLOOKUP(C3,'Price Averages'!$D$4:$D$103,'Price Averages'!$E$4:$E$103, "FALSE"), F3) -> 160 | H3: 80 | I3: =IF(H3="", _xlfn.XLOOKUP(C3, 'Cost Averages'!$D$4:$D$103,'Cost Averages'!$E$4:$E$103, "FALSE"),H3) -> 80 | J3: =E3*G3 -> 160 | K3: =E3*I3 -> 80 | L3: =J3-K3 -> 80 | M3: Neither | N3: HS-7862 | O3: Healthcare & Safety | P3: 14.423323 | Q3: =CHAR(64+(YEAR(A3)-2014)) -> A | R3: =YEAR(A3) -> 2015 | S3: =IF(Q3=CHAR(64 + (YEAR(A3) - 2014)), 0, 1) -> 0
A4: 42178.711 | B4: 15-2073 | C4: P055 | D4: 8 | E4: =IF(D4="", _xlfn.XLOOKUP(C4,'Median Quantity per product'!$D$4:$D$103,'Median Quantity per product'!$E$4:$E$103, "NA"),'Project Work - Data wrows'!D4) -> 8 | F4: 360 | G4: =IF(F4="",_xlfn.XLOOKUP(C4,'Price Averages'!$D$4:$D$103,'Price Averages'!$E$4:$E$103, "FALSE"), F4) -> 360 | H4: 90 | I4: =IF(H4="", _xlfn.XLOOKUP(C4, 'Cost Averages'!$D$4:$D$103,'Cost Averages'!$E$4:$E$103, "FALSE"),H4) -> 90 | J4: =E4*G4 -> 2880 | K4: =E4*I4 -> 720 | L4: =J4-K4 -> 2160 | M4: Neither | N4: CP-2960 | O4: Corporate & Professional | P4: 13.062293 | Q4: =CHAR(64+(YEAR(A4)-2014)) -> A | R4: =YEAR(A4) -> 2015 | S4: =IF(Q4=CHAR(64 + (YEAR(A4) - 2014)), 0, 1) -> 0
A5: 42368.549 | B5: 15-3490 | C5: P057 | D5: 9 | E5: =IF(D5="", _xlfn.XLOOKUP(C5,'Median Quantity per product'!$D$4:$D$103,'Median Quantity per product'!$E$4:$E$103, "NA"),'Project Work - Data wrows'!D5) -> 9 | F5: 252 | G5: =IF(F5="",_xlfn.XLOOKUP(C5,'Price Averages'!$D$4:$D$103,'Price Averages'!$E$4:$E$103, "FALSE"), F5) -> 252 | H5: 63 | I5: =IF(H5="", _xlfn.XLOOKUP(C5, 'Cost Averages'!$D$4:$D$103,'Cost Averages'!$E$4:$E$103, "FALSE"),H5) -> 63 | J5: =E5*G5 -> 2268 | K5: =E5*I5 -> 567 | L5: =J5-K5 -> 1701 | M5: Satisfied | N5: CT-3606 | O5: Creative & Technology | P5: 12.173452 | Q5: =CHAR(64+(YEAR(A5)-2014)) -> A | R5: =YEAR(A5) -> 2015 | S5: =IF(Q5=CHAR(64 + (YEAR(A5) - 2014)), 0, 1) -> 0
A6: 42216.891 | B6: 15-4617 | C6: P075 | D6: 19 | E6: =IF(D6="", _xlfn.XLOOKUP(C6,'Median Quantity per product'!$D$4:$D$103,'Median Quantity per product'!$E$4:$E$103, "NA"),'Project Work - Data wrows'!D6) -> 19 | F6: 160 | G6: =IF(F6="",_xlfn.XLOOKUP(C6,'Price Averages'!$D$4:$D$103,'Price Averages'!$E$4:$E$103, "FALSE"), F6) -> 160 | H6: 80 | I6: =IF(H6="", _xlfn.XLOOKUP(C6, 'Cost Averages'!$D$4:$D$103,'Cost Averages'!$E$4:$E$103, "FALSE"),H6) -> 80 | J6: =E6*G6 -> 3040 | K6: =E6*I6 -> 1520 | L6: =J6-K6 -> 1520 | M6: Neither | N6: EE-4917 | O6: Education | P6: 11.756375 | Q6: =CHAR(64+(YEAR(A6)-2014)) -> A | R6: =YEAR(A6) -> 2015 | S6: =IF(Q6=CHAR(64 + (YEAR(A6) - 2014)), 0, 1) -> 0
A7: 42322.453 | B7: 15-3015 | C7: P098 | D7: 17 | E7: =IF(D7="", _xlfn.XLOOKUP(C7,'Median Quantity per product'!$D$4:$D$103,'Median Quantity per product'!$E$4:$E$103, "NA"),'Project Work - Data wrows'!D7) -> 17 | F7: 201 | G7: =IF(F7="",_xlfn.XLOOKUP(C7,'Price Averages'!$D$4:$D$103,'Price Averages'!$E$4:$E$103, "FALSE"), F7) -> 201 | H7: 67 | I7: =IF(H7="", _xlfn.XLOOKUP(C7, 'Cost Averages'!$D$4:$D$103,'Cost Averages'!$E$4:$E$103, "FALSE"),H7) -> 67 | J7: =E7*G7 -> 3417 | K7: =E7*I7 -> 1139 | L7: =J7-K7 -> 2278 | M7: Satisfied | N7: EE-4613 | O7: Education | P7: 15.26855 | Q7: =CHAR(64+(YEAR(A7)-2014)) -> A | R7: =YEAR(A7) -> 2015 | S7: =IF(Q7=CHAR(64 + (YEAR(A7) - 2014)), 0, 1) -> 0
A8: 42641.299 | B8: 16-1896 | C8: P005 | D8: 20 | E8: =IF(D8="", _xlfn.XLOOKUP(C8,'Median Quantity per product'!$D$4:$D$103,'Median Quantity per product'!$E$4:$E$103, "NA"),'Project Work - Data wrows'!D8) -> 20 | G8: =IF(F8="",_xlfn.XLOOKUP(C8,'Price Averages'!$D$4:$D$103,'Price Averages'!$E$4:$E$103, "FALSE"), F8) -> 76 | H8: 19 | I8: =IF(H8="", _xlfn.XLOOKUP(C8, 'Cost Averages'!$D$4:$D$103,'Cost Averages'!$E$4:$E$103, "FALSE"),H8) -> 19 | J8: =E8*G8 -> 1520 | K8: =E8*I8 -> 380 | L8: =J8-K8 -> 1140 | M8: Neither | N8: CT-3174 | O8: Creative & Technology | P8: 15.187892 | Q8: =CHAR(64+(YEAR(A8)-2014)) -> B | R8: =YEAR(A8) -> 2016 | S8: =IF(Q8=CHAR(64 + (YEAR(A8) - 2014)), 0, 1) -> 0
A9: 42673.243 | B9: 16-1836 | C9: P006 | D9: 2 | E9: =IF(D9="", _xlfn.XLOOKUP(C9,'Median Quantity per product'!$D$4:$D$103,'Median Quantity per product'!$E$4:$E$103, "NA"),'Project Work - Data wrows'!D9) -> 2 | G9: =IF(F9="",_xlfn.XLOOKUP(C9,'Price Averages'!$D$4:$D$103,'Price Averages'!$E$4:$E$103, "FALSE"), F9) -> 38 | H9: 19 | I9: =IF(H9="", _xlfn.XLOOKUP(C9, 'Cost Averages'!$D$4:$D$103,'Cost Averages'!$E$4:$E$103, "FALSE"),H9) -> 19 | J9: =E9*G9 -> 76 | K9: =E9*I9 -> 38 | L9: =J9-K9 -> 38 | M9: Neither | N9: CG-1672 | O9: Community & Government | P9: 11.655356 | Q9: =CHAR(64+(YEAR(A9)-2014)) -> B | R9: =YEAR(A9) -> 2016 | S9: =IF(Q9=CHAR(64 + (YEAR(A9) - 2014)), 0, 1) -> 0
A10: 42695.685 | B10: 16-4606 | C10: P008 | D10: 6 | E10: =IF(D10="", _xlfn.XLOOKUP(C10,'Median Quantity per product'!$D$4:$D$103,'Median Quantity per product'!$E$4:$E$103, "NA"),'Project Work - Data wrows'!D10) -> 6 | F10: 225 | G10: =IF(F10="",_xlfn.XLOOKUP(C10,'Price Averages'!$D$4:$D$103,'Price Averages'!$E$4:$E$103, "FALSE"), F10) -> 225 | H10: 75 | I10: =IF(H10="", _xlfn.XLOOKUP(C10, 'Cost Averages'!$D$4:$D$103,'Cost Averages'!$E$4:$E$103, "FALSE"),H10) -> 75 | J10: =E10*G10 -> 1350 | K10: =E10*I10 -> 450 | L10: =J10-K10 -> 900 | M10: Neither | N10: SR-930 | O10: Sports & Recreation | P10: 14.690199 | Q10: =CHAR(64+(YEAR(A10)-2014)) -> B | R10: =YEAR(A10) -> 2016 | S10: =IF(Q10=CHAR(64 + (YEAR(A10) - 2014)), 0, 1) -> 0
A11: 42681.511 | B11: 16-3455 | C11: P013 | D11: 11 | E11: =IF(D11="", _xlfn.XLOOKUP(C11,'Median Quantity per product'!$D$4:$D$103,'Median Quantity per product'!$E$4:$E$103, "NA"),'Project Work - Data wrows'!D11) -> 11 | F11: 58 | G11: =IF(F11="",_xlfn.XLOOKUP(C11,'Price Averages'!$D$4:$D$103,'Price Averages'!$E$4:$E$103, "FALSE"), F11) -> 58 | I11: =IF(H11="", _xlfn.XLOOKUP(C11, 'Cost Averages'!$D$4:$D$103,'Cost Averages'!$E$4:$E$103, "FALSE"),H11) -> 29 | J11: =E11*G11 -> 638 | K11: =E11*I11 -> 319 | L11: =J11-K11 -> 319 | M11: Neither | N11: EE-450 | O11: Education | P11: 8.3272838 | Q11: =CHAR(64+(YEAR(A11)-2014)) -> B | R11: =YEAR(A11) -> 2016 | S11: =IF(Q11=CHAR(64 + (YEAR(A11) - 2014)), 0, 1) -> 0
A12: 42709.937 | B12: 16-4839 | C12: P017 | D12: 16 | E12: =IF(D12="", _xlfn.XLOOKUP(C12,'Median Quantity per product'!$D$4:$D$103,'Median Quantity per product'!$E$4:$E$103, "NA"),'Project Work - Data wrows'!D12) -> 16 | F12: 120 | G12: =IF(F12="",_xlfn.XLOOKUP(C12,'Price Averages'!$D$4:$D$103,'Price Averages'!$E$4:$E$103, "FALSE"), F12) -> 120 | H12: 30 | I12: =IF(H12="", _xlfn.XLOOKUP(C12, 'Cost Averages'!$D$4:$D$103,'Cost Averages'!$E$4:$E$103, "FALSE"),H12) -> 30 | J12: =E12*G12 -> 1920 | K12: =E12*I12 -> 480 | L12: =J12-K12 -> 1440 | M12: Satisfied | N12: CP-2926 | O12: Corporate & Professional | P12: 8.1743378 | Q12: =CHAR(64+(YEAR(A12)-2014)) -> B | R12: =YEAR(A12) -> 2016 | S12: =IF(Q12=CHAR(64 + (YEAR(A12) - 2014)), 0, 1) -> 0
A13: 42686.704 | B13: 16-4049 | C13: P038 | D13: 18 | E13: =IF(D13="", _xlfn.XLOOKUP(C13,'Median Quantity per product'!$D$4:$D$103,'Median Quantity per product'!$E$4:$E$103, "NA"),'Project Work - Data wrows'!D13) -> 18 | F13: 240 | G13: =IF(F13="",_xlfn.XLOOKUP(C13,'Price Averages'!$D$4:$D$103,'Price Averages'!$E$4:$E$103, "FALSE"), F13) -> 240 | H13: 80 | I13: =IF(H13="", _xlfn.XLOOKUP(C13, 'Cost Averages'!$D$4:$D$103,'Cost Averages'!$E$4:$E$103, "FALSE"),H13) -> 80 | J13: =E13*G13 -> 4320 | K13: =E13*I13 -> 1440 | L13: =J13-K13 -> 2880 | M13: Neither | N13: SR-9468 | O13: Sports & Recreation | P13: 10.010333 | Q13: =CHAR(64+(YEAR(A13)-2014)) -> B | R13: =YEAR(A13) -> 2016 | S13: =IF(Q13=CHAR(64 + (YEAR(A13) - 2014)), 0, 1) -> 0
A14: 42676.558 | B14: 16-1558 | C14: P040 | D14: 16 | E14: =IF(D14="", _xlfn.XLOOKUP(C14,'Median Quantity per product'!$D$4:$D$103,'Median Quantity per product'!$E$4:$E$103, "NA"),'Project Work - Data wrows'!D14) -> 16 | F14: 160 | G14: =IF(F14="",_xlfn.XLOOKUP(C14,'Price Averages'!$D$4:$D$103,'Price Averages'!$E$4:$E$103, "FALSE"), F14) -> 160 | H14: 80 | I14: =IF(H14="", _xlfn.XLOOKUP(C14, 'Cost Averages'!$D$4:$D$103,'Cost Averages'!$E$4:$E$103, "FALSE"),H14) -> 80 | J14: =E14*G14 -> 2560 | K14: =E14*I14 -> 1280 | L14: =J14-K14 -> 1280 | M14: Neither | N14: FE-6981 | O14: Facilities & Services | P14: 10.517826 | Q14: =CHAR(64+(YEAR(A14)-2014)) -> B | R14: =YEAR(A14) -> 2016 | S14: =IF(Q14=CHAR(64 + (YEAR(A14) - 2014)), 0, 1) -> 0
A15: 42693.272 | B15: 16-2390 | C15: P043 | D15: 8 | E15: =IF(D15="", _xlfn.XLOOKUP(C15,'Median Quantity per product'!$D$4:$D$103,'Median Quantity per product'!$E$4:$E$103, "NA"),'Project Work - Data wrows'!D15) -> 8 | F15: 184 | G15: =IF(F15="",_xlfn.XLOOKUP(C15,'Price Averages'!$D$4:$D$103,'Price Averages'!$E$4:$E$103, "FALSE"), F15) -> 184 | H15: 92 | I15: =IF(H15="", _xlfn.XLOOKUP(C15, 'Cost Averages'!$D$4:$D$103,'Cost Averages'!$E$4:$E$103, "FALSE"),H15) -> 92 | J15: =E15*G15 -> 1472 | K15: =E15*I15 -> 736 | L15: =J15-K15 -> 736 | M15: Neither | N15: HS-712 | O15: Healthcare & Safety | P15: 10.428287 | Q15: =CHAR(64+(YEAR(A15)-2014)) -> B | R15: =YEAR(A15) -> 2016 | S15: =IF(Q15=CHAR(64 + (YEAR(A15) - 2014)), 0, 1) -> 0
A16: 42720.868 | B16: 16-4872 | C16: P055 | D16: 9 | E16: =IF(D16="", _xlfn.XLOOKUP(C16,'Median Quantity per product'!$D$4:$D$103,'Median Quantity per product'!$E$4:$E$103, "NA"),'Project Work - Data wrows'!D16) -> 9 | G16: =IF(F16="",_xlfn.XLOOKUP(C16,'Price Averages'!$D$4:$D$103,'Price Averages'!$E$4:$E$103, "FALSE"), F16) -> 360 | H16: 90 | I16: =IF(H16="", _xlfn.XLOOKUP(C16, 'Cost Averages'!$D$4:$D$103,'Cost Averages'!$E$4:$E$103, "FALSE"),H16) -> 90 | J16: =E16*G16 -> 3240 | K16: =E16*I16 -> 810 | L16: =J16-K16 -> 2430 | M16: Satisfied | N16: SR-9808 | O16: Sports & Recreation | P16: 10.816866 | Q16: =CHAR(64+(YEAR(A16)-2014)) -> B | R16: =YEAR(A16) -> 2016 | S16: =IF(Q16=CHAR(64 + (YEAR(A16) - 2014)), 0, 1) -> 0
A17: 42485.261 | B17: 16-3871 | C17: P056 | D17: 18 | E17: =IF(D17="", _xlfn.XLOOKUP(C17,'Median Quantity per product'!$D$4:$D$103,'Median Quantity per product'!$E$4:$E$103, "NA"),'Project Work - Data wrows'!D17) -> 18 | G17: =IF(F17="",_xlfn.XLOOKUP(C17,'Price Averages'!$D$4:$D$103,'Price Averages'!$E$4:$E$103, "FALSE"), F17) -> 72 | H17: 36 | I17: =IF(H17="", _xlfn.XLOOKUP(C17, 'Cost Averages'!$D$4:$D$103,'Cost Averages'!$E$4:$E$103, "FALSE"),H17) -> 36 | J17: =E17*G17 -> 1296 | K17: =E17*I17 -> 648 | L17: =J17-K17 -> 648 | M17: Dissatisfied | N17: CT-3881 | O17: Creative & Technology | P17: 13.459801 | Q17: =CHAR(64+(YEAR(A17)-2014)) -> B | R17: =YEAR(A17) -> 2016 | S17: =IF(Q17=CHAR(64 + (YEAR(A17) - 2014)), 0, 1) -> 0
A18: 42656.038 | B18: 16-1050 | C18: P058 | D18: 8 | E18: =IF(D18="", _xlfn.XLOOKUP(C18,'Median Quantity per product'!$D$4:$D$103,'Median Quantity per product'!$E$4:$E$103, "NA"),'Project Work - Data wrows'!D18) -> 8 | G18: =IF(F18="",_xlfn.XLOOKUP(C18,'Price Averages'!$D$4:$D$103,'Price Averages'!$E$4:$E$103, "FALSE"), F18) -> 356 | H18: 89 | I18: =IF(H18="", _xlfn.XLOOKUP(C18, 'Cost Averages'!$D$4:$D$103,'Cost Averages'!$E$4:$E$103, "FALSE"),H18) -> 89 | J18: =E18*G18 -> 2848 | K18: =E18*I18 -> 712 | L18: =J18-K18 -> 2136 | M18: Neither | N18: EE-4357 | O18: Education | P18: 13.466363 | Q18: =CHAR(64+(YEAR(A18)-2014)) -> B | R18: =YEAR(A18) -> 2016 | S18: =IF(Q18=CHAR(64 + (YEAR(A18) - 2014)), 0, 1) -> 0
A19: 42720.978 | B19: 16-1451 | C19: P064 | D19: 1 | E19: =IF(D19="", _xlfn.XLOOKUP(C19,'Median Quantity per product'!$D$4:$D$103,'Median Quantity per product'!$E$4:$E$103, "NA"),'Project Work - Data wrows'!D19) -> 1 | F19: 231 | G19: =IF(F19="",_xlfn.XLOOKUP(C19,'Price Averages'!$D$4:$D$103,'Price Averages'!$E$4:$E$103, "FALSE"), F19) -> 231 | H19: 77 | I19: =IF(H19="", _xlfn.XLOOKUP(C19, 'Cost Averages'!$D$4:$D$103,'Cost Averages'!$E$4:$E$103, "FALSE"),H19) -> 77 | J19: =E19*G19 -> 231 | K19: =E19*I19 -> 77 | L19: =J19-K19 -> 154 | M19: Neither | N19: CT-3498 | O19: Creative & Technology | P19: 10.588336 | Q19: =CHAR(64+(YEAR(A19)-2014)) -> B | R19: =YEAR(A19) -> 2016 | S19: =IF(Q19=CHAR(64 + (YEAR(A19) - 2014)), 0, 1) -> 0
A20: 42715.504 | B20: 16-1764 | C20: P065 | E20: =IF(D20="", _xlfn.XLOOKUP(C20,'Median Quantity per product'!$D$4:$D$103,'Median Quantity per product'!$E$4:$E$103, "NA"),'Project Work - Data wrows'!D20) -> 10 | F20: 50 | G20: =IF(F20="",_xlfn.XLOOKUP(C20,'Price Averages'!$D$4:$D$103,'Price Averages'!$E$4:$E$103, "FALSE"), F20) -> 50 | I20: =IF(H20="", _xlfn.XLOOKUP(C20, 'Cost Averages'!$D$4:$D$103,'Cost Averages'!$E$4:$E$103, "FALSE"),H20) -> 25 | J20: =E20*G20 -> 500 | K20: =E20*I20 -> 250 | L20: =J20-K20 -> 250 | M20: Neither | N20: CT-3439 | O20: Creative & Technology | P20: 7.897407 | Q20: =CHAR(64+(YEAR(A20)-2014)) -> B | R20: =YEAR(A20) -> 2016 | S20: =IF(Q20=CHAR(64 + (YEAR(A20) - 2014)), 0, 1) -> 0
A21: 42614.075 | B21: 16-2604 | C21: P067 | D21: 11 | E21: =IF(D21="", _xlfn.XLOOKUP(C21,'Median Quantity per product'!$D$4:$D$103,'Median Quantity per product'!$E$4:$E$103, "NA"),'Project Work - Data wrows'!D21) -> 11 | F21: 144 | G21: =IF(F21="",_xlfn.XLOOKUP(C21,'Price Averages'!$D$4:$D$103,'Price Averages'!$E$4:$E$103, "FALSE"), F21) -> 144 | H21: 36 | I21: =IF(H21="", _xlfn.XLOOKUP(C21, 'Cost Averages'!$D$4:$D$103,'Cost Averages'!$E$4:$E$103, "FALSE"),H21) -> 36 | J21: =E21*G21 -> 1584 | K21: =E21*I21 -> 396 | L21: =J21-K21 -> 1188 | M21: Satisfied | N21: CG-137 | O21: Community & Government | P21: 12.796588 | Q21: =CHAR(64+(YEAR(A21)-2014)) -> B | R21: =YEAR(A21) -> 2016 | S21: =IF(Q21=CHAR(64 + (YEAR(A21) - 2014)), 0, 1) -> 0
A22: 42615.366 | B22: 16-4442 | C22: P072 | D22: 12 | E22: =IF(D22="", _xlfn.XLOOKUP(C22,'Median Quantity per product'!$D$4:$D$103,'Median Quantity per product'!$E$4:$E$103, "NA"),'Project Work - Data wrows'!D22) -> 12 | F22: 132 | G22: =IF(F22="",_xlfn.XLOOKUP(C22,'Price Averages'!$D$4:$D$103,'Price Averages'!$E$4:$E$103, "FALSE"), F22) -> 132 | H22: 44 | I22: =IF(H22="", _xlfn.XLOOKUP(C22, 'Cost Averages'!$D$4:$D$103,'Cost Averages'!$E$4:$E$103, "FALSE"),H22) -> 44 | J22: =E22*G22 -> 1584 | K22: =E22*I22 -> 528 | L22: =J22-K22 -> 1056 | M22: Dissatisfied | N22: FE-6892 | O22: Facilities & Services | P22: 14.817898 | Q22: =CHAR(64+(YEAR(A22)-2014)) -> B | R22: =YEAR(A22) -> 2016 | S22: =IF(Q22=CHAR(64 + (YEAR(A22) - 2014)), 0, 1) -> 0
A23: 42476.479 | B23: 16-2216 | C23: P074 | D23: 10 | E23: =IF(D23="", _xlfn.XLOOKUP(C23,'Median Quantity per product'!$D$4:$D$103,'Median Quantity per product'!$E$4:$E$103, "NA"),'Project Work - Data wrows'!D23) -> 10 | F23: 352 | G23: =IF(F23="",_xlfn.XLOOKUP(C23,'Price Averages'!$D$4:$D$103,'Price Averages'!$E$4:$E$103, "FALSE"), F23) -> 352 | I23: =IF(H23="", _xlfn.XLOOKUP(C23, 'Cost Averages'!$D$4:$D$103,'Cost Averages'!$E$4:$E$103, "FALSE"),H23) -> 88 | J23: =E23*G23 -> 3520 | K23: =E23*I23 -> 880 | L23: =J23-K23 -> 2640 | M23: Dissatisfied | N23: HS-7291 | O23: Healthcare & Safety | P23: 10.42743 | Q23: =CHAR(64+(YEAR(A23)-2014)) -> B | R23: =YEAR(A23) -> 2016 | S23: =IF(Q23=CHAR(64 + (YEAR(A23) - 2014)), 0, 1) -> 0
A24: 42614.684 | B24: 16-1985 | C24: P074 | D24: 13 | E24: =IF(D24="", _xlfn.XLOOKUP(C24,'Median Quantity per product'!$D$4:$D$103,'Median Quantity per product'!$E$4:$E$103, "NA"),'Project Work - Data wrows'!D24) -> 13 | F24: 352 | G24: =IF(F24="",_xlfn.XLOOKUP(C24,'Price Averages'!$D$4:$D$103,'Price Averages'!$E$4:$E$103, "FALSE"), F24) -> 352 | H24: 88 | I24: =IF(H24="", _xlfn.XLOOKUP(C24, 'Cost Averages'!$D$4:$D$103,'Cost Averages'!$E$4:$E$103, "FALSE"),H24) -> 88 | J24: =E24*G24 -> 4576 | K24: =E24*I24 -> 1144 | L24: =J24-K24 -> 3432 | M24: Satisfied | N24: CP-2325 | O24: Corporate & Professional | P24: 11.701919 | Q24: =CHAR(64+(YEAR(A24)-2014)) -> B | R24: =YEAR(A24) -> 2016 | S24: =IF(Q24=CHAR(64 + (YEAR(A24) - 2014)), 0, 1) -> 0
A25: 42720.244 | B25: 16-1417 | C25: P081 | D25: 20 | E25: =IF(D25="", _xlfn.XLOOKUP(C25,'Median Quantity per product'!$D$4:$D$103,'Median Quantity per product'!$E$4:$E$103, "NA"),'Project Work - Data wrows'!D25) -> 20 | F25: 50 | G25: =IF(F25="",_xlfn.XLOOKUP(C25,'Price Averages'!$D$4:$D$103,'Price Averages'!$E$4:$E$103, "FALSE"), F25) -> 50 | I25: =IF(H25="", _xlfn.XLOOKUP(C25, 'Cost Averages'!$D$4:$D$103,'Cost Averages'!$E$4:$E$103, "FALSE"),H25) -> 25 | J25: =E25*G25 -> 1000 | K25: =E25*I25 -> 500 | L25: =J25-K25 -> 500 | M25: Neither | N25: CP-2629 | O25: Corporate & Professional | P25: 10.411813 | Q25: =CHAR(64+(YEAR(A25)-2014)) -> B | R25: =YEAR(A25) -> 2016 | S25: =IF(Q25=CHAR(64 + (YEAR(A25) - 2014)), 0, 1) -> 0
A26: 42673.971 | B26: 16-3460 | C26: P083 | D26: 2 | E26: =IF(D26="", _xlfn.XLOOKUP(C26,'Median Quantity per product'!$D$4:$D$103,'Median Quantity per product'!$E$4:$E$103, "NA"),'Project Work - Data wrows'!D26) -> 2 | F26: 90 | G26: =IF(F26="",_xlfn.XLOOKUP(C26,'Price Averages'!$D$4:$D$103,'Price Averages'!$E$4:$E$103, "FALSE"), F26) -> 90 | I26: =IF(H26="", _xlfn.XLOOKUP(C26, 'Cost Averages'!$D$4:$D$103,'Cost Averages'!$E$4:$E$103, "FALSE"),H26) -> 45 | J26: =E26*G26 -> 180 | K26: =E26*I26 -> 90 | L26: =J26-K26 -> 90 | M26: Satisfied | N26: CT-3920 | O26: Creative & Technology | P26: 14.661477 | Q26: =CHAR(64+(YEAR(A26)-2014)) -> B | R26: =YEAR(A26) -> 2016 | S26: =IF(Q26=CHAR(64 + (YEAR(A26) - 2014)), 0, 1) -> 0
A27: 42472.852 | B27: 16-2269 | C27: P088 | E27: =IF(D27="", _xlfn.XLOOKUP(C27,'Median Quantity per product'!$D$4:$D$103,'Median Quantity per product'!$E$4:$E$103, "NA"),'Project Work - Data wrows'!D27) -> 9 | F27: 192 | G27: =IF(F27="",_xlfn.XLOOKUP(C27,'Price Averages'!$D$4:$D$103,'Price Averages'!$E$4:$E$103, "FALSE"), F27) -> 192 | H27: 96 | I27: =IF(H27="", _xlfn.XLOOKUP(C27, 'Cost Averages'!$D$4:$D$103,'Cost Averages'!$E$4:$E$103, "FALSE"),H27) -> 96 | J27: =E27*G27 -> 1728 | K27: =E27*I27 -> 864 | L27: =J27-K27 -> 864 | M27: Satisfied | N27: HS-7802 | O27: Healthcare & Safety | P27: 12.801145 | Q27: =CHAR(64+(YEAR(A27)-2014)) -> B | R27: =YEAR(A27) -> 2016 | S27: =IF(Q27=CHAR(64 + (YEAR(A27) - 2014)), 0, 1) -> 0
A28: 42447.175 | B28: 16-2553 | C28: P100 | D28: 5 | E28: =IF(D28="", _xlfn.XLOOKUP(C28,'Median Quantity per product'!$D$4:$D$103,'Median Quantity per product'!$E$4:$E$103, "NA"),'Project Work - Data wrows'!D28) -> 5 | F28: 46 | G28: =IF(F28="",_xlfn.XLOOKUP(C28,'Price Averages'!$D$4:$D$103,'Price Averages'!$E$4:$E$103, "FALSE"), F28) -> 46 | H28: 23 | I28: =IF(H28="", _xlfn.XLOOKUP(C28, 'Cost Averages'!$D$4:$D$103,'Cost Averages'!$E$4:$E$103, "FALSE"),H28) -> 23 | J28: =E28*G28 -> 230 | K28: =E28*I28 -> 115 | L28: =J28-K28 -> 115 | M28: Satisfied | N28: EE-46 | O28: Education | P28: 9.8238489 | Q28: =CHAR(64+(YEAR(A28)-2014)) -> B | R28: =YEAR(A28) -> 2016 | S28: =IF(Q28=CHAR(64 + (YEAR(A28) - 2014)), 0, 1) -> 0
A29: 43092.206 | B29: 17-2409 | C29: P001 | D29: 11 | E29: =IF(D29="", _xlfn.XLOOKUP(C29,'Median Quantity per product'!$D$4:$D$103,'Median Quantity per product'!$E$4:$E$103, "NA"),'Project Work - Data wrows'!D29) -> 11 | F29: 108 | G29: =IF(F29="",_xlfn.XLOOKUP(C29,'Price Averages'!$D$4:$D$103,'Price Averages'!$E$4:$E$103, "FALSE"), F29) -> 108 | H29: 36 | I29: =IF(H29="", _xlfn.XLOOKUP(C29, 'Cost Averages'!$D$4:$D$103,'Cost Averages'!$E$4:$E$103, "FALSE"),H29) -> 36 | J29: =E29*G29 -> 1188 | K29: =E29*I29 -> 396 | L29: =J29-K29 -> 792 | M29: Satisfied | N29: SR-9132 | O29: Sports & Recreation | P29: 12.865075 | Q29: =CHAR(64+(YEAR(A29)-2014)) -> C | R29: =YEAR(A29) -> 2017 | S29: =IF(Q29=CHAR(64 + (YEAR(A29) - 2014)), 0, 1) -> 0
A30: 43036.146 | B30: 17-4686 | C30: P001 | D30: 18 | E30: =IF(D30="", _xlfn.XLOOKUP(C30,'Median Quantity per product'!$D$4:$D$103,'Median Quantity per product'!$E$4:$E$103, "NA"),'Project Work - Data wrows'!D30) -> 18 | F30: 108 | G30: =IF(F30="",_xlfn.XLOOKUP(C30,'Price Averages'!$D$4:$D$103,'Price Averages'!$E$4:$E$103, "FALSE"), F30) -> 108 | H30: 36 | I30: =IF(H30="", _xlfn.XLOOKUP(C30, 'Cost Averages'!$D$4:$D$103,'Cost Averages'!$E$4:$E$103, "FALSE"),H30) -> 36 | J30: =E30*G30 -> 1944 | K30: =E30*I30 -> 648 | L30: =J30-K30 -> 1296 | M30: Satisfied | N30: FE-621 | O30: Facilities & Services | P30: 11.410471 | Q30: =CHAR(64+(YEAR(A30)-2014)) -> C | R30: =YEAR(A30) -> 2017 | S30: =IF(Q30=CHAR(64 + (YEAR(A30) - 2014)), 0, 1) -> 0
A31: 43092.742 | B31: 17-2826 | C31: P002 | D31: 18 | E31: =IF(D31="", _xlfn.XLOOKUP(C31,'Median Quantity per product'!$D$4:$D$103,'Median Quantity per product'!$E$4:$E$103, "NA"),'Project Work - Data wrows'!D31) -> 18 | F31: 144 | G31: =IF(F31="",_xlfn.XLOOKUP(C31,'Price Averages'!$D$4:$D$103,'Price Averages'!$E$4:$E$103, "FALSE"), F31) -> 144 | H31: 36 | I31: =IF(H31="", _xlfn.XLOOKUP(C31, 'Cost Averages'!$D$4:$D$103,'Cost Averages'!$E$4:$E$103, "FALSE"),H31) -> 36 | J31: =E31*G31 -> 2592 | K31: =E31*I31 -> 648 | L31: =J31-K31 -> 1944 | M31: Satisfied | N31: CT-363 | O31: Creative & Technology | P31: 9.9471687 | Q31: =CHAR(64+(YEAR(A31)-2014)) -> C | R31: =YEAR(A31) -> 2017 | S31: =IF(Q31=CHAR(64 + (YEAR(A31) - 2014)), 0, 1) -> 0
A32: 43061.961 | B32: 17-2765 | C32: P004 | D32: 6 | E32: =IF(D32="", _xlfn.XLOOKUP(C32,'Median Quantity per product'!$D$4:$D$103,'Median Quantity per product'!$E$4:$E$103, "NA"),'Project Work - Data wrows'!D32) -> 6 | G32: =IF(F32="",_xlfn.XLOOKUP(C32,'Price Averages'!$D$4:$D$103,'Price Averages'!$E$4:$E$103, "FALSE"), F32) -> 189 | H32: 63 | I32: =IF(H32="", _xlfn.XLOOKUP(C32, 'Cost Averages'!$D$4:$D$103,'Cost Averages'!$E$4:$E$103, "FALSE"),H32) -> 63 | J32: =E32*G32 -> 1134 | K32: =E32*I32 -> 378 | L32: =J32-K32 -> 756 | M32: Satisfied | N32: CG-1804 | O32: Community & Government | P32: 12.045339 | Q32: =CHAR(64+(YEAR(A32)-2014)) -> C | R32: =YEAR(A32) -> 2017 | S32: =IF(Q32=CHAR(64 + (YEAR(A32) - 2014)), 0, 1) -> 0
A33: 43068.673 | B33: 17-4764 | C33: P005 | D33: 14 | E33: =IF(D33="", _xlfn.XLOOKUP(C33,'Median Quantity per product'!$D$4:$D$103,'Median Quantity per product'!$E$4:$E$103, "NA"),'Project Work - Data wrows'!D33) -> 14 | G33: =IF(F33="",_xlfn.XLOOKUP(C33,'Price Averages'!$D$4:$D$103,'Price Averages'!$E$4:$E$103, "FALSE"), F33) -> 76 | H33: 19 | I33: =IF(H33="", _xlfn.XLOOKUP(C33, 'Cost Averages'!$D$4:$D$103,'Cost Averages'!$E$4:$E$103, "FALSE"),H33) -> 19 | J33: =E33*G33 -> 1064 | K33: =E33*I33 -> 266 | L33: =J33-K33 -> 798 | M33: Satisfied | N33: CP-2846 | O33: Corporate & Professional | P33: 16.254955 | Q33: =CHAR(64+(YEAR(A33)-2014)) -> C | R33: =YEAR(A33) -> 2017 | S33: =IF(Q33=CHAR(64 + (YEAR(A33) - 2014)), 0, 1) -> 0
A34: 43061.027 | B34: 17-4263 | C34: P006 | D34: 13 | E34: =IF(D34="", _xlfn.XLOOKUP(C34,'Median Quantity per product'!$D$4:$D$103,'Median Quantity per product'!$E$4:$E$103, "NA"),'Project Work - Data wrows'!D34) -> 13 | F34: 38 | G34: =IF(F34="",_xlfn.XLOOKUP(C34,'Price Averages'!$D$4:$D$103,'Price Averages'!$E$4:$E$103, "FALSE"), F34) -> 38 | H34: 19 | I34: =IF(H34="", _xlfn.XLOOKUP(C34, 'Cost Averages'!$D$4:$D$103,'Cost Averages'!$E$4:$E$103, "FALSE"),H34) -> 19 | J34: =E34*G34 -> 494 | K34: =E34*I34 -> 247 | L34: =J34-K34 -> 247 | M34: Neither | N34: SR-9332 | O34: Sports & Recreation | P34: 12.701326 | Q34: =CHAR(64+(YEAR(A34)-2014)) -> C | R34: =YEAR(A34) -> 2017 | S34: =IF(Q34=CHAR(64 + (YEAR(A34) - 2014)), 0, 1) -> 0
A35: 43052.497 | B35: 17-4776 | C35: P007 | D35: 5 | E35: =IF(D35="", _xlfn.XLOOKUP(C35,'Median Quantity per product'!$D$4:$D$103,'Median Quantity per product'!$E$4:$E$103, "NA"),'Project Work - Data wrows'!D35) -> 5 | F35: 225 | G35: =IF(F35="",_xlfn.XLOOKUP(C35,'Price Averages'!$D$4:$D$103,'Price Averages'!$E$4:$E$103, "FALSE"), F35) -> 225 | H35: 75 | I35: =IF(H35="", _xlfn.XLOOKUP(C35, 'Cost Averages'!$D$4:$D$103,'Cost Averages'!$E$4:$E$103, "FALSE"),H35) -> 75 | J35: =E35*G35 -> 1125 | K35: =E35*I35 -> 375 | L35: =J35-K35 -> 750 | M35: Neither | N35: CG-1264 | O35: Community & Government | P35: 13.811877 | Q35: =CHAR(64+(YEAR(A35)-2014)) -> C | R35: =YEAR(A35) -> 2017 | S35: =IF(Q35=CHAR(64 + (YEAR(A35) - 2014)), 0, 1) -> 0
A36: 42980.801 | B36: 17-2114 | C36: P008 | D36: 6 | E36: =IF(D36="", _xlfn.XLOOKUP(C36,'Median Quantity per product'!$D$4:$D$103,'Median Quantity per product'!$E$4:$E$103, "NA"),'Project Work - Data wrows'!D36) -> 6 | F36: 225 | G36: =IF(F36="",_xlfn.XLOOKUP(C36,'Price Averages'!$D$4:$D$103,'Price Averages'!$E$4:$E$103, "FALSE"), F36) -> 225 | H36: 75 | I36: =IF(H36="", _xlfn.XLOOKUP(C36, 'Cost Averages'!$D$4:$D$103,'Cost Averages'!$E$4:$E$103, "FALSE"),H36) -> 75 | J36: =E36*G36 -> 1350 | K36: =E36*I36 -> 450 | L36: =J36-K36 -> 900 | M36: Neither | N36: FE-6482 | O36: Facilities & Services | P36: 11.769294 | Q36: =CHAR(64+(YEAR(A36)-2014)) -> C | R36: =YEAR(A36) -> 2017 | S36: =IF(Q36=CHAR(64 + (YEAR(A36) - 2014)), 0, 1) -> 0
A37: 43080.739 | B37: 17-2199 | C37: P009 | D37: 1 | E37: =IF(D37="", _xlfn.XLOOKUP(C37,'Median Quantity per product'!$D$4:$D$103,'Median Quantity per product'!$E$4:$E$103, "NA"),'Project Work - Data wrows'!D37) -> 1 | F37: 255 | G37: =IF(F37="",_xlfn.XLOOKUP(C37,'Price Averages'!$D$4:$D$103,'Price Averages'!$E$4:$E$103, "FALSE"), F37) -> 255 | H37: 85 | I37: =IF(H37="", _xlfn.XLOOKUP(C37, 'Cost Averages'!$D$4:$D$103,'Cost Averages'!$E$4:$E$103, "FALSE"),H37) -> 85 | J37: =E37*G37 -> 255 | K37: =E37*I37 -> 85 | L37: =J37-K37 -> 170 | M37: Neither | N37: FE-629 | O37: Facilities & Services | P37: 11.311041 | Q37: =CHAR(64+(YEAR(A37)-2014)) -> C | R37: =YEAR(A37) -> 2017 | S37: =IF(Q37=CHAR(64 + (YEAR(A37) - 2014)), 0, 1) -> 0
A38: 42868.389 | B38: 17-1371 | C38: P009 | D38: 15 | E38: =IF(D38="", _xlfn.XLOOKUP(C38,'Median Quantity per product'!$D$4:$D$103,'Median Quantity per product'!$E$4:$E$103, "NA"),'Project Work - Data wrows'!D38) -> 15 | F38: 255 | G38: =IF(F38="",_xlfn.XLOOKUP(C38,'Price Averages'!$D$4:$D$103,'Price Averages'!$E$4:$E$103, "FALSE"), F38) -> 255 | H38: 85 | I38: =IF(H38="", _xlfn.XLOOKUP(C38, 'Cost Averages'!$D$4:$D$103,'Cost Averages'!$E$4:$E$103, "FALSE"),H38) -> 85 | J38: =E38*G38 -> 3825 | K38: =E38*I38 -> 1275 | L38: =J38-K38 -> 2550 | M38: Satisfied | N38: SR-9198 | O38: Sports & Recreation | P38: 11.443504 | Q38: =CHAR(64+(YEAR(A38)-2014)) -> C | R38: =YEAR(A38) -> 2017 | S38: =IF(Q38=CHAR(64 + (YEAR(A38) - 2014)), 0, 1) -> 0
A39: 43001.986 | B39: 17-2322 | C39: P009 | D39: 16 | E39: =IF(D39="", _xlfn.XLOOKUP(C39,'Median Quantity per product'!$D$4:$D$103,'Median Quantity per product'!$E$4:$E$103, "NA"),'Project Work - Data wrows'!D39) -> 16 | G39: =IF(F39="",_xlfn.XLOOKUP(C39,'Price Averages'!$D$4:$D$103,'Price Averages'!$E$4:$E$103, "FALSE"), F39) -> 255 | H39: 85 | I39: =IF(H39="", _xlfn.XLOOKUP(C39, 'Cost Averages'!$D$4:$D$103,'Cost Averages'!$E$4:$E$103, "FALSE"),H39) -> 85 | J39: =E39*G39 -> 4080 | K39: =E39*I39 -> 1360 | L39: =J39-K39 -> 2720 | M39: Neither | N39: CP-2430 | O39: Corporate & Professional | P39: 11.274865 | Q39: =CHAR(64+(YEAR(A39)-2014)) -> C | R39: =YEAR(A39) -> 2017 | S39: =IF(Q39=CHAR(64 + (YEAR(A39) - 2014)), 0, 1) -> 0
A40: 43017.553 | B40: 17-1421 | C40: P010 | D40: 6 | E40: =IF(D40="", _xlfn.XLOOKUP(C40,'Median Quantity per product'!$D$4:$D$103,'Median Quantity per product'!$E$4:$E$103, "NA"),'Project Work - Data wrows'!D40) -> 6 | F40: 144 | G40: =IF(F40="",_xlfn.XLOOKUP(C40,'Price Averages'!$D$4:$D$103,'Price Averages'!$E$4:$E$103, "FALSE"), F40) -> 144 | H40: 36 | I40: =IF(H40="", _xlfn.XLOOKUP(C40, 'Cost Averages'!$D$4:$D$103,'Cost Averages'!$E$4:$E$103, "FALSE"),H40) -> 36 | J40: =E40*G40 -> 864 | K40: =E40*I40 -> 216 | L40: =J40-K40 -> 648 | M40: Neither | N40: CP-2380 | O40: Corporate & Professional | P40: 15.478388 | Q40: =CHAR(64+(YEAR(A40)-2014)) -> C | R40: =YEAR(A40) -> 2017 | S40: =IF(Q40=CHAR(64 + (YEAR(A40) - 2014)), 0, 1) -> 0
A41: 42799.219 | B41: 17-1285 | C41: P011 | D41: 2 | E41: =IF(D41="", _xlfn.XLOOKUP(C41,'Median Quantity per product'!$D$4:$D$103,'Median Quantity per product'!$E$4:$E$103, "NA"),'Project Work - Data wrows'!D41) -> 2 | F41: 264 | G41: =IF(F41="",_xlfn.XLOOKUP(C41,'Price Averages'!$D$4:$D$103,'Price Averages'!$E$4:$E$103, "FALSE"), F41) -> 264 | H41: 88 | I41: =IF(H41="", _xlfn.XLOOKUP(C41, 'Cost Averages'!$D$4:$D$103,'Cost Averages'!$E$4:$E$103, "FALSE"),H41) -> 88 | J41: =E41*G41 -> 528 | K41: =E41*I41 -> 176 | L41: =J41-K41 -> 352 | M41: Satisfied | N41: CP-2251 | O41: Corporate & Professional | P41: 11.003497 | Q41: =CHAR(64+(YEAR(A41)-2014)) -> C | R41: =YEAR(A41) -> 2017 | S41: =IF(Q41=CHAR(64 + (YEAR(A41) - 2014)), 0, 1) -> 0
A42: 42911.837 | B42: 17-1345 | C42: P011 | D42: 12 | E42: =IF(D42="", _xlfn.XLOOKUP(C42,'Median Quantity per product'!$D$4:$D$103,'Median Quantity per product'!$E$4:$E$103, "NA"),'Project Work - Data wrows'!D42) -> 12 | F42: 264 | G42: =IF(F42="",_xlfn.XLOOKUP(C42,'Price Averages'!$D$4:$D$103,'Price Averages'!$E$4:$E$103, "FALSE"), F42) -> 264 | H42: 88 | I42: =IF(H42="", _xlfn.XLOOKUP(C42, 'Cost Averages'!$D$4:$D$103,'Cost Averages'!$E$4:$E$103, "FALSE"),H42) -> 88 | J42: =E42*G42 -> 3168 | K42: =E42*I42 -> 1056 | L42: =J42-K42 -> 2112 | M42: Satisfied | N42: CT-3737 | O42: Creative & Technology | P42: 8.0758316 | Q42: =CHAR(64+(YEAR(A42)-2014)) -> C | R42: =YEAR(A42) -> 2017 | S42: =IF(Q42=CHAR(64 + (YEAR(A42) - 2014)), 0, 1) -> 0
A43: 42920.589 | B43: 17-2317 | C43: P011 | D43: 16 | E43: =IF(D43="", _xlfn.XLOOKUP(C43,'Median Quantity per product'!$D$4:$D$103,'Median Quantity per product'!$E$4:$E$103, "NA"),'Project Work - Data wrows'!D43) -> 16 | F43: 264 | G43: =IF(F43="",_xlfn.XLOOKUP(C43,'Price Averages'!$D$4:$D$103,'Price Averages'!$E$4:$E$103, "FALSE"), F43) -> 264 | H43: 88 | I43: =IF(H43="", _xlfn.XLOOKUP(C43, 'Cost Averages'!$D$4:$D$103,'Cost Averages'!$E$4:$E$103, "FALSE"),H43) -> 88 | J43: =E43*G43 -> 4224 | K43: =E43*I43 -> 1408 | L43: =J43-K43 -> 2816 | M43: Neither | N43: HS-7670 | O43: Healthcare & Safety | P43: 8.7741864 | Q43: =CHAR(64+(YEAR(A43)-2014)) -> C | R43: =YEAR(A43) -> 2017 | S43: =IF(Q43=CHAR(64 + (YEAR(A43) - 2014)), 0, 1) -> 0
A44: 42913.57 | B44: 17-2043 | C44: P012 | D44: 13 | E44: =IF(D44="", _xlfn.XLOOKUP(C44,'Median Quantity per product'!$D$4:$D$103,'Median Quantity per product'!$E$4:$E$103, "NA"),'Project Work - Data wrows'!D44) -> 13 | F44: 30 | G44: =IF(F44="",_xlfn.XLOOKUP(C44,'Price Averages'!$D$4:$D$103,'Price Averages'!$E$4:$E$103, "FALSE"), F44) -> 30 | I44: =IF(H44="", _xlfn.XLOOKUP(C44, 'Cost Averages'!$D$4:$D$103,'Cost Averages'!$E$4:$E$103, "FALSE"),H44) -> 15 | J44: =E44*G44 -> 390 | K44: =E44*I44 -> 195 | L44: =J44-K44 -> 195 | M44: Satisfied | N44: HS-735 | O44: Healthcare & Safety | P44: 9.8892508 | Q44: =CHAR(64+(YEAR(A44)-2014)) -> C | R44: =YEAR(A44) -> 2017 | S44: =IF(Q44=CHAR(64 + (YEAR(A44) - 2014)), 0, 1) -> 0
A45: 43085.869 | B45: 17-3764 | C45: P012 | D45: 16 | E45: =IF(D45="", _xlfn.XLOOKUP(C45,'Median Quantity per product'!$D$4:$D$103,'Median Quantity per product'!$E$4:$E$103, "NA"),'Project Work - Data wrows'!D45) -> 16 | F45: 30 | G45: =IF(F45="",_xlfn.XLOOKUP(C45,'Price Averages'!$D$4:$D$103,'Price Averages'!$E$4:$E$103, "FALSE"), F45) -> 30 | H45: 15 | I45: =IF(H45="", _xlfn.XLOOKUP(C45, 'Cost Averages'!$D$4:$D$103,'Cost Averages'!$E$4:$E$103, "FALSE"),H45) -> 15 | J45: =E45*G45 -> 480 | K45: =E45*I45 -> 240 | L45: =J45-K45 -> 240 | M45: Neither | N45: CG-1634 | O45: Community & Government | P45: 9.2053706 | Q45: =CHAR(64+(YEAR(A45)-2014)) -> C | R45: =YEAR(A45) -> 2017 | S45: =IF(Q45=CHAR(64 + (YEAR(A45) - 2014)), 0, 1) -> 0
A46: 43072.093 | B46: 17-2741 | C46: P013 | D46: 3 | E46: =IF(D46="", _xlfn.XLOOKUP(C46,'Median Quantity per product'!$D$4:$D$103,'Median Quantity per product'!$E$4:$E$103, "NA"),'Project Work - Data wrows'!D46) -> 3 | G46: =IF(F46="",_xlfn.XLOOKUP(C46,'Price Averages'!$D$4:$D$103,'Price Averages'!$E$4:$E$103, "FALSE"), F46) -> 58 | H46: 29 | I46: =IF(H46="", _xlfn.XLOOKUP(C46, 'Cost Averages'!$D$4:$D$103,'Cost Averages'!$E$4:$E$103, "FALSE"),H46) -> 29 | J46: =E46*G46 -> 174 | K46: =E46*I46 -> 87 | L46: =J46-K46 -> 87 | M46: Satisfied | N46: EE-4361 | O46: Education | P46: 14.760829 | Q46: =CHAR(64+(YEAR(A46)-2014)) -> C | R46: =YEAR(A46) -> 2017 | S46: =IF(Q46=CHAR(64 + (YEAR(A46) - 2014)), 0, 1) -> 0
A47: 42968.295 | B47: 17-1392 | C47: P013 | D47: 16 | E47: =IF(D47="", _xlfn.XLOOKUP(C47,'Median Quantity per product'!$D$4:$D$103,'Median Quantity per product'!$E$4:$E$103, "NA"),'Project Work - Data wrows'!D47) -> 16 | G47: =IF(F47="",_xlfn.XLOOKUP(C47,'Price Averages'!$D$4:$D$103,'Price Averages'!$E$4:$E$103, "FALSE"), F47) -> 58 | H47: 29 | I47: =IF(H47="", _xlfn.XLOOKUP(C47, 'Cost Averages'!$D$4:$D$103,'Cost Averages'!$E$4:$E$103, "FALSE"),H47) -> 29 | J47: =E47*G47 -> 928 | K47: =E47*I47 -> 464 | L47: =J47-K47 -> 464 | M47: Satisfied | N47: CP-2216 | O47: Corporate & Professional | P47: 13.299525 | Q47: =CHAR(64+(YEAR(A47)-2014)) -> C | R47: =YEAR(A47) -> 2017 | S47: =IF(Q47=CHAR(64 + (YEAR(A47) - 2014)), 0, 1) -> 0
A48: 42930.42 | B48: 17-2584 | C48: P015 | D48: 9 | E48: =IF(D48="", _xlfn.XLOOKUP(C48,'Median Quantity per product'!$D$4:$D$103,'Median Quantity per product'!$E$4:$E$103, "NA"),'Project Work - Data wrows'!D48) -> 9 | F48: 176 | G48: =IF(F48="",_xlfn.XLOOKUP(C48,'Price Averages'!$D$4:$D$103,'Price Averages'!$E$4:$E$103, "FALSE"), F48) -> 176 | H48: 88 | I48: =IF(H48="", _xlfn.XLOOKUP(C48, 'Cost Averages'!$D$4:$D$103,'Cost Averages'!$E$4:$E$103, "FALSE"),H48) -> 88 | J48: =E48*G48 -> 1584 | K48: =E48*I48 -> 792 | L48: =J48-K48 -> 792 | M48: Dissatisfied | N48: SR-9989 | O48: Sports & Recreation | P48: 15.602184 | Q48: =CHAR(64+(YEAR(A48)-2014)) -> C | R48: =YEAR(A48) -> 2017 | S48: =IF(Q48=CHAR(64 + (YEAR(A48) - 2014)), 0, 1) -> 0
A49: 42997.842 | B49: 17-3573 | C49: P016 | D49: 17 | E49: =IF(D49="", _xlfn.XLOOKUP(C49,'Median Quantity per product'!$D$4:$D$103,'Median Quantity per product'!$E$4:$E$103, "NA"),'Project Work - Data wrows'!D49) -> 17 | F49: 110 | G49: =IF(F49="",_xlfn.XLOOKUP(C49,'Price Averages'!$D$4:$D$103,'Price Averages'!$E$4:$E$103, "FALSE"), F49) -> 110 | H49: 55 | I49: =IF(H49="", _xlfn.XLOOKUP(C49, 'Cost Averages'!$D$4:$D$103,'Cost Averages'!$E$4:$E$103, "FALSE"),H49) -> 55 | J49: =E49*G49 -> 1870 | K49: =E49*I49 -> 935 | L49: =J49-K49 -> 935 | M49: Neither | N49: CT-3618 | O49: Creative & Technology | P49: 11.995407 | Q49: =CHAR(64+(YEAR(A49)-2014)) -> C | R49: =YEAR(A49) -> 2017 | S49: =IF(Q49=CHAR(64 + (YEAR(A49) - 2014)), 0, 1) -> 0
A50: 43100.802 | B50: 17-2848 | C50: P018 | D50: 18 | E50: =IF(D50="", _xlfn.XLOOKUP(C50,'Median Quantity per product'!$D$4:$D$103,'Median Quantity per product'!$E$4:$E$103, "NA"),'Project Work - Data wrows'!D50) -> 18 | F50: 108 | G50: =IF(F50="",_xlfn.XLOOKUP(C50,'Price Averages'!$D$4:$D$103,'Price Averages'!$E$4:$E$103, "FALSE"), F50) -> 108 | H50: 54 | I50: =IF(H50="", _xlfn.XLOOKUP(C50, 'Cost Averages'!$D$4:$D$103,'Cost Averages'!$E$4:$E$103, "FALSE"),H50) -> 54 | J50: =E50*G50 -> 1944 | K50: =E50*I50 -> 972 | L50: =J50-K50 -> 972 | M50: Neither | N50: HS-7862 | O50: Healthcare & Safety | P50: 14.423323 | Q50: =CHAR(64+(YEAR(A50)-2014)) -> C | R50: =YEAR(A50) -> 2017 | S50: =IF(Q50=CHAR(64 + (YEAR(A50) - 2014)), 0, 1) -> 0
A51: 42923.53 | B51: 17-3969 | C51: P019 | D51: 6 | E51: =IF(D51="", _xlfn.XLOOKUP(C51,'Median Quantity per product'!$D$4:$D$103,'Median Quantity per product'!$E$4:$E$103, "NA"),'Project Work - Data wrows'!D51) -> 6 | G51: =IF(F51="",_xlfn.XLOOKUP(C51,'Price Averages'!$D$4:$D$103,'Price Averages'!$E$4:$E$103, "FALSE"), F51) -> 308 | H51: 77 | I51: =IF(H51="", _xlfn.XLOOKUP(C51, 'Cost Averages'!$D$4:$D$103,'Cost Averages'!$E$4:$E$103, "FALSE"),H51) -> 77 | J51: =E51*G51 -> 1848 | K51: =E51*I51 -> 462 | L51: =J51-K51 -> 1386 | M51: Neither | N51: CP-2862 | O51: Corporate & Professional | P51: 14.370283 | Q51: =CHAR(64+(YEAR(A51)-2014)) -> C | R51: =YEAR(A51) -> 2017 | S51: =IF(Q51=CHAR(64 + (YEAR(A51) - 2014)), 0, 1) -> 0
A52: 43076.454 | B52: 17-2090 | C52: P019 | D52: 10 | E52: =IF(D52="", _xlfn.XLOOKUP(C52,'Median Quantity per product'!$D$4:$D$103,'Median Quantity per product'!$E$4:$E$103, "NA"),'Project Work - Data wrows'!D52) -> 10 | G52: =IF(F52="",_xlfn.XLOOKUP(C52,'Price Averages'!$D$4:$D$103,'Price Averages'!$E$4:$E$103, "FALSE"), F52) -> 308 | H52: 77 | I52: =IF(H52="", _xlfn.XLOOKUP(C52, 'Cost Averages'!$D$4:$D$103,'Cost Averages'!$E$4:$E$103, "FALSE"),H52) -> 77 | J52: =E52*G52 -> 3080 | K52: =E52*I52 -> 770 | L52: =J52-K52 -> 2310 | M52: Neither | N52: FE-685 | O52: Facilities & Services | P52: 10.95659 | Q52: =CHAR(64+(YEAR(A52)-2014)) -> C | R52: =YEAR(A52) -> 2017 | S52: =IF(Q52=CHAR(64 + (YEAR(A52) - 2014)), 0, 1) -> 0
A53: 43014.745 | B53: 17-4372 | C53: P020 | D53: 13 | E53: =IF(D53="", _xlfn.XLOOKUP(C53,'Median Quantity per product'!$D$4:$D$103,'Median Quantity per product'!$E$4:$E$103, "NA"),'Project Work - Data wrows'!D53) -> 13 | F53: 180 | G53: =IF(F53="",_xlfn.XLOOKUP(C53,'Price Averages'!$D$4:$D$103,'Price Averages'!$E$4:$E$103, "FALSE"), F53) -> 180 | H53: 45 | I53: =IF(H53="", _xlfn.XLOOKUP(C53, 'Cost Averages'!$D$4:$D$103,'Cost Averages'!$E$4:$E$103, "FALSE"),H53) -> 45 | J53: =E53*G53 -> 2340 | K53: =E53*I53 -> 585 | L53: =J53-K53 -> 1755 | M53: Dissatisfied | N53: EE-4917 | O53: Education | P53: 11.756375 | Q53: =CHAR(64+(YEAR(A53)-2014)) -> C | R53: =YEAR(A53) -> 2017 | S53: =IF(Q53=CHAR(64 + (YEAR(A53) - 2014)), 0, 1) -> 0
A54: 42985.284 | B54: 17-3087 | C54: P020 | D54: 16 | E54: =IF(D54="", _xlfn.XLOOKUP(C54,'Median Quantity per product'!$D$4:$D$103,'Median Quantity per product'!$E$4:$E$103, "NA"),'Project Work - Data wrows'!D54) -> 16 | F54: 180 | G54: =IF(F54="",_xlfn.XLOOKUP(C54,'Price Averages'!$D$4:$D$103,'Price Averages'!$E$4:$E$103, "FALSE"), F54) -> 180 | H54: 45 | I54: =IF(H54="", _xlfn.XLOOKUP(C54, 'Cost Averages'!$D$4:$D$103,'Cost Averages'!$E$4:$E$103, "FALSE"),H54) -> 45 | J54: =E54*G54 -> 2880 | K54: =E54*I54 -> 720 | L54: =J54-K54 -> 2160 | M54: Dissatisfied | N54: CT-3754 | O54: Creative & Technology | P54: 8.2871811 | Q54: =CHAR(64+(YEAR(A54)-2014)) -> C | R54: =YEAR(A54) -> 2017 | S54: =IF(Q54=CHAR(64 + (YEAR(A54) - 2014)), 0, 1) -> 0
A55: 42998.156 | B55: 17-2218 | C55: P021 | D55: 7 | E55: =IF(D55="", _xlfn.XLOOKUP(C55,'Median Quantity per product'!$D$4:$D$103,'Median Quantity per product'!$E$4:$E$103, "NA"),'Project Work - Data wrows'!D55) -> 7 | F55: 207 | G55: =IF(F55="",_xlfn.XLOOKUP(C55,'Price Averages'!$D$4:$D$103,'Price Averages'!$E$4:$E$103, "FALSE"), F55) -> 207 | H55: 69 | I55: =IF(H55="", _xlfn.XLOOKUP(C55, 'Cost Averages'!$D$4:$D$103,'Cost Averages'!$E$4:$E$103, "FALSE"),H55) -> 69 | J55: =E55*G55 -> 1449 | K55: =E55*I55 -> 483 | L55: =J55-K55 -> 966 | M55: Dissatisfied | N55: HS-7607 | O55: Healthcare & Safety | P55: 11.563725 | Q55: =CHAR(64+(YEAR(A55)-2014)) -> C | R55: =YEAR(A55) -> 2017 | S55: =IF(Q55=CHAR(64 + (YEAR(A55) - 2014)), 0, 1) -> 0
A56: 42922.594 | B56: 17-4707 | C56: P023 | D56: 12 | E56: =IF(D56="", _xlfn.XLOOKUP(C56,'Median Quantity per product'!$D$4:$D$103,'Median Quantity per product'!$E$4:$E$103, "NA"),'Project Work - Data wrows'!D56) -> 12 | F56: 126 | G56: =IF(F56="",_xlfn.XLOOKUP(C56,'Price Averages'!$D$4:$D$103,'Price Averages'!$E$4:$E$103, "FALSE"), F56) -> 126 | H56: 42 | I56: =IF(H56="", _xlfn.XLOOKUP(C56, 'Cost Averages'!$D$4:$D$103,'Cost Averages'!$E$4:$E$103, "FALSE"),H56) -> 42 | J56: =E56*G56 -> 1512 | K56: =E56*I56 -> 504 | L56: =J56-K56 -> 1008 | M56: Satisfied | N56: CG-1316 | O56: Community & Government | P56: 15.45886 | Q56: =CHAR(64+(YEAR(A56)-2014)) -> C | R56: =YEAR(A56) -> 2017 | S56: =IF(Q56=CHAR(64 + (YEAR(A56) - 2014)), 0, 1) -> 0
A57: 42974.019 | B57: 17-3997 | C57: P024 | D57: 8 | E57: =IF(D57="", _xlfn.XLOOKUP(C57,'Median Quantity per product'!$D$4:$D$103,'Median Quantity per product'!$E$4:$E$103, "NA"),'Project Work - Data wrows'!D57) -> 8 | F57: 66 | G57: =IF(F57="",_xlfn.XLOOKUP(C57,'Price Averages'!$D$4:$D$103,'Price Averages'!$E$4:$E$103, "FALSE"), F57) -> 66 | H57: 33 | I57: =IF(H57="", _xlfn.XLOOKUP(C57, 'Cost Averages'!$D$4:$D$103,'Cost Averages'!$E$4:$E$103, "FALSE"),H57) -> 33 | J57: =E57*G57 -> 528 | K57: =E57*I57 -> 264 | L57: =J57-K57 -> 264 | M57: Neither | N57: FE-6323 | O57: Facilities & Services | P57: 10.523528 | Q57: =CHAR(64+(YEAR(A57)-2014)) -> C | R57: =YEAR(A57) -> 2017 | S57: =IF(Q57=CHAR(64 + (YEAR(A57) - 2014)), 0, 1) -> 0
A58: 42911.018 | B58: 17-1860 | C58: P026 | D58: 7 | E58: =IF(D58="", _xlfn.XLOOKUP(C58,'Median Quantity per product'!$D$4:$D$103,'Median Quantity per product'!$E$4:$E$103, "NA"),'Project Work - Data wrows'!D58) -> 7 | F58: 280 | G58: =IF(F58="",_xlfn.XLOOKUP(C58,'Price Averages'!$D$4:$D$103,'Price Averages'!$E$4:$E$103, "FALSE"), F58) -> 280 | H58: 70 | I58: =IF(H58="", _xlfn.XLOOKUP(C58, 'Cost Averages'!$D$4:$D$103,'Cost Averages'!$E$4:$E$103, "FALSE"),H58) -> 70 | J58: =E58*G58 -> 1960 | K58: =E58*I58 -> 490 | L58: =J58-K58 -> 1470 | M58: Dissatisfied | N58: FE-6898 | O58: Facilities & Services | P58: 12.514998 | Q58: =CHAR(64+(YEAR(A58)-2014)) -> C | R58: =YEAR(A58) -> 2017 | S58: =IF(Q58=CHAR(64 + (YEAR(A58) - 2014)), 0, 1) -> 0
A59: 43010.588 | B59: 17-4392 | C59: P026 | D59: 8 | E59: =IF(D59="", _xlfn.XLOOKUP(C59,'Median Quantity per product'!$D$4:$D$103,'Median Quantity per product'!$E$4:$E$103, "NA"),'Project Work - Data wrows'!D59) -> 8 | F59: 280 | G59: =IF(F59="",_xlfn.XLOOKUP(C59,'Price Averages'!$D$4:$D$103,'Price Averages'!$E$4:$E$103, "FALSE"), F59) -> 280 | H59: 70 | I59: =IF(H59="", _xlfn.XLOOKUP(C59, 'Cost Averages'!$D$4:$D$103,'Cost Averages'!$E$4:$E$103, "FALSE"),H59) -> 70 | J59: =E59*G59 -> 2240 | K59: =E59*I59 -> 560 | L59: =J59-K59 -> 1680 | M59: Dissatisfied | N59: FE-6919 | O59: Facilities & Services | P59: 13.37808 | Q59: =CHAR(64+(YEAR(A59)-2014)) -> C | R59: =YEAR(A59) -> 2017 | S59: =IF(Q59=CHAR(64 + (YEAR(A59) - 2014)), 0, 1) -> 0
A60: 42889.125 | B60: 17-4153 | C60: P027 | D60: 2 | E60: =IF(D60="", _xlfn.XLOOKUP(C60,'Median Quantity per product'!$D$4:$D$103,'Median Quantity per product'!$E$4:$E$103, "NA"),'Project Work - Data wrows'!D60) -> 2 | F60: 140 | G60: =IF(F60="",_xlfn.XLOOKUP(C60,'Price Averages'!$D$4:$D$103,'Price Averages'!$E$4:$E$103, "FALSE"), F60) -> 140 | H60: 70 | I60: =IF(H60="", _xlfn.XLOOKUP(C60, 'Cost Averages'!$D$4:$D$103,'Cost Averages'!$E$4:$E$103, "FALSE"),H60) -> 70 | J60: =E60*G60 -> 280 | K60: =E60*I60 -> 140 | L60: =J60-K60 -> 140 | M60: Dissatisfied | N60: CT-3920 | O60: Creative & Technology | P60: 14.661477 | Q60: =CHAR(64+(YEAR(A60)-2014)) -> C | R60: =YEAR(A60) -> 2017 | S60: =IF(Q60=CHAR(64 + (YEAR(A60) - 2014)), 0, 1) -> 0
A61: 43007.042 | B61: 17-1266 | C61: P029 | D61: 3 | E61: =IF(D61="", _xlfn.XLOOKUP(C61,'Median Quantity per product'!$D$4:$D$103,'Median Quantity per product'!$E$4:$E$103, "NA"),'Project Work - Data wrows'!D61) -> 3 | G61: =IF(F61="",_xlfn.XLOOKUP(C61,'Price Averages'!$D$4:$D$103,'Price Averages'!$E$4:$E$103, "FALSE"), F61) -> 300 | H61: 75 | I61: =IF(H61="", _xlfn.XLOOKUP(C61, 'Cost Averages'!$D$4:$D$103,'Cost Averages'!$E$4:$E$103, "FALSE"),H61) -> 75 | J61: =E61*G61 -> 900 | K61: =E61*I61 -> 225 | L61: =J61-K61 -> 675 | M61: Dissatisfied | N61: CT-3955 | O61: Creative & Technology | P61: 11.130819 | Q61: =CHAR(64+(YEAR(A61)-2014)) -> C | R61: =YEAR(A61) -> 2017 | S61: =IF(Q61=CHAR(64 + (YEAR(A61) - 2014)), 0, 1) -> 0
A62: 42960.917 | B62: 17-3732 | C62: P031 | D62: 6 | E62: =IF(D62="", _xlfn.XLOOKUP(C62,'Median Quantity per product'!$D$4:$D$103,'Median Quantity per product'!$E$4:$E$103, "NA"),'Project Work - Data wrows'!D62) -> 6 | F62: 146 | G62: =IF(F62="",_xlfn.XLOOKUP(C62,'Price Averages'!$D$4:$D$103,'Price Averages'!$E$4:$E$103, "FALSE"), F62) -> 146 | H62: 73 | I62: =IF(H62="", _xlfn.XLOOKUP(C62, 'Cost Averages'!$D$4:$D$103,'Cost Averages'!$E$4:$E$103, "FALSE"),H62) -> 73 | J62: =E62*G62 -> 876 | K62: =E62*I62 -> 438 | L62: =J62-K62 -> 438 | M62: Neither | N62: CG-1367 | O62: Community & Government | P62: 15.604305 | Q62: =CHAR(64+(YEAR(A62)-2014)) -> C | R62: =YEAR(A62) -> 2017 | S62: =IF(Q62=CHAR(64 + (YEAR(A62) - 2014)), 0, 1) -> 0
A63: 43006.7 | B63: 17-1767 | C63: P031 | D63: 14 | E63: =IF(D63="", _xlfn.XLOOKUP(C63,'Median Quantity per product'!$D$4:$D$103,'Median Quantity per product'!$E$4:$E$103, "NA"),'Project Work - Data wrows'!D63) -> 14 | F63: 146 | G63: =IF(F63="",_xlfn.XLOOKUP(C63,'Price Averages'!$D$4:$D$103,'Price Averages'!$E$4:$E$103, "FALSE"), F63) -> 146 | H63: 73 | I63: =IF(H63="", _xlfn.XLOOKUP(C63, 'Cost Averages'!$D$4:$D$103,'Cost Averages'!$E$4:$E$103, "FALSE"),H63) -> 73 | J63: =E63*G63 -> 2044 | K63: =E63*I63 -> 1022 | L63: =J63-K63 -> 1022 | M63: Neither | N63: FE-621 | O63: Facilities & Services | P63: 11.410471 | Q63: =CHAR(64+(YEAR(A63)-2014)) -> C | R63: =YEAR(A63) -> 2017 | S63: =IF(Q63=CHAR(64 + (YEAR(A63) - 2014)), 0, 1) -> 0
A64: 43042.65 | B64: 17-1955 | C64: P032 | D64: 14 | E64: =IF(D64="", _xlfn.XLOOKUP(C64,'Median Quantity per product'!$D$4:$D$103,'Median Quantity per product'!$E$4:$E$103, "NA"),'Project Work - Data wrows'!D64) -> 14 | F64: 92 | G64: =IF(F64="",_xlfn.XLOOKUP(C64,'Price Averages'!$D$4:$D$103,'Price Averages'!$E$4:$E$103, "FALSE"), F64) -> 92 | H64: 46 | I64: =IF(H64="", _xlfn.XLOOKUP(C64, 'Cost Averages'!$D$4:$D$103,'Cost Averages'!$E$4:$E$103, "FALSE"),H64) -> 46 | J64: =E64*G64 -> 1288 | K64: =E64*I64 -> 644 | L64: =J64-K64 -> 644 | M64: Satisfied | N64: CP-2889 | O64: Corporate & Professional | P64: 10.248947 | Q64: =CHAR(64+(YEAR(A64)-2014)) -> C | R64: =YEAR(A64) -> 2017 | S64: =IF(Q64=CHAR(64 + (YEAR(A64) - 2014)), 0, 1) -> 0
A65: 43008.135 | B65: 17-2606 | C65: P034 | D65: 1 | E65: =IF(D65="", _xlfn.XLOOKUP(C65,'Median Quantity per product'!$D$4:$D$103,'Median Quantity per product'!$E$4:$E$103, "NA"),'Project Work - Data wrows'!D65) -> 1 | F65: 114 | G65: =IF(F65="",_xlfn.XLOOKUP(C65,'Price Averages'!$D$4:$D$103,'Price Averages'!$E$4:$E$103, "FALSE"), F65) -> 114 | H65: 57 | I65: =IF(H65="", _xlfn.XLOOKUP(C65, 'Cost Averages'!$D$4:$D$103,'Cost Averages'!$E$4:$E$103, "FALSE"),H65) -> 57 | J65: =E65*G65 -> 114 | K65: =E65*I65 -> 57 | L65: =J65-K65 -> 57 | M65: Neither | N65: CT-3471 | O65: Creative & Technology | P65: 13.537351 | Q65: =CHAR(64+(YEAR(A65)-2014)) -> C | R65: =YEAR(A65) -> 2017 | S65: =IF(Q65=CHAR(64 + (YEAR(A65) - 2014)), 0, 1) -> 0
A66: 43074.481 | B66: 17-4852 | C66: P034 | D66: 3 | E66: =IF(D66="", _xlfn.XLOOKUP(C66,'Median Quantity per product'!$D$4:$D$103,'Median Quantity per product'!$E$4:$E$103, "NA"),'Project Work - Data wrows'!D66) -> 3 | G66: =IF(F66="",_xlfn.XLOOKUP(C66,'Price Averages'!$D$4:$D$103,'Price Averages'!$E$4:$E$103, "FALSE"), F66) -> 114 | H66: 57 | I66: =IF(H66="", _xlfn.XLOOKUP(C66, 'Cost Averages'!$D$4:$D$103,'Cost Averages'!$E$4:$E$103, "FALSE"),H66) -> 57 | J66: =E66*G66 -> 342 | K66: =E66*I66 -> 171 | L66: =J66-K66 -> 171 | M66: Satisfied | N66: EE-4140 | O66: Education | P66: 11.710936 | Q66: =CHAR(64+(YEAR(A66)-2014)) -> C | R66: =YEAR(A66) -> 2017 | S66: =IF(Q66=CHAR(64 + (YEAR(A66) - 2014)), 0, 1) -> 0
A67: 42986.391 | B67: 17-3063 | C67: P035 | D67: 8 | E67: =IF(D67="", _xlfn.XLOOKUP(C67,'Median Quantity per product'!$D$4:$D$103,'Median Quantity per product'!$E$4:$E$103, "NA"),'Project Work - Data wrows'!D67) -> 8 | G67: =IF(F67="",_xlfn.XLOOKUP(C67,'Price Averages'!$D$4:$D$103,'Price Averages'!$E$4:$E$103, "FALSE"), F67) -> 144 | H67: 48 | I67: =IF(H67="", _xlfn.XLOOKUP(C67, 'Cost Averages'!$D$4:$D$103,'Cost Averages'!$E$4:$E$103, "FALSE"),H67) -> 48 | J67: =E67*G67 -> 1152 | K67: =E67*I67 -> 384 | L67: =J67-K67 -> 768 | M67: Neither | N67: SR-9105 | O67: Sports & Recreation | P67: 11.072271 | Q67: =CHAR(64+(YEAR(A67)-2014)) -> C | R67: =YEAR(A67) -> 2017 | S67: =IF(Q67=CHAR(64 + (YEAR(A67) - 2014)), 0, 1) -> 0
A68: 42968.905 | B68: 17-3578 | C68: P040 | D68: 2 | E68: =IF(D68="", _xlfn.XLOOKUP(C68,'Median Quantity per product'!$D$4:$D$103,'Median Quantity per product'!$E$4:$E$103, "NA"),'Project Work - Data wrows'!D68) -> 2 | F68: 160 | G68: =IF(F68="",_xlfn.XLOOKUP(C68,'Price Averages'!$D$4:$D$103,'Price Averages'!$E$4:$E$103, "FALSE"), F68) -> 160 | H68: 80 | I68: =IF(H68="", _xlfn.XLOOKUP(C68, 'Cost Averages'!$D$4:$D$103,'Cost Averages'!$E$4:$E$103, "FALSE"),H68) -> 80 | J68: =E68*G68 -> 320 | K68: =E68*I68 -> 160 | L68: =J68-K68 -> 160 | M68: Neither | N68: FE-6631 | O68: Facilities & Services | P68: 8.1352386 | Q68: =CHAR(64+(YEAR(A68)-2014)) -> C | R68: =YEAR(A68) -> 2017 | S68: =IF(Q68=CHAR(64 + (YEAR(A68) - 2014)), 0, 1) -> 0
A69: 42987.056 | B69: 17-4787 | C69: P040 | D69: 5 | E69: =IF(D69="", _xlfn.XLOOKUP(C69,'Median Quantity per product'!$D$4:$D$103,'Median Quantity per product'!$E$4:$E$103, "NA"),'Project Work - Data wrows'!D69) -> 5 | F69: 160 | G69: =IF(F69="",_xlfn.XLOOKUP(C69,'Price Averages'!$D$4:$D$103,'Price Averages'!$E$4:$E$103, "FALSE"), F69) -> 160 | H69: 80 | I69: =IF(H69="", _xlfn.XLOOKUP(C69, 'Cost Averages'!$D$4:$D$103,'Cost Averages'!$E$4:$E$103, "FALSE"),H69) -> 80 | J69: =E69*G69 -> 800 | K69: =E69*I69 -> 400 | L69: =J69-K69 -> 400 | M69: Dissatisfied | N69: CG-1580 | O69: Community & Government | P69: 8.8169309 | Q69: =CHAR(64+(YEAR(A69)-2014)) -> C | R69: =YEAR(A69) -> 2017 | S69: =IF(Q69=CHAR(64 + (YEAR(A69) - 2014)), 0, 1) -> 0
A70: 43060.662 | B70: 17-4293 | C70: P040 | D70: 6 | E70: =IF(D70="", _xlfn.XLOOKUP(C70,'Median Quantity per product'!$D$4:$D$103,'Median Quantity per product'!$E$4:$E$103, "NA"),'Project Work - Data wrows'!D70) -> 6 | F70: 160 | G70: =IF(F70="",_xlfn.XLOOKUP(C70,'Price Averages'!$D$4:$D$103,'Price Averages'!$E$4:$E$103, "FALSE"), F70) -> 160 | H70: 80 | I70: =IF(H70="", _xlfn.XLOOKUP(C70, 'Cost Averages'!$D$4:$D$103,'Cost Averages'!$E$4:$E$103, "FALSE"),H70) -> 80 | J70: =E70*G70 -> 960 | K70: =E70*I70 -> 480 | L70: =J70-K70 -> 480 | M70: Satisfied | N70: FE-6482 | O70: Facilities & Services | P70: 11.769294 | Q70: =CHAR(64+(YEAR(A70)-2014)) -> C | R70: =YEAR(A70) -> 2017 | S70: =IF(Q70=CHAR(64 + (YEAR(A70) - 2014)), 0, 1) -> 0
A71: 42946.785 | B71: 17-2486 | C71: P040 | D71: 9 | E71: =IF(D71="", _xlfn.XLOOKUP(C71,'Median Quantity per product'!$D$4:$D$103,'Median Quantity per product'!$E$4:$E$103, "NA"),'Project Work - Data wrows'!D71) -> 9 | F71: 160 | G71: =IF(F71="",_xlfn.XLOOKUP(C71,'Price Averages'!$D$4:$D$103,'Price Averages'!$E$4:$E$103, "FALSE"), F71) -> 160 | H71: 80 | I71: =IF(H71="", _xlfn.XLOOKUP(C71, 'Cost Averages'!$D$4:$D$103,'Cost Averages'!$E$4:$E$103, "FALSE"),H71) -> 80 | J71: =E71*G71 -> 1440 | K71: =E71*I71 -> 720 | L71: =J71-K71 -> 720 | M71: Dissatisfied | N71: FE-6944 | O71: Facilities & Services | P71: 13.518413 | Q71: =CHAR(64+(YEAR(A71)-2014)) -> C | R71: =YEAR(A71) -> 2017 | S71: =IF(Q71=CHAR(64 + (YEAR(A71) - 2014)), 0, 1) -> 0
A72: 43069.717 | B72: 17-3724 | C72: P041 | D72: 13 | E72: =IF(D72="", _xlfn.XLOOKUP(C72,'Median Quantity per product'!$D$4:$D$103,'Median Quantity per product'!$E$4:$E$103, "NA"),'Project Work - Data wrows'!D72) -> 13 | G72: =IF(F72="",_xlfn.XLOOKUP(C72,'Price Averages'!$D$4:$D$103,'Price Averages'!$E$4:$E$103, "FALSE"), F72) -> 144 | I72: =IF(H72="", _xlfn.XLOOKUP(C72, 'Cost Averages'!$D$4:$D$103,'Cost Averages'!$E$4:$E$103, "FALSE"),H72) -> 36 | J72: =E72*G72 -> 1872 | K72: =E72*I72 -> 468 | L72: =J72-K72 -> 1404 | M72: Dissatisfied | N72: CG-1618 | O72: Community & Government | P72: 8.1628931 | Q72: =CHAR(64+(YEAR(A72)-2014)) -> C | R72: =YEAR(A72) -> 2017 | S72: =IF(Q72=CHAR(64 + (YEAR(A72) - 2014)), 0, 1) -> 0
A73: 43073.676 | B73: 17-3471 | C73: P047 | D73: 4 | E73: =IF(D73="", _xlfn.XLOOKUP(C73,'Median Quantity per product'!$D$4:$D$103,'Median Quantity per product'!$E$4:$E$103, "NA"),'Project Work - Data wrows'!D73) -> 4 | F73: 72 | G73: =IF(F73="",_xlfn.XLOOKUP(C73,'Price Averages'!$D$4:$D$103,'Price Averages'!$E$4:$E$103, "FALSE"), F73) -> 72 | H73: 36 | I73: =IF(H73="", _xlfn.XLOOKUP(C73, 'Cost Averages'!$D$4:$D$103,'Cost Averages'!$E$4:$E$103, "FALSE"),H73) -> 36 | J73: =E73*G73 -> 288 | K73: =E73*I73 -> 144 | L73: =J73-K73 -> 144 | M73: Neither | N73: EE-4858 | O73: Education | P73: 12.456741 | Q73: =CHAR(64+(YEAR(A73)-2014)) -> C | R73: =YEAR(A73) -> 2017 | S73: =IF(Q73=CHAR(64 + (YEAR(A73) - 2014)), 0, 1) -> 0
A74: 42852.304 | B74: 17-2258 | C74: P047 | D74: 12 | E74: =IF(D74="", _xlfn.XLOOKUP(C74,'Median Quantity per product'!$D$4:$D$103,'Median Quantity per product'!$E$4:$E$103, "NA"),'Project Work - Data wrows'!D74) -> 12 | F74: 72 | G74: =IF(F74="",_xlfn.XLOOKUP(C74,'Price Averages'!$D$4:$D$103,'Price Averages'!$E$4:$E$103, "FALSE"), F74) -> 72 | H74: 36 | I74: =IF(H74="", _xlfn.XLOOKUP(C74, 'Cost Averages'!$D$4:$D$103,'Cost Averages'!$E$4:$E$103, "FALSE"),H74) -> 36 | J74: =E74*G74 -> 864 | K74: =E74*I74 -> 432 | L74: =J74-K74 -> 432 | M74: Dissatisfied | N74: SR-9639 | O74: Sports & Recreation | P74: 12.487915 | Q74: =CHAR(64+(YEAR(A74)-2014)) -> C | R74: =YEAR(A74) -> 2017 | S74: =IF(Q74=CHAR(64 + (YEAR(A74) - 2014)), 0, 1) -> 0
A75: 43066.994 | B75: 17-2601 | C75: P048 | D75: 2 | E75: =IF(D75="", _xlfn.XLOOKUP(C75,'Median Quantity per product'!$D$4:$D$103,'Median Quantity per product'!$E$4:$E$103, "NA"),'Project Work - Data wrows'!D75) -> 2 | G75: =IF(F75="",_xlfn.XLOOKUP(C75,'Price Averages'!$D$4:$D$103,'Price Averages'!$E$4:$E$103, "FALSE"), F75) -> 252 | I75: =IF(H75="", _xlfn.XLOOKUP(C75, 'Cost Averages'!$D$4:$D$103,'Cost Averages'!$E$4:$E$103, "FALSE"),H75) -> 63 | J75: =E75*G75 -> 504 | K75: =E75*I75 -> 126 | L75: =J75-K75 -> 378 | M75: Satisfied | N75: EE-4649 | O75: Education | P75: 13.392447 | Q75: =CHAR(64+(YEAR(A75)-2014)) -> C | R75: =YEAR(A75) -> 2017 | S75: =IF(Q75=CHAR(64 + (YEAR(A75) - 2014)), 0, 1) -> 0
A76: 43085.026 | B76: 17-4464 | C76: P048 | D76: 16 | E76: =IF(D76="", _xlfn.XLOOKUP(C76,'Median Quantity per product'!$D$4:$D$103,'Median Quantity per product'!$E$4:$E$103, "NA"),'Project Work - Data wrows'!D76) -> 16 | F76: 252 | G76: =IF(F76="",_xlfn.XLOOKUP(C76,'Price Averages'!$D$4:$D$103,'Price Averages'!$E$4:$E$103, "FALSE"), F76) -> 252 | H76: 63 | I76: =IF(H76="", _xlfn.XLOOKUP(C76, 'Cost Averages'!$D$4:$D$103,'Cost Averages'!$E$4:$E$103, "FALSE"),H76) -> 63 | J76: =E76*G76 -> 4032 | K76: =E76*I76 -> 1008 | L76: =J76-K76 -> 3024 | M76: Satisfied | N76: HS-7204 | O76: Healthcare & Safety | P76: 9.4608555 | Q76: =CHAR(64+(YEAR(A76)-2014)) -> C | R76: =YEAR(A76) -> 2017 | S76: =IF(Q76=CHAR(64 + (YEAR(A76) - 2014)), 0, 1) -> 0
A77: 42781.143 | B77: 17-4385 | C77: P049 | D77: 20 | E77: =IF(D77="", _xlfn.XLOOKUP(C77,'Median Quantity per product'!$D$4:$D$103,'Median Quantity per product'!$E$4:$E$103, "NA"),'Project Work - Data wrows'!D77) -> 20 | F77: 356 | G77: =IF(F77="",_xlfn.XLOOKUP(C77,'Price Averages'!$D$4:$D$103,'Price Averages'!$E$4:$E$103, "FALSE"), F77) -> 356 | H77: 89 | I77: =IF(H77="", _xlfn.XLOOKUP(C77, 'Cost Averages'!$D$4:$D$103,'Cost Averages'!$E$4:$E$103, "FALSE"),H77) -> 89 | J77: =E77*G77 -> 7120 | K77: =E77*I77 -> 1780 | L77: =J77-K77 -> 5340 | M77: Satisfied | N77: SR-9989 | O77: Sports & Recreation | P77: 15.602184 | Q77: =CHAR(64+(YEAR(A77)-2014)) -> C | R77: =YEAR(A77) -> 2017 | S77: =IF(Q77=CHAR(64 + (YEAR(A77) - 2014)), 0, 1) -> 0
A78: 42871.471 | B78: 17-2421 | C78: P050 | D78: 10 | E78: =IF(D78="", _xlfn.XLOOKUP(C78,'Median Quantity per product'!$D$4:$D$103,'Median Quantity per product'!$E$4:$E$103, "NA"),'Project Work - Data wrows'!D78) -> 10 | F78: 108 | G78: =IF(F78="",_xlfn.XLOOKUP(C78,'Price Averages'!$D$4:$D$103,'Price Averages'!$E$4:$E$103, "FALSE"), F78) -> 108 | H78: 36 | I78: =IF(H78="", _xlfn.XLOOKUP(C78, 'Cost Averages'!$D$4:$D$103,'Cost Averages'!$E$4:$E$103, "FALSE"),H78) -> 36 | J78: =E78*G78 -> 1080 | K78: =E78*I78 -> 360 | L78: =J78-K78 -> 720 | M78: Neither | N78: CP-2758 | O78: Corporate & Professional | P78: 11.816654 | Q78: =CHAR(64+(YEAR(A78)-2014)) -> C | R78: =YEAR(A78) -> 2017 | S78: =IF(Q78=CHAR(64 + (YEAR(A78) - 2014)), 0, 1) -> 0
A79: 42985.107 | B79: 17-3805 | C79: P051 | D79: 9 | E79: =IF(D79="", _xlfn.XLOOKUP(C79,'Median Quantity per product'!$D$4:$D$103,'Median Quantity per product'!$E$4:$E$103, "NA"),'Project Work - Data wrows'!D79) -> 9 | F79: 135 | G79: =IF(F79="",_xlfn.XLOOKUP(C79,'Price Averages'!$D$4:$D$103,'Price Averages'!$E$4:$E$103, "FALSE"), F79) -> 135 | H79: 45 | I79: =IF(H79="", _xlfn.XLOOKUP(C79, 'Cost Averages'!$D$4:$D$103,'Cost Averages'!$E$4:$E$103, "FALSE"),H79) -> 45 | J79: =E79*G79 -> 1215 | K79: =E79*I79 -> 405 | L79: =J79-K79 -> 810 | M79: Neither | N79: HS-7475 | O79: Healthcare & Safety | P79: 13.005538 | Q79: =CHAR(64+(YEAR(A79)-2014)) -> C | R79: =YEAR(A79) -> 2017 | S79: =IF(Q79=CHAR(64 + (YEAR(A79) - 2014)), 0, 1) -> 0
A80: 43061.961 | B80: 17-3301 | C80: P051 | E80: =IF(D80="", _xlfn.XLOOKUP(C80,'Median Quantity per product'!$D$4:$D$103,'Median Quantity per product'!$E$4:$E$103, "NA"),'Project Work - Data wrows'!D80) -> 10 | F80: 135 | G80: =IF(F80="",_xlfn.XLOOKUP(C80,'Price Averages'!$D$4:$D$103,'Price Averages'!$E$4:$E$103, "FALSE"), F80) -> 135 | I80: =IF(H80="", _xlfn.XLOOKUP(C80, 'Cost Averages'!$D$4:$D$103,'Cost Averages'!$E$4:$E$103, "FALSE"),H80) -> 45 | J80: =E80*G80 -> 1350 | K80: =E80*I80 -> 450 | L80: =J80-K80 -> 900 | M80: Neither | N80: EE-434 | O80: Education | P80: 12.29978 | Q80: =CHAR(64+(YEAR(A80)-2014)) -> C | R80: =YEAR(A80) -> 2017 | S80: =IF(Q80=CHAR(64 + (YEAR(A80) - 2014)), 0, 1) -> 0
A81: 42913.739 | B81: 17-4529 | C81: P052 | D81: 9 | E81: =IF(D81="", _xlfn.XLOOKUP(C81,'Median Quantity per product'!$D$4:$D$103,'Median Quantity per product'!$E$4:$E$103, "NA"),'Project Work - Data wrows'!D81) -> 9 | F81: 352 | G81: =IF(F81="",_xlfn.XLOOKUP(C81,'Price Averages'!$D$4:$D$103,'Price Averages'!$E$4:$E$103, "FALSE"), F81) -> 352 | H81: 88 | I81: =IF(H81="", _xlfn.XLOOKUP(C81, 'Cost Averages'!$D$4:$D$103,'Cost Averages'!$E$4:$E$103, "FALSE"),H81) -> 88 | J81: =E81*G81 -> 3168 | K81: =E81*I81 -> 792 | L81: =J81-K81 -> 2376 | M81: Satisfied | N81: FE-6981 | O81: Facilities & Services | P81: 10.517826 | Q81: =CHAR(64+(YEAR(A81)-2014)) -> C | R81: =YEAR(A81) -> 2017 | S81: =IF(Q81=CHAR(64 + (YEAR(A81) - 2014)), 0, 1) -> 0
A82: 43039.632 | B82: 17-4260 | C82: P054 | D82: 20 | E82: =IF(D82="", _xlfn.XLOOKUP(C82,'Median Quantity per product'!$D$4:$D$103,'Median Quantity per product'!$E$4:$E$103, "NA"),'Project Work - Data wrows'!D82) -> 20 | F82: 144 | G82: =IF(F82="",_xlfn.XLOOKUP(C82,'Price Averages'!$D$4:$D$103,'Price Averages'!$E$4:$E$103, "FALSE"), F82) -> 144 | H82: 48 | I82: =IF(H82="", _xlfn.XLOOKUP(C82, 'Cost Averages'!$D$4:$D$103,'Cost Averages'!$E$4:$E$103, "FALSE"),H82) -> 48 | J82: =E82*G82 -> 2880 | K82: =E82*I82 -> 960 | L82: =J82-K82 -> 1920 | M82: Dissatisfied | N82: SR-9400 | O82: Sports & Recreation | P82: 12.342715 | Q82: =CHAR(64+(YEAR(A82)-2014)) -> C | R82: =YEAR(A82) -> 2017 | S82: =IF(Q82=CHAR(64 + (YEAR(A82) - 2014)), 0, 1) -> 0
A83: 43044.409 | B83: 17-4758 | C83: P055 | D83: 15 | E83: =IF(D83="", _xlfn.XLOOKUP(C83,'Median Quantity per product'!$D$4:$D$103,'Median Quantity per product'!$E$4:$E$103, "NA"),'Project Work - Data wrows'!D83) -> 15 | F83: 360 | G83: =IF(F83="",_xlfn.XLOOKUP(C83,'Price Averages'!$D$4:$D$103,'Price Averages'!$E$4:$E$103, "FALSE"), F83) -> 360 | H83: 90 | I83: =IF(H83="", _xlfn.XLOOKUP(C83, 'Cost Averages'!$D$4:$D$103,'Cost Averages'!$E$4:$E$103, "FALSE"),H83) -> 90 | J83: =E83*G83 -> 5400 | K83: =E83*I83 -> 1350 | L83: =J83-K83 -> 4050 | M83: Satisfied | N83: EE-4649 | O83: Education | P83: 13.392447 | Q83: =CHAR(64+(YEAR(A83)-2014)) -> C | R83: =YEAR(A83) -> 2017 | S83: =IF(Q83=CHAR(64 + (YEAR(A83) - 2014)), 0, 1) -> 0
A84: 43052.329 | B84: 17-2067 | C84: P055 | D84: 16 | E84: =IF(D84="", _xlfn.XLOOKUP(C84,'Median Quantity per product'!$D$4:$D$103,'Median Quantity per product'!$E$4:$E$103, "NA"),'Project Work - Data wrows'!D84) -> 16 | F84: 360 | G84: =IF(F84="",_xlfn.XLOOKUP(C84,'Price Averages'!$D$4:$D$103,'Price Averages'!$E$4:$E$103, "FALSE"), F84) -> 360 | I84: =IF(H84="", _xlfn.XLOOKUP(C84, 'Cost Averages'!$D$4:$D$103,'Cost Averages'!$E$4:$E$103, "FALSE"),H84) -> 90 | J84: =E84*G84 -> 5760 | K84: =E84*I84 -> 1440 | L84: =J84-K84 -> 4320 | M84: Satisfied | N84: CT-3648 | O84: Creative & Technology | P84: 10.764294 | Q84: =CHAR(64+(YEAR(A84)-2014)) -> C | R84: =YEAR(A84) -> 2017 | S84: =IF(Q84=CHAR(64 + (YEAR(A84) - 2014)), 0, 1) -> 0
A85: 42853.616 | B85: 17-4752 | C85: P056 | D85: 19 | E85: =IF(D85="", _xlfn.XLOOKUP(C85,'Median Quantity per product'!$D$4:$D$103,'Median Quantity per product'!$E$4:$E$103, "NA"),'Project Work - Data wrows'!D85) -> 19 | F85: 72 | G85: =IF(F85="",_xlfn.XLOOKUP(C85,'Price Averages'!$D$4:$D$103,'Price Averages'!$E$4:$E$103, "FALSE"), F85) -> 72 | H85: 36 | I85: =IF(H85="", _xlfn.XLOOKUP(C85, 'Cost Averages'!$D$4:$D$103,'Cost Averages'!$E$4:$E$103, "FALSE"),H85) -> 36 | J85: =E85*G85 -> 1368 | K85: =E85*I85 -> 684 | L85: =J85-K85 -> 684 | M85: Neither | N85: EE-46 | O85: Education | P85: 9.8238489 | Q85: =CHAR(64+(YEAR(A85)-2014)) -> C | R85: =YEAR(A85) -> 2017 | S85: =IF(Q85=CHAR(64 + (YEAR(A85) - 2014)), 0, 1) -> 0
A86: 43097.141 | B86: 17-4532 | C86: P059 | D86: 14 | E86: =IF(D86="", _xlfn.XLOOKUP(C86,'Median Quantity per product'!$D$4:$D$103,'Median Quantity per product'!$E$4:$E$103, "NA"),'Project Work - Data wrows'!D86) -> 14 | G86: =IF(F86="",_xlfn.XLOOKUP(C86,'Price Averages'!$D$4:$D$103,'Price Averages'!$E$4:$E$103, "FALSE"), F86) -> 267 | H86: 89 | I86: =IF(H86="", _xlfn.XLOOKUP(C86, 'Cost Averages'!$D$4:$D$103,'Cost Averages'!$E$4:$E$103, "FALSE"),H86) -> 89 | J86: =E86*G86 -> 3738 | K86: =E86*I86 -> 1246 | L86: =J86-K86 -> 2492 | M86: Neither | N86: FE-6339 | O86: Facilities & Services | P86: 13.853439 | Q86: =CHAR(64+(YEAR(A86)-2014)) -> C | R86: =YEAR(A86) -> 2017 | S86: =IF(Q86=CHAR(64 + (YEAR(A86) - 2014)), 0, 1) -> 0
A87: 43027.023 | B87: 17-3100 | C87: P059 | D87: 16 | E87: =IF(D87="", _xlfn.XLOOKUP(C87,'Median Quantity per product'!$D$4:$D$103,'Median Quantity per product'!$E$4:$E$103, "NA"),'Project Work - Data wrows'!D87) -> 16 | F87: 267 | G87: =IF(F87="",_xlfn.XLOOKUP(C87,'Price Averages'!$D$4:$D$103,'Price Averages'!$E$4:$E$103, "FALSE"), F87) -> 267 | H87: 89 | I87: =IF(H87="", _xlfn.XLOOKUP(C87, 'Cost Averages'!$D$4:$D$103,'Cost Averages'!$E$4:$E$103, "FALSE"),H87) -> 89 | J87: =E87*G87 -> 4272 | K87: =E87*I87 -> 1424 | L87: =J87-K87 -> 2848 | M87: Neither | N87: FE-6752 | O87: Facilities & Services | P87: 10.966283 | Q87: =CHAR(64+(YEAR(A87)-2014)) -> C | R87: =YEAR(A87) -> 2017 | S87: =IF(Q87=CHAR(64 + (YEAR(A87) - 2014)), 0, 1) -> 0
A88: 42768.415 | B88: 17-3014 | C88: P059 | E88: =IF(D88="", _xlfn.XLOOKUP(C88,'Median Quantity per product'!$D$4:$D$103,'Median Quantity per product'!$E$4:$E$103, "NA"),'Project Work - Data wrows'!D88) -> 11.5 | F88: 267 | G88: =IF(F88="",_xlfn.XLOOKUP(C88,'Price Averages'!$D$4:$D$103,'Price Averages'!$E$4:$E$103, "FALSE"), F88) -> 267 | H88: 89 | I88: =IF(H88="", _xlfn.XLOOKUP(C88, 'Cost Averages'!$D$4:$D$103,'Cost Averages'!$E$4:$E$103, "FALSE"),H88) -> 89 | J88: =E88*G88 -> 3070.5 | K88: =E88*I88 -> 1023.5 | L88: =J88-K88 -> 2047 | M88: Satisfied | N88: SR-9557 | O88: Sports & Recreation | P88: 10.988762 | Q88: =CHAR(64+(YEAR(A88)-2014)) -> C | R88: =YEAR(A88) -> 2017 | S88: =IF(Q88=CHAR(64 + (YEAR(A88) - 2014)), 0, 1) -> 0
A89: 43085.794 | B89: 17-2359 | C89: P060 | D89: 5 | E89: =IF(D89="", _xlfn.XLOOKUP(C89,'Median Quantity per product'!$D$4:$D$103,'Median Quantity per product'!$E$4:$E$103, "NA"),'Project Work - Data wrows'!D89) -> 5 | F89: 300 | G89: =IF(F89="",_xlfn.XLOOKUP(C89,'Price Averages'!$D$4:$D$103,'Price Averages'!$E$4:$E$103, "FALSE"), F89) -> 300 | H89: 75 | I89: =IF(H89="", _xlfn.XLOOKUP(C89, 'Cost Averages'!$D$4:$D$103,'Cost Averages'!$E$4:$E$103, "FALSE"),H89) -> 75 | J89: =E89*G89 -> 1500 | K89: =E89*I89 -> 375 | L89: =J89-K89 -> 1125 | M89: Neither | N89: SR-9320 | O89: Sports & Recreation | P89: 12.133499 | Q89: =CHAR(64+(YEAR(A89)-2014)) -> C | R89: =YEAR(A89) -> 2017 | S89: =IF(Q89=CHAR(64 + (YEAR(A89) - 2014)), 0, 1) -> 0
A90: 43098.497 | B90: 17-3569 | C90: P060 | D90: 16 | E90: =IF(D90="", _xlfn.XLOOKUP(C90,'Median Quantity per product'!$D$4:$D$103,'Median Quantity per product'!$E$4:$E$103, "NA"),'Project Work - Data wrows'!D90) -> 16 | F90: 300 | G90: =IF(F90="",_xlfn.XLOOKUP(C90,'Price Averages'!$D$4:$D$103,'Price Averages'!$E$4:$E$103, "FALSE"), F90) -> 300 | H90: 75 | I90: =IF(H90="", _xlfn.XLOOKUP(C90, 'Cost Averages'!$D$4:$D$103,'Cost Averages'!$E$4:$E$103, "FALSE"),H90) -> 75 | J90: =E90*G90 -> 4800 | K90: =E90*I90 -> 1200 | L90: =J90-K90 -> 3600 | M90: Neither | N90: CT-3693 | O90: Creative & Technology | P90: 13.259563 | Q90: =CHAR(64+(YEAR(A90)-2014)) -> C | R90: =YEAR(A90) -> 2017 | S90: =IF(Q90=CHAR(64 + (YEAR(A90) - 2014)), 0, 1) -> 0
A91: 43030.842 | B91: 17-4621 | C91: P061 | D91: 5 | E91: =IF(D91="", _xlfn.XLOOKUP(C91,'Median Quantity per product'!$D$4:$D$103,'Median Quantity per product'!$E$4:$E$103, "NA"),'Project Work - Data wrows'!D91) -> 5 | F91: 264 | G91: =IF(F91="",_xlfn.XLOOKUP(C91,'Price Averages'!$D$4:$D$103,'Price Averages'!$E$4:$E$103, "FALSE"), F91) -> 264 | I91: =IF(H91="", _xlfn.XLOOKUP(C91, 'Cost Averages'!$D$4:$D$103,'Cost Averages'!$E$4:$E$103, "FALSE"),H91) -> 88 | J91: =E91*G91 -> 1320 | K91: =E91*I91 -> 440 | L91: =J91-K91 -> 880 | M91: Neither | N91: FE-6254 | O91: Facilities & Services | P91: 11.961762 | Q91: =CHAR(64+(YEAR(A91)-2014)) -> C | R91: =YEAR(A91) -> 2017 | S91: =IF(Q91=CHAR(64 + (YEAR(A91) - 2014)), 0, 1) -> 0
A92: 43087.79 | B92: 17-3553 | C92: P061 | D92: 13 | E92: =IF(D92="", _xlfn.XLOOKUP(C92,'Median Quantity per product'!$D$4:$D$103,'Median Quantity per product'!$E$4:$E$103, "NA"),'Project Work - Data wrows'!D92) -> 13 | F92: 264 | G92: =IF(F92="",_xlfn.XLOOKUP(C92,'Price Averages'!$D$4:$D$103,'Price Averages'!$E$4:$E$103, "FALSE"), F92) -> 264 | H92: 88 | I92: =IF(H92="", _xlfn.XLOOKUP(C92, 'Cost Averages'!$D$4:$D$103,'Cost Averages'!$E$4:$E$103, "FALSE"),H92) -> 88 | J92: =E92*G92 -> 3432 | K92: =E92*I92 -> 1144 | L92: =J92-K92 -> 2288 | M92: Satisfied | N92: CT-3932 | O92: Creative & Technology | P92: 13.929237 | Q92: =CHAR(64+(YEAR(A92)-2014)) -> C | R92: =YEAR(A92) -> 2017 | S92: =IF(Q92=CHAR(64 + (YEAR(A92) - 2014)), 0, 1) -> 0
A93: 42990.559 | B93: 17-3371 | C93: P063 | D93: 1 | E93: =IF(D93="", _xlfn.XLOOKUP(C93,'Median Quantity per product'!$D$4:$D$103,'Median Quantity per product'!$E$4:$E$103, "NA"),'Project Work - Data wrows'!D93) -> 1 | F93: 261 | G93: =IF(F93="",_xlfn.XLOOKUP(C93,'Price Averages'!$D$4:$D$103,'Price Averages'!$E$4:$E$103, "FALSE"), F93) -> 261 | I93: =IF(H93="", _xlfn.XLOOKUP(C93, 'Cost Averages'!$D$4:$D$103,'Cost Averages'!$E$4:$E$103, "FALSE"),H93) -> 87 | J93: =E93*G93 -> 261 | K93: =E93*I93 -> 87 | L93: =J93-K93 -> 174 | M93: Satisfied | N93: HS-7291 | O93: Healthcare & Safety | P93: 10.42743 | Q93: =CHAR(64+(YEAR(A93)-2014)) -> C | R93: =YEAR(A93) -> 2017 | S93: =IF(Q93=CHAR(64 + (YEAR(A93) - 2014)), 0, 1) -> 0
A94: 43081.342 | B94: 17-2222 | C94: P063 | D94: 6 | E94: =IF(D94="", _xlfn.XLOOKUP(C94,'Median Quantity per product'!$D$4:$D$103,'Median Quantity per product'!$E$4:$E$103, "NA"),'Project Work - Data wrows'!D94) -> 6 | F94: 261 | G94: =IF(F94="",_xlfn.XLOOKUP(C94,'Price Averages'!$D$4:$D$103,'Price Averages'!$E$4:$E$103, "FALSE"), F94) -> 261 | H94: 87 | I94: =IF(H94="", _xlfn.XLOOKUP(C94, 'Cost Averages'!$D$4:$D$103,'Cost Averages'!$E$4:$E$103, "FALSE"),H94) -> 87 | J94: =E94*G94 -> 1566 | K94: =E94*I94 -> 522 | L94: =J94-K94 -> 1044 | M94: Dissatisfied | N94: CT-3497 | O94: Creative & Technology | P94: 11.783468 | Q94: =CHAR(64+(YEAR(A94)-2014)) -> C | R94: =YEAR(A94) -> 2017 | S94: =IF(Q94=CHAR(64 + (YEAR(A94) - 2014)), 0, 1) -> 0
A95: 42873.804 | B95: 17-1857 | C95: P063 | D95: 13 | E95: =IF(D95="", _xlfn.XLOOKUP(C95,'Median Quantity per product'!$D$4:$D$103,'Median Quantity per product'!$E$4:$E$103, "NA"),'Project Work - Data wrows'!D95) -> 13 | F95: 261 | G95: =IF(F95="",_xlfn.XLOOKUP(C95,'Price Averages'!$D$4:$D$103,'Price Averages'!$E$4:$E$103, "FALSE"), F95) -> 261 | H95: 87 | I95: =IF(H95="", _xlfn.XLOOKUP(C95, 'Cost Averages'!$D$4:$D$103,'Cost Averages'!$E$4:$E$103, "FALSE"),H95) -> 87 | J95: =E95*G95 -> 3393 | K95: =E95*I95 -> 1131 | L95: =J95-K95 -> 2262 | M95: Neither | N95: EE-46 | O95: Education | P95: 9.8238489 | Q95: =CHAR(64+(YEAR(A95)-2014)) -> C | R95: =YEAR(A95) -> 2017 | S95: =IF(Q95=CHAR(64 + (YEAR(A95) - 2014)), 0, 1) -> 0
A96: 43069.61 | B96: 17-3345 | C96: P064 | D96: 3 | E96: =IF(D96="", _xlfn.XLOOKUP(C96,'Median Quantity per product'!$D$4:$D$103,'Median Quantity per product'!$E$4:$E$103, "NA"),'Project Work - Data wrows'!D96) -> 3 | F96: 231 | G96: =IF(F96="",_xlfn.XLOOKUP(C96,'Price Averages'!$D$4:$D$103,'Price Averages'!$E$4:$E$103, "FALSE"), F96) -> 231 | H96: 77 | I96: =IF(H96="", _xlfn.XLOOKUP(C96, 'Cost Averages'!$D$4:$D$103,'Cost Averages'!$E$4:$E$103, "FALSE"),H96) -> 77 | J96: =E96*G96 -> 693 | K96: =E96*I96 -> 231 | L96: =J96-K96 -> 462 | M96: Dissatisfied | N96: CG-142 | O96: Community & Government | P96: 14.412866 | Q96: =CHAR(64+(YEAR(A96)-2014)) -> C | R96: =YEAR(A96) -> 2017 | S96: =IF(Q96=CHAR(64 + (YEAR(A96) - 2014)), 0, 1) -> 0
A97: 42839.351 | B97: 17-2101 | C97: P065 | D97: 6 | E97: =IF(D97="", _xlfn.XLOOKUP(C97,'Median Quantity per product'!$D$4:$D$103,'Median Quantity per product'!$E$4:$E$103, "NA"),'Project Work - Data wrows'!D97) -> 6 | F97: 50 | G97: =IF(F97="",_xlfn.XLOOKUP(C97,'Price Averages'!$D$4:$D$103,'Price Averages'!$E$4:$E$103, "FALSE"), F97) -> 50 | H97: 25 | I97: =IF(H97="", _xlfn.XLOOKUP(C97, 'Cost Averages'!$D$4:$D$103,'Cost Averages'!$E$4:$E$103, "FALSE"),H97) -> 25 | J97: =E97*G97 -> 300 | K97: =E97*I97 -> 150 | L97: =J97-K97 -> 150 | M97: Neither | N97: CT-3229 | O97: Creative & Technology | P97: 15.770847 | Q97: =CHAR(64+(YEAR(A97)-2014)) -> C | R97: =YEAR(A97) -> 2017 | S97: =IF(Q97=CHAR(64 + (YEAR(A97) - 2014)), 0, 1) -> 0
A98: 42992.182 | B98: 17-4811 | C98: P066 | D98: 8 | E98: =IF(D98="", _xlfn.XLOOKUP(C98,'Median Quantity per product'!$D$4:$D$103,'Median Quantity per product'!$E$4:$E$103, "NA"),'Project Work - Data wrows'!D98) -> 8 | G98: =IF(F98="",_xlfn.XLOOKUP(C98,'Price Averages'!$D$4:$D$103,'Price Averages'!$E$4:$E$103, "FALSE"), F98) -> 34 | H98: 17 | I98: =IF(H98="", _xlfn.XLOOKUP(C98, 'Cost Averages'!$D$4:$D$103,'Cost Averages'!$E$4:$E$103, "FALSE"),H98) -> 17 | J98: =E98*G98 -> 272 | K98: =E98*I98 -> 136 | L98: =J98-K98 -> 136 | M98: Dissatisfied | N98: CT-3443 | O98: Creative & Technology | P98: 11.312215 | Q98: =CHAR(64+(YEAR(A98)-2014)) -> C | R98: =YEAR(A98) -> 2017 | S98: =IF(Q98=CHAR(64 + (YEAR(A98) - 2014)), 0, 1) -> 0
A99: 42798.41 | B99: 17-1042 | C99: P066 | D99: 15 | E99: =IF(D99="", _xlfn.XLOOKUP(C99,'Median Quantity per product'!$D$4:$D$103,'Median Quantity per product'!$E$4:$E$103, "NA"),'Project Work - Data wrows'!D99) -> 15 | G99: =IF(F99="",_xlfn.XLOOKUP(C99,'Price Averages'!$D$4:$D$103,'Price Averages'!$E$4:$E$103, "FALSE"), F99) -> 34 | I99: =IF(H99="", _xlfn.XLOOKUP(C99, 'Cost Averages'!$D$4:$D$103,'Cost Averages'!$E$4:$E$103, "FALSE"),H99) -> 17 | J99: =E99*G99 -> 510 | K99: =E99*I99 -> 255 | L99: =J99-K99 -> 255 | M99: Satisfied | N99: HS-7652 | O99: Healthcare & Safety | P99: 14.377134 | Q99: =CHAR(64+(YEAR(A99)-2014)) -> C | R99: =YEAR(A99) -> 2017 | S99: =IF(Q99=CHAR(64 + (YEAR(A99) - 2014)), 0, 1) -> 0
A100: 43068.791 | B100: 17-1916 | C100: P067 | D100: 13 | E100: =IF(D100="", _xlfn.XLOOKUP(C100,'Median Quantity per product'!$D$4:$D$103,'Median Quantity per product'!$E$4:$E$103, "NA"),'Project Work - Data wrows'!D100) -> 13 | F100: 144 | G100: =IF(F100="",_xlfn.XLOOKUP(C100,'Price Averages'!$D$4:$D$103,'Price Averages'!$E$4:$E$103, "FALSE"), F100) -> 144 | H100: 36 | I100: =IF(H100="", _xlfn.XLOOKUP(C100, 'Cost Averages'!$D$4:$D$103,'Cost Averages'!$E$4:$E$103, "FALSE"),H100) -> 36 | J100: =E100*G100 -> 1872 | K100: =E100*I100 -> 468 | L100: =J100-K100 -> 1404 | M100: Neither | N100: CG-1416 | O100: Community & Government | P100: 12.155895 | Q100: =CHAR(64+(YEAR(A100)-2014)) -> C | R100: =YEAR(A100) -> 2017 | S100: =IF(Q100=CHAR(64 + (YEAR(A100) - 2014)), 0, 1) -> 0
...

Sheet Median Quantity per product
A3: Row Labels | B3: Average of Quantity
A4: P001 | B4: 12.425 | D4: P001 | E4: 12.5
A5: P002 | B5: 10.688889 | D5: P002 | E5: 11
A6: P003 | B6: 9.525 | D6: P003 | E6: 9
A7: P004 | B7: 11.347826 | D7: P004 | E7: 11
A8: P005 | B8: 11.025 | D8: P005 | E8: 10.5
A9: P006 | B9: 9.3111111 | D9: P006 | E9: 9
A10: P007 | B10: 9.8965517 | D10: P007 | E10: 11
A11: P008 | B11: 10.482759 | D11: P008 | E11: 11
A12: P009 | B12: 11.904762 | D12: P009 | E12: 14.5
A13: P010 | B13: 10.186047 | D13: P010 | E13: 9
A14: P011 | B14: 8.9 | D14: P011 | E14: 8.5
A15: P012 | B15: 10.575758 | D15: P012 | E15: 12
... A103: P100 | B103: 9.7234043 | D103: P100 | E103: 9
A104: (blank)
A105: Grand Total | B105: 10.499083

Sheet Differences wrows
A3: Row Labels | B3: Average of Profit | C3: StdDev of Profit | D3: Count of Profit | E3: Sum of Profit | H3: Row Labels | I3: Average of Profit | J3: StdDev of Profit | K3: Count of Profit | L3: Sum of Profit
A4: A | B4: 1448 | C4: 822.85625 | D4: 6 | E4: 8688 | H4: A | I4: 1448 | J4: 822.85625 | K4: 6 | L4: 8688 | N4: =(I4-I5)/SQRT((J4^2/K4)+(J5^2/K5)) -> 0.73338397
A5: B | B5: 1154.0952 | C5: 1001.4063 | D5: 21 | E5: 24236 | H5: B | I5: 1154.0952 | J5: 1001.4063 | K5: 21 | L5: 24236 | N5: =(I5-I6)/SQRT((J5^2/K5)+(J6^2/K6)) -> -0.23375535
A6: C | B6: 1211.0943 | C6: 1113.8942 | D6: 106 | E6: 128376 | H6: C | I6: 1211.0943 | J6: 1113.8942 | K6: 106 | L6: 128376 | N6: =(I6-I7)/SQRT((J6^2/K6)+(J7^2/K7)) -> -0.75221392
A7: D | B7: 1305.6197 | C7: 1197.5543 | D7: 351 | E7: 458272.5 | H7: D | I7: 1305.6197 | J7: 1197.5543 | K7: 351 | L7: 458272.5 | N7: =(I7-I8)/SQRT((J7^2/K7)+(J8^2/K8)) -> 1.8639811
A8: E | B8: 1166.8229 | C8: 1070.1237 | D8: 785 | E8: 915956 | H8: E | I8: 1166.8229 | J8: 1070.1237 | K8: 785 | L8: 915956 | N8: =(I8-I9)/SQRT((J8^2/K8)+(J9^2/K9)) -> -1.1395177
A9: F | B9: 1223.4959 | C9: 1106.6677 | D9: 1207 | E9: 1476759.5 | H9: F | I9: 1223.4959 | J9: 1106.6677 | K9: 1207 | L9: 1476759.5 | N9: =(I9-I10)/SQRT((J9^2/K9)+(J10^2/K10)) -> 0.14066727
A10: G | B10: 1216.7001 | C10: 1120.6856 | D10: 952 | E10: 1158298.5 | H10: G | I10: 1216.7001 | J10: 1120.6856 | K10: 952 | L10: 1158298.5 | N10: =(I10-I11)/SQRT((J10^2/K10)+(J11^2/K11)) -> -0.018053251
A11: H | B11: 1217.8088 | C11: 1109.4597 | D11: 502 | E11: 611340 | H11: H | I11: 1217.8088 | J11: 1109.4597 | K11: 502 | L11: 611340 | N11: =(I11-I12)/SQRT((J11^2/K11)+(J12^2/K12)) -> 2.6926827
A12: I | B12: 918.96552 | C12: 756.43204 | D12: 58 | E12: 53300 | H12: I | I12: 918.96552 | J12: 756.43204 | K12: 58 | L12: 53300 | N12: =(I12-I13)/SQRT((J12^2/K12)+(J13^2/K13)) -> -1.1126851
A13: J | B13: 1407.0909 | C13: 1417.1919 | D13: 11 | E13: 15478 | H13: J | I13: 1407.0909 | J13: 1417.1919 | K13: 11 | L13: 15478 | N13: =(I13-I14)/SQRT((J13^2/K13)+(J14^2/K14)) -> 2.1642064
A14: K | B14: 470 | C14: 98.994949 | D14: 2 | E14: 940 | H14: K | I14: 470 | J14: 98.994949 | K14: 2 | L14: 940
A15: Grand Total | B15: 1212.608 | C15: 1107.48 | D15: 4001 | E15: 4851644.5
H16: A | I16: 1448 | J16: 822.85625 | K16: 6 | L16: 8688 | N16: =I4-I16 -> 0 | O16: =J4-J16 -> 0
H17: B | I17: 1216.9474 | J17: 1029.5546 | K17: 19 | L17: 23122 | N17: =I5-I17 -> -62.85213 | O17: =J5-J17 -> -28.148365
H18: C | I18: 1193.6765 | J18: 1123.0273 | K18: 102 | L18: 121755 | N18: =I6-I18 -> 17.417869 | O18: =J6-J18 -> -9.1331497
H19: D | I19: 1316.4048 | J19: 1212.4246 | K19: 336 | L19: 442312 | N19: =I7-I19 -> -10.785104 | O19: =J7-J19 -> -14.870323
H20: E | I20: 1169.192 | J20: 1083.6076 | K20: 750 | L20: 876894 | N20: =I8-I20 -> -2.3690701 | O20: =J8-J20 -> -13.48395
H21: F | I21: 1219.6756 | J21: 1116.7021 | K21: 1153 | L21: 1406286 | N21: =I9-I21 -> 3.8202287 | O21: =J9-J21 -> -10.034404
H22: G | I22: 1215.0917 | J22: 1134.1437 | K22: 905 | L22: 1099658 | N22: =I10-I22 -> 1.6083923 | O22: =J10-J22 -> -13.458071
H23: H | I23: 1223.3726 | J23: 1122.5755 | K23: 475 | L23: 581102 | N23: =I11-I23 -> -5.5638666 | O23: =J11-J23 -> -13.115814
H24: I | I24: 910.83929 | J24: 763.91613 | K24: 56 | L24: 51007 | N24: =I12-I24 -> 8.1262315 | O24: =J12-J24 -> -7.4840811
H25: J | I25: 1407.0909 | J25: 1417.1919 | K25: 11 | L25: 15478 | N25: =I13-I25 -> 0 | O25: =J13-J25 -> 0
H26: K | I26: 470 | J26: 98.994949 | K26: 2 | L26: 940 | N26: =I14-I26 -> 0 | O26: =J14-J26 -> 0

Sheet Stats Test
B5: Profit
B6: A | C6: B | D6: C | E6: D | F6: E | G6: F | H6: G | I6: H | J6: I | K6: J | L6: K | N6: t-Test: Two-Sample Assuming Unequal Variances | R6: t-Test: Two-Sample Assuming Unequal Variances
B7: 949 | C7: 1140 | D7: 792 | E7: 792 | F7: 288 | G7: 432 | H7: 144 | I7: 504 | J7: 1944 | K7: 3150 | L7: 540
B8: 80 | C8: 38 | D8: 1296 | E8: 792 | F8: 288 | G8: 576 | H8: 432 | I8: 648 | J8: 2142 | K8: 384 | L8: 400 | O8: A | P8: B | S8: B | T8: C
B9: 2160 | C9: 900 | D9: 1944 | E9: 216 | F9: 720 | G9: 648 | H9: 648 | I9: 1224 | J9: 216 | K9: 2646 | N9: Mean | O9: 1448 | P9: 1154.0952 | R9: Mean | S9: 1154.0952 | T9: 1211.0943
B10: 1701 | C10: 319 | D10: 756 | E10: 972 | F10: 720 | G10: 936 | H10: 720 | I10: 216 | J10: 225 | K10: 1408 | N10: Variance | O10: 677092.4 | P10: 1002814.5 | R10: Variance | S10: 1002814.5 | T10: 1240760.2
B11: 1520 | C11: 1440 | D11: 798 | E11: 1512 | F11: 792 | G11: 1008 | H11: 792 | I11: 432 | J11: 406 | K11: 63 | N11: Observations | O11: 6 | P11: 21 | R11: Observations | S11: 21 | T11: 106
B12: 2278 | C12: 2880 | D12: 247 | E12: 2160 | F12: 936 | G12: 1008 | H12: 792 | I12: 648 | J12: 810 | K12: 4488 | N12: Hypothesized Mean Difference | O12: 0 | R12: Hypothesized Mean Difference | S12: 0
C13: 1280 | D13: 750 | E13: 2160 | F13: 1080 | G13: 1152 | H13: 864 | I13: 864 | J13: 690 | K13: 282 | N13: df | O13: 10 | R13: df | S13: 31
C14: 736 | D14: 900 | E14: 1188 | F14: 1296 | G14: 1224 | H14: 1008 | I14: 1188 | J14: 420 | K14: 1170 | N14: t Stat | O14: 0.73338397 | R14: t Stat | S14: -0.23375535
C15: 2430 | D15: 170 | E15: 1134 | F15: 1296 | G15: 1440 | H15: 1008 | I15: 1512 | J15: 210 | K15: 720 | N15: P(T<=t) one-tail | O15: 0.24008196 | R15: P(T<=t) one-tail | S15: 0.40835587
C16: 648 | D16: 2550 | E16: 1134 | F16: 1368 | G16: 900 | H16: 1080 | I16: 1620 | J16: 280 | K16: 672 | N16: t Critical one-tail | O16: 1.8124611 | R16: t Critical one-tail | S16: 1.6955188
C17: 2136 | D17: 2720 | E17: 1260 | F17: 1368 | G17: 108 | H17: 1152 | I17: 1620 | J17: 780 | K17: 495 | N17: P(T<=t) two-tail | O17: 0.48016393 | R17: P(T<=t) two-tail | S17: 0.81671174
C18: 154 | D18: 648 | E18: 2268 | F18: 216 | G18: 324 | H18: 1224 | I18: 2160 | J18: 450 | N18: t Critical two-tail | O18: 2.2281389 | R18: t Critical two-tail | S18: 2.0395134
C19: 250 | D19: 352 | E19: 2394 | F19: 216 | G19: 432 | H19: 1296 | I19: 2520 | J19: 722
C20: 1188 | D20: 2112 | E20: 252 | F20: 324 | G20: 540 | H20: 540 | I20: 504 | J20: 228 | N20: t-Test: Two-Sample Assuming Unequal Variances | R20: t-Test: Two-Sample Assuming Unequal Variances
C21: 1056 | D21: 2816 | E21: 882 | F21: 432 | G21: 648 | H21: 864 | I21: 504 | J21: 969
C22: 2640 | D22: 195 | E22: 1386 | F22: 540 | G22: 864 | H22: 1404 | I22: 756 | J22: 768 | O22: C | P22: D | S22: D | T22: E
C23: 3432 | D23: 240 | E23: 2268 | F23: 1188 | G23: 1080 | H23: 1512 | I23: 882 | J23: 960 | N23: Mean | O23: 1211.0943 | P23: 1305.6197 | R23: Mean | S23: 1305.6197 | T23: 1166.8229
C24: 500 | D24: 87 | E24: 171 | F24: 1296 | G24: 1188 | H24: 1944 | I24: 882 | J24: 2560 | N24: Variance | O24: 1240760.2 | P24: 1434136.3 | R24: Variance | S24: 1434136.3 | T24: 1145164.7
C25: 90 | D25: 464 | E25: 513 | F25: 1296 | G25: 1296 | H25: 1188 | I25: 882 | J25: 1600 | N25: Observations | O25: 106 | P25: 351 | R25: Observations | S25: 351 | T25: 785
C26: 864 | D26: 792 | E26: 627 | F26: 1836 | G26: 1404 | H26: 252 | I26: 1386 | J26: 720 | N26: Hypothesized Mean Difference | O26: 0 | R26: Hypothesized Mean Difference | S26: 0
C27: 115 | D27: 935 | E27: 912 | F27: 1188 | G27: 1512 | H27: 378 | I27: 2016 | J27: 1120 | N27: df | O27: 184 | R27: df | S27: 610
D28: 972 | E28: 969 | F28: 630 | G28: 1620 | H28: 630 | I28: 2016 | J28: 1520 | N28: t Stat | O28: -0.75221392 | R28: t Stat | S28: 1.8639811
D29: 1386 | E29: 598.5 | F29: 756 | G29: 1944 | H29: 1260 | I29: 2520 | J29: 648 | N29: P(T<=t) one-tail | O29: 0.2264418 | R29: P(T<=t) one-tail | S29: 0.031402273
D30: 2310 | E30: 95 | F30: 882 | G30: 2052 | H30: 1512 | I30: 570 | J30: 644 | N30: t Critical one-tail | O30: 1.6531771 | R30: t Critical one-tail | S30: 1.6473554
D31: 1755 | E31: 114 | F31: 1008 | G31: 2160 | H31: 1512 | I31: 1026 | J31: 267 | N31: P(T<=t) two-tail | O31: 0.45288361 | R31: P(T<=t) two-tail | S31: 0.062804545
D32: 2160 | E32: 323 | F32: 1008 | G32: 1188 | H32: 1764 | I32: 1140 | J32: 1350 | N32: t Critical two-tail | O32: 1.9729405 | R32: t Critical two-tail | S32: 1.9638606
D33: 966 | E33: 342 | F33: 1134 | G33: 126 | H33: 2268 | I33: 76 | J33: 1710
D34: 1008 | E34: 150 | F34: 1386 | G34: 252 | H34: 252 | I34: 114 | J34: 960 | N34: t-Test: Two-Sample Assuming Unequal Variances | R34: t-Test: Two-Sample Assuming Unequal Variances
D35: 264 | E35: 1500 | F35: 1386 | G35: 252 | H35: 378 | I35: 190 | J35: 72
D36: 1470 | E36: 2100 | F36: 1386 | G36: 252 | H36: 504 | I36: 266 | J36: 2079 | O36: E | P36: F | S36: F | T36: G
D37: 1680 | E37: 2250 | F37: 1512 | G37: 504 | H37: 1008 | I37: 450 | J37: 1125 | N37: Mean | O37: 1166.8229 | P37: 1223.4959 | R37: Mean | S37: 1223.4959 | T37: 1216.7001
D38: 140 | E38: 1500 | F38: 1638 | G38: 630 | H38: 1008 | I38: 750 | J38: 3600 | N38: Variance | O38: 1145164.7 | P38: 1224713.5 | R38: Variance | S38: 1224713.5 | T38: 1255936.2
D39: 675 | E39: 972 | F39: 2016 | G39: 630 | H39: 1134 | I39: 2100 | J39: 100 | N39: Observations | O39: 785 | P39: 1207 | R39: Observations | S39: 1207 | T39: 952
D40: 438 | E40: 1188 | F40: 2142 | G40: 756 | H40: 1134 | I40: 450 | J40: 17 | N40: Hypothesized Mean Difference | O40: 0 | R40: Hypothesized Mean Difference | S40: 0
D41: 1022 | E41: 1404 | F41: 1008 | G41: 1008 | H41: 1638 | I41: 450 | J41: 153 | N41: df | O41: 1715 | R41: df | S41: 2030
D42: 644 | E42: 2160 | F42: 1260 | G42: 1008 | H42: 1764 | I42: 1050 | J42: 306 | N42: t Stat | O42: -1.1395177 | R42: t Stat | S42: 0.14066727
D43: 57 | E43: 1232 | F43: 1512 | G43: 1638 | H43: 1764 | I43: 2250 | J43: 819 | N43: P(T<=t) one-tail | O43: 0.12732321 | R43: P(T<=t) one-tail | S43: 0.44407338
D44: 171 | E44: 1408 | F44: 1890 | G44: 1764 | H44: 2268 | I44: 2250 | J44: 693 | N44: t Critical one-tail | O44: 1.6457426 | R44: t Critical one-tail | S44: 1.6456046
D45: 768 | E45: 2992 | F45: 1890 | G45: 2016 | H45: 2520 | I45: 2850 | J45: 1540 | N45: P(T<=t) two-tail | O45: 0.25464641 | R45: P(T<=t) two-tail | S45: 0.88814676
D46: 160 | E46: 75 | F46: 1890 | G46: 882 | H46: 57 | I46: 680 | J46: 528 | N46: t Critical two-tail | O46: 1.9613482 | R46: t Critical two-tail | S46: 1.9611333
D47: 400 | E47: 90 | F47: 2142 | G47: 1008 | H47: 57 | I47: 680 | J47: 423
D48: 480 | E48: 464 | F48: 2394 | G48: 1008 | H48: 114 | I48: 2890 | J48: 1200 | N48: t-Test: Two-Sample Assuming Unequal Variances | R48: t-Test: Two-Sample Assuming Unequal Variances
D49: 720 | E49: 551 | F49: 114 | G49: 1008 | H49: 228 | I49: 2465 | J49: 1786
D50: 1404 | E50: 830 | F50: 228 | G50: 1764 | H50: 285 | I50: 2465 | J50: 540 | O50: G | P50: H | S50: H | T50: I
D51: 144 | E51: 913 | F51: 285 | G51: 1890 | H51: 513 | I51: 432 | J51: 240 | N51: Mean | O51: 1216.7001 | P51: 1217.8088 | R51: Mean | S51: 1217.8088 | T51: 918.96552
D52: 432 | E52: 1079 | F52: 456 | G52: 2016 | H52: 570 | I52: 1620 | J52: 264 | N52: Variance | O52: 1255936.2 | P52: 1230900.9 | R52: Variance | S52: 1230900.9 | T52: 572189.44
D53: 378 | E53: 1577 | F53: 969 | G53: 2016 | H53: 627 | I53: 1620 | J53: 384 | N53: Observations | O53: 952 | P53: 502 | R53: Observations | S53: 502 | T53: 58
D54: 3024 | E54: 264 | F54: 969 | G54: 2394 | H54: 798 | I54: 176 | J54: 576 | N54: Hypothesized Mean Difference | O54: 0 | R54: Hypothesized Mean Difference | S54: 0
D55: 5340 | E55: 1320 | F55: 598.5 | G55: 2394 | H55: 912 | I55: 352 | J55: 102 | N55: df | O55: 1028 | R55: df | S55: 88
D56: 720 | E56: 1672 | F56: 38 | G56: 228 | H56: 912 | I56: 352 | J56: 1071 | N56: t Stat | O56: -0.018053251 | R56: t Stat | S56: 2.6926827
D57: 810 | E57: 1760 | F57: 57 | G57: 285 | H57: 912 | I57: 1408 | J57: 1530 | N57: P(T<=t) one-tail | O57: 0.49279994 | R57: P(T<=t) one-tail | S57: 0.0042426182
D58: 900 | E58: 110 | F58: 76 | G58: 399 | H58: 1026 | I58: 2112 | J58: 1683 | N58: t Critical one-tail | O58: 1.6463372 | R58: t Critical one-tail | S58: 1.662354
D59: 2376 | E59: 220 | F59: 76 | G59: 399 | H59: 1083 | I59: 2816 | J59: 2295 | N59: P(T<=t) two-tail | O59: 0.98559988 | R59: P(T<=t) two-tail | S59: 0.0084852363
D60: 1920 | E60: 550 | F60: 114 | G60: 456 | H60: 57 | I60: 15 | J60: 2295 | N60: t Critical two-tail | O60: 1.9622743 | R60: t Critical two-tail | S60: 1.9872899
D61: 4050 | E61: 990 | F61: 133 | G61: 513 | H61: 95 | I61: 75 | J61: 184
D62: 4320 | E62: 90 | F62: 171 | G62: 798 | H62: 133 | I62: 90 | J62: 297 | N62: t-Test: Two-Sample Assuming Unequal Variances | R62: t-Test: Two-Sample Assuming Unequal Variances
D63: 684 | E63: 162 | F63: 209 | G63: 969 | H63: 152 | I63: 165 | J63: 495
D64: 2492 | E64: 702 | F64: 209 | G64: 969 | H64: 152 | I64: 210 | J64: 1584 | O64: I | P64: J | S64: J | T64: K
D65: 2848 | E65: 918 | F65: 247 | G65: 1140 | H65: 171 | I65: 319 | N65: Mean | O65: 918.96552 | P65: 1407.0909 | R65: Mean | S65: 1407.0909 | T65: 470
D66: 2047 | E66: 231 | F66: 285 | G66: 598.5 | H66: 171 | I66: 493 | N66: Variance | O66: 572189.44 | P66: 2008432.9 | R66: Variance | S66: 2008432.9 | T66: 9800
D67: 1125 | E67: 1386 | F67: 285 | G67: 19 | H67: 228 | I67: 664 | N67: Observations | O67: 58 | P67: 11 | R67: Observations | S67: 11 | T67: 2
D68: 3600 | E68: 1617 | F68: 342 | G68: 38 | H68: 228 | I68: 1162 | N68: Hypothesized Mean Difference | O68: 0 | R68: Hypothesized Mean Difference | S68: 0
D69: 880 | E69: 2772 | F69: 380 | G69: 38 | H69: 285 | I69: 1328 | N69: df | O69: 11 | R69: df | S69: 10
D70: 2288 | E70: 2772 | F70: 150 | G70: 76 | H70: 361 | I70: 1577 | N70: t Stat | O70: -1.1126851 | R70: t Stat | S70: 2.1642064
D71: 174 | E71: 4158 | F71: 600 | G71: 133 | H71: 171 | I71: 1660 | N71: P(T<=t) one-tail | O71: 0.14478442 | R71: P(T<=t) one-tail | S71: 0.027856224
D72: 1044 | E72: 138 | F72: 1650 | G72: 133 | H72: 171 | I72: 996 | N72: t Critical one-tail | O72: 1.7958848 | R72: t Critical one-tail | S72: 1.8124611
D73: 2262 | E73: 552 | F73: 1800 | G73: 209 | H73: 171 | I73: 1232 | N73: P(T<=t) two-tail | O73: 0.28956884 | R73: P(T<=t) two-tail | S73: 0.055712449
D74: 462 | E74: 966 | F74: 1950 | G74: 228 | H74: 750 | I74: 110 | N74: t Critical two-tail | O74: 2.2009852 | R74: t Critical two-tail | S74: 2.2281389
D75: 150 | E75: 1104 | F75: 2850 | G75: 304 | H75: 750 | I75: 165
D76: 136 | E76: 2346 | F76: 3000 | G76: 323 | H76: 750 | I76: 440
D77: 255 | E77: 816 | F77: 300 | G77: 750 | H77: 1050 | I77: 632.5
D78: 1404 | E78: 1224 | F78: 450 | G78: 1500 | H78: 1200 | I78: 180
D79: 1620 | E79: 1326 | F79: 1500 | G79: 1800 | H79: 1950 | I79: 270
D80: 1836 | E80: 1734 | F80: 510 | G80: 1800 | H80: 750 | I80: 810
D81: 825 | E81: 1836 | F81: 850 | G81: 1800 | H81: 900 | I81: 900
D82: 840 | E82: 2040 | F82: 1190 | G82: 2100 | H82: 1800 | I82: 990
D83: 1760 | E83: 84 | F83: 2720 | G83: 2400 | H83: 1950 | I83: 1080
D84: 2112 | E84: 1092 | F84: 2720 | G84: 2400 | H84: 680 | I84: 1080
D85: 2640 | E85: 99 | F85: 3060 | G85: 300 | H85: 680 | I85: 1530
D86: 900 | E86: 231 | F86: 2465 | G86: 900 | H86: 850 | I86: 162
... D112: 437 | E112: 760 | F112: 581 | G112: 3230 | H112: 3344 | I112: 1938
E113: 418 | F113: 581 | G113: 3230 | H113: 1496 | I113: 2040
E114: 342 | F114: 996 | G114: 3400 | H114: 30 | I114: 336
E115: 627 | F115: 1079 | G115: 3400 | H115: 30 | I115: 504
E116: 1083 | F116: 1245 | G116: 2465 | H116: 45 | I116: 840
E117: 192 | F117: 1577 | G117: 432 | H117: 75 | I117: 840
E118: 480 | F118: 792 | G118: 432 | H118: 90 | I118: 1428
E119: 576 | F119: 1056 | G119: 540 | H119: 135 | I119: 561
E120: 1056 | F120: 1056 | G120: 648 | H120: 180 | I120: 627
E121: 1680 | F121: 1760 | G121: 648 | H121: 255 | I121: 396
E122: 3360 | F122: 1100 | G122: 648 | H122: 270 | I122: 280
E123: 80 | F123: 55 | G123: 756 | H123: 285 | I123: 1820
E124: 480 | F124: 495 | G124: 864 | H124: 29 | I124: 2520
... E357: 391 | F357: 900 | G357: 486 | H357: 2520 | I357: 560
F358: 900 | G358: 594 | H358: 2940 | I358: 840
F359: 1350 | G359: 648 | H359: 2940 | I359: 840
F360: 787.5 | G360: 648 | H360: 3150 | I360: 980
F361: 38 | G361: 702 | H361: 3360 | I361: 980
...

Sheet Project Work - Data wrows (2)
A1: Order Date | B1: Order Number | C1: Product | D1: Quantity | E1: Price Per Unit | F1: Fixed Price Per Unit | G1: Cost per Unit | H1: Fixed Cost Per Unit | I1: Revenue | J1: Costs | K1: Profit | L1: Order Survey Response | M1: Customer ID | N1: Customer Category | O1: Customer Tenure | P1: Subset Label | Q1: Subset | R1: Subset Check
A2: 44414 | B2: 21-1810 | C2: P001 | D2: 2 | E2: 108 | F2: =IF(E2="",_xlfn.XLOOKUP(C2,'Price Averages'!$D$4:$D$103,'Price Averages'!$E$4:$E$103, "FALSE"), E2) -> 108 | G2: 36 | H2: =IF(G2="", _xlfn.XLOOKUP(C2, 'Cost Averages'!$D$4:$D$103,'Cost Averages'!$E$4:$E$103, "FALSE"),G2) -> 36 | L2: Neither | M2: CG-1446 | N2: Community & Government | O2: 14.59367 | P2: =CHAR(64+(YEAR(A2)-2014)) -> G | Q2: =YEAR(A2) -> 2021 | R2: =IF(P2=CHAR(64 + (YEAR(A2) - 2014)), 0, 1) -> 0
A3: 43785.001 | B3: 19-1635 | C3: P001 | D3: 4 | E3: 108 | F3: =IF(E3="",_xlfn.XLOOKUP(C3,'Price Averages'!$D$4:$D$103,'Price Averages'!$E$4:$E$103, "FALSE"), E3) -> 108 | G3: 36 | H3: =IF(G3="", _xlfn.XLOOKUP(C3, 'Cost Averages'!$D$4:$D$103,'Cost Averages'!$E$4:$E$103, "FALSE"),G3) -> 36 | L3: Neither | M3: CT-3471 | N3: Creative & Technology | O3: 13.537351 | P3: =CHAR(64+(YEAR(A3)-2014)) -> E | Q3: =YEAR(A3) -> 2019 | R3: =IF(P3=CHAR(64 + (YEAR(A3) - 2014)), 0, 1) -> 0
A4: 43681.278 | B4: 19-2614 | C4: P001 | D4: 4 | E4: 108 | F4: =IF(E4="",_xlfn.XLOOKUP(C4,'Price Averages'!$D$4:$D$103,'Price Averages'!$E$4:$E$103, "FALSE"), E4) -> 108 | G4: 36 | H4: =IF(G4="", _xlfn.XLOOKUP(C4, 'Cost Averages'!$D$4:$D$103,'Cost Averages'!$E$4:$E$103, "FALSE"),G4) -> 36 | L4: Satisfied | M4: HS-7220 | N4: Healthcare & Safety | O4: 7.1104128 | P4: =CHAR(64+(YEAR(A4)-2014)) -> E | Q4: =YEAR(A4) -> 2019 | R4: =IF(P4=CHAR(64 + (YEAR(A4) - 2014)), 0, 1) -> 0
A5: 44139.002 | B5: 20-1947 | C5: P001 | D5: 6 | E5: 108 | F5: =IF(E5="",_xlfn.XLOOKUP(C5,'Price Averages'!$D$4:$D$103,'Price Averages'!$E$4:$E$103, "FALSE"), E5) -> 108 | G5: 36 | H5: =IF(G5="", _xlfn.XLOOKUP(C5, 'Cost Averages'!$D$4:$D$103,'Cost Averages'!$E$4:$E$103, "FALSE"),G5) -> 36 | L5: Neither | M5: CT-3932 | N5: Creative & Technology | O5: 13.929237 | P5: =CHAR(64+(YEAR(A5)-2014)) -> F | Q5: =YEAR(A5) -> 2020 | R5: =IF(P5=CHAR(64 + (YEAR(A5) - 2014)), 0, 1) -> 0
A6: 44248.705 | B6: 21-3874 | C6: P001 | D6: 6 | E6: 108 | F6: =IF(E6="",_xlfn.XLOOKUP(C6,'Price Averages'!$D$4:$D$103,'Price Averages'!$E$4:$E$103, "FALSE"), E6) -> 108 | G6: 36 | H6: =IF(G6="", _xlfn.XLOOKUP(C6, 'Cost Averages'!$D$4:$D$103,'Cost Averages'!$E$4:$E$103, "FALSE"),G6) -> 36 | L6: Neither | M6: CT-3242 | N6: Creative & Technology | O6: 11.082295 | P6: =CHAR(64+(YEAR(A6)-2014)) -> G | Q6: =YEAR(A6) -> 2021 | R6: =IF(P6=CHAR(64 + (YEAR(A6) - 2014)), 0, 1) -> 0
A7: 44575.067 | B7: 22-2472 | C7: P001 | D7: 7 | E7: 108 | F7: =IF(E7="",_xlfn.XLOOKUP(C7,'Price Averages'!$D$4:$D$103,'Price Averages'!$E$4:$E$103, "FALSE"), E7) -> 108 | H7: =IF(G7="", _xlfn.XLOOKUP(C7, 'Cost Averages'!$D$4:$D$103,'Cost Averages'!$E$4:$E$103, "FALSE"),G7) -> 36 | L7: Neither | M7: FE-652 | N7: Facilities & Services | O7: 14.376987 | P7: =CHAR(64+(YEAR(A7)-2014)) -> H | Q7: =YEAR(A7) -> 2022 | R7: =IF(P7=CHAR(64 + (YEAR(A7) - 2014)), 0, 1) -> 0
A8: 43941 | B8: 20-3100 | C8: P001 | D8: 8 | E8: 108 | F8: =IF(E8="",_xlfn.XLOOKUP(C8,'Price Averages'!$D$4:$D$103,'Price Averages'!$E$4:$E$103, "FALSE"), E8) -> 108 | G8: 36 | H8: =IF(G8="", _xlfn.XLOOKUP(C8, 'Cost Averages'!$D$4:$D$103,'Cost Averages'!$E$4:$E$103, "FALSE"),G8) -> 36 | L8: Neither | M8: SR-930 | N8: Sports & Recreation | O8: 14.690199 | P8: =CHAR(64+(YEAR(A8)-2014)) -> F | Q8: =YEAR(A8) -> 2020 | R8: =IF(P8=CHAR(64 + (YEAR(A8) - 2014)), 0, 1) -> 0
A9: 44005.712 | B9: 20-4975 | C9: P001 | D9: 9 | E9: 108 | F9: =IF(E9="",_xlfn.XLOOKUP(C9,'Price Averages'!$D$4:$D$103,'Price Averages'!$E$4:$E$103, "FALSE"), E9) -> 108 | G9: 36 | H9: =IF(G9="", _xlfn.XLOOKUP(C9, 'Cost Averages'!$D$4:$D$103,'Cost Averages'!$E$4:$E$103, "FALSE"),G9) -> 36 | L9: Dissatisfied | M9: CG-1606 | N9: Community & Government | O9: 12.452986 | P9: =CHAR(64+(YEAR(A9)-2014)) -> F | Q9: =YEAR(A9) -> 2020 | R9: =IF(P9=CHAR(64 + (YEAR(A9) - 2014)), 0, 1) -> 0
A10: 44321 | B10: 21-2909 | C10: P001 | D10: 9 | E10: 108 | F10: =IF(E10="",_xlfn.XLOOKUP(C10,'Price Averages'!$D$4:$D$103,'Price Averages'!$E$4:$E$103, "FALSE"), E10) -> 108 | G10: 36 | H10: =IF(G10="", _xlfn.XLOOKUP(C10, 'Cost Averages'!$D$4:$D$103,'Cost Averages'!$E$4:$E$103, "FALSE"),G10) -> 36 | L10: Neither | M10: HS-7802 | N10: Healthcare & Safety | O10: 12.801145 | P10: =CHAR(64+(YEAR(A10)-2014)) -> G | Q10: =YEAR(A10) -> 2021 | R10: =IF(P10=CHAR(64 + (YEAR(A10) - 2014)), 0, 1) -> 0
A11: 44608.864 | B11: 22-1971 | C11: P001 | D11: 9 | E11: 108 | F11: =IF(E11="",_xlfn.XLOOKUP(C11,'Price Averages'!$D$4:$D$103,'Price Averages'!$E$4:$E$103, "FALSE"), E11) -> 108 | H11: =IF(G11="", _xlfn.XLOOKUP(C11, 'Cost Averages'!$D$4:$D$103,'Cost Averages'!$E$4:$E$103, "FALSE"),G11) -> 36 | L11: Neither | M11: CP-2865 | N11: Corporate & Professional | O11: 11.971066 | P11: =CHAR(64+(YEAR(A11)-2014)) -> H | Q11: =YEAR(A11) -> 2022 | R11: =IF(P11=CHAR(64 + (YEAR(A11) - 2014)), 0, 1) -> 0
A12: 43566.034 | B12: 19-1999 | C12: P001 | D12: 10 | E12: 108 | F12: =IF(E12="",_xlfn.XLOOKUP(C12,'Price Averages'!$D$4:$D$103,'Price Averages'!$E$4:$E$103, "FALSE"), E12) -> 108 | G12: 36 | H12: =IF(G12="", _xlfn.XLOOKUP(C12, 'Cost Averages'!$D$4:$D$103,'Cost Averages'!$E$4:$E$103, "FALSE"),G12) -> 36 | L12: Satisfied | M12: HS-7291 | N12: Healthcare & Safety | O12: 10.42743 | P12: =CHAR(64+(YEAR(A12)-2014)) -> E | Q12: =YEAR(A12) -> 2019 | R12: =IF(P12=CHAR(64 + (YEAR(A12) - 2014)), 0, 1) -> 0
A13: 43604.871 | B13: 19-2066 | C13: P001 | D13: 10 | E13: 108 | F13: =IF(E13="",_xlfn.XLOOKUP(C13,'Price Averages'!$D$4:$D$103,'Price Averages'!$E$4:$E$103, "FALSE"), E13) -> 108 | G13: 36 | H13: =IF(G13="", _xlfn.XLOOKUP(C13, 'Cost Averages'!$D$4:$D$103,'Cost Averages'!$E$4:$E$103, "FALSE"),G13) -> 36 | L13: Neither | M13: FE-6981 | N13: Facilities & Services | O13: 10.517826 | P13: =CHAR(64+(YEAR(A13)-2014)) -> E | Q13: =YEAR(A13) -> 2019 | R13: =IF(P13=CHAR(64 + (YEAR(A13) - 2014)), 0, 1) -> 0
A14: 44301 | B14: 21-1426 | C14: P001 | D14: 10 | E14: 108 | F14: =IF(E14="",_xlfn.XLOOKUP(C14,'Price Averages'!$D$4:$D$103,'Price Averages'!$E$4:$E$103, "FALSE"), E14) -> 108 | G14: 36 | H14: =IF(G14="", _xlfn.XLOOKUP(C14, 'Cost Averages'!$D$4:$D$103,'Cost Averages'!$E$4:$E$103, "FALSE"),G14) -> 36 | L14: Neither | M14: CP-2865 | N14: Corporate & Professional | O14: 11.971066 | P14: =CHAR(64+(YEAR(A14)-2014)) -> G | Q14: =YEAR(A14) -> 2021 | R14: =IF(P14=CHAR(64 + (YEAR(A14) - 2014)), 0, 1) -> 0
A15: 43092.206 | B15: 17-2409 | C15: P001 | D15: 11 | E15: 108 | F15: =IF(E15="",_xlfn.XLOOKUP(C15,'Price Averages'!$D$4:$D$103,'Price Averages'!$E$4:$E$103, "FALSE"), E15) -> 108 | G15: 36 | H15: =IF(G15="", _xlfn.XLOOKUP(C15, 'Cost Averages'!$D$4:$D$103,'Cost Averages'!$E$4:$E$103, "FALSE"),G15) -> 36 | L15: Satisfied | M15: SR-9132 | N15: Sports & Recreation | O15: 12.865075 | P15: =CHAR(64+(YEAR(A15)-2014)) -> C | Q15: =YEAR(A15) -> 2017 | R15: =IF(P15=CHAR(64 + (YEAR(A15) - 2014)), 0, 1) -> 0
A16: 43434.135 | B16: 18-1412 | C16: P001 | D16: 11 | E16: 108 | F16: =IF(E16="",_xlfn.XLOOKUP(C16,'Price Averages'!$D$4:$D$103,'Price Averages'!$E$4:$E$103, "FALSE"), E16) -> 108 | G16: 36 | H16: =IF(G16="", _xlfn.XLOOKUP(C16, 'Cost Averages'!$D$4:$D$103,'Cost Averages'!$E$4:$E$103, "FALSE"),G16) -> 36 | L16: Satisfied | M16: EE-4169 | N16: Education | O16: 15.24191 | P16: =CHAR(64+(YEAR(A16)-2014)) -> D | Q16: =YEAR(A16) -> 2018 | R16: =IF(P16=CHAR(64 + (YEAR(A16) - 2014)), 0, 1) -> 0
A17: 43361.9 | B17: 18-3462 | C17: P001 | D17: 11 | F17: =IF(E17="",_xlfn.XLOOKUP(C17,'Price Averages'!$D$4:$D$103,'Price Averages'!$E$4:$E$103, "FALSE"), E17) -> 108 | G17: 36 | H17: =IF(G17="", _xlfn.XLOOKUP(C17, 'Cost Averages'!$D$4:$D$103,'Cost Averages'!$E$4:$E$103, "FALSE"),G17) -> 36 | L17: Dissatisfied | M17: CG-1627 | N17: Community & Government | O17: 15.856808 | P17: =CHAR(64+(YEAR(A17)-2014)) -> D | Q17: =YEAR(A17) -> 2018 | R17: =IF(P17=CHAR(64 + (YEAR(A17) - 2014)), 0, 1) -> 0
A18: 43566.117 | B18: 19-2912 | C18: P001 | D18: 11 | E18: 108 | F18: =IF(E18="",_xlfn.XLOOKUP(C18,'Price Averages'!$D$4:$D$103,'Price Averages'!$E$4:$E$103, "FALSE"), E18) -> 108 | G18: 36 | H18: =IF(G18="", _xlfn.XLOOKUP(C18, 'Cost Averages'!$D$4:$D$103,'Cost Averages'!$E$4:$E$103, "FALSE"),G18) -> 36 | L18: Satisfied | M18: CT-3169 | N18: Creative & Technology | O18: 8.8514729 | P18: =CHAR(64+(YEAR(A18)-2014)) -> E | Q18: =YEAR(A18) -> 2019 | R18: =IF(P18=CHAR(64 + (YEAR(A18) - 2014)), 0, 1) -> 0
A19: 44326.837 | B19: 21-3329 | C19: P001 | D19: 11 | E19: 108 | F19: =IF(E19="",_xlfn.XLOOKUP(C19,'Price Averages'!$D$4:$D$103,'Price Averages'!$E$4:$E$103, "FALSE"), E19) -> 108 | G19: 36 | H19: =IF(G19="", _xlfn.XLOOKUP(C19, 'Cost Averages'!$D$4:$D$103,'Cost Averages'!$E$4:$E$103, "FALSE"),G19) -> 36 | L19: Neither | M19: FE-6765 | N19: Facilities & Services | O19: 7.733715 | P19: =CHAR(64+(YEAR(A19)-2014)) -> G | Q19: =YEAR(A19) -> 2021 | R19: =IF(P19=CHAR(64 + (YEAR(A19) - 2014)), 0, 1) -> 0
A20: 44373 | B20: 21-4574 | C20: P001 | D20: 11 | E20: 108 | F20: =IF(E20="",_xlfn.XLOOKUP(C20,'Price Averages'!$D$4:$D$103,'Price Averages'!$E$4:$E$103, "FALSE"), E20) -> 108 | G20: 36 | H20: =IF(G20="", _xlfn.XLOOKUP(C20, 'Cost Averages'!$D$4:$D$103,'Cost Averages'!$E$4:$E$103, "FALSE"),G20) -> 36 | L20: Neither | M20: CT-3242 | N20: Creative & Technology | O20: 11.082295 | P20: =CHAR(64+(YEAR(A20)-2014)) -> G | Q20: =YEAR(A20) -> 2021 | R20: =IF(P20=CHAR(64 + (YEAR(A20) - 2014)), 0, 1) -> 0
A21: 44201 | B21: 21-1653 | C21: P001 | D21: 12 | E21: 108 | F21: =IF(E21="",_xlfn.XLOOKUP(C21,'Price Averages'!$D$4:$D$103,'Price Averages'!$E$4:$E$103, "FALSE"), E21) -> 108 | G21: 36 | H21: =IF(G21="", _xlfn.XLOOKUP(C21, 'Cost Averages'!$D$4:$D$103,'Cost Averages'!$E$4:$E$103, "FALSE"),G21) -> 36 | L21: Neither | M21: HS-712 | N21: Healthcare & Safety | O21: 10.428287 | P21: =CHAR(64+(YEAR(A21)-2014)) -> G | Q21: =YEAR(A21) -> 2021 | R21: =IF(P21=CHAR(64 + (YEAR(A21) - 2014)), 0, 1) -> 0
A22: 43606.173 | B22: 19-4248 | C22: P001 | D22: 13 | E22: 108 | F22: =IF(E22="",_xlfn.XLOOKUP(C22,'Price Averages'!$D$4:$D$103,'Price Averages'!$E$4:$E$103, "FALSE"), E22) -> 108 | H22: =IF(G22="", _xlfn.XLOOKUP(C22, 'Cost Averages'!$D$4:$D$103,'Cost Averages'!$E$4:$E$103, "FALSE"),G22) -> 36 | L22: Dissatisfied | M22: CG-1672 | N22: Community & Government | O22: 11.655356 | P22: =CHAR(64+(YEAR(A22)-2014)) -> E | Q22: =YEAR(A22) -> 2019 | R22: =IF(P22=CHAR(64 + (YEAR(A22) - 2014)), 0, 1) -> 0
A23: 44185.074 | B23: 20-2203 | C23: P001 | D23: 13 | E23: 108 | F23: =IF(E23="",_xlfn.XLOOKUP(C23,'Price Averages'!$D$4:$D$103,'Price Averages'!$E$4:$E$103, "FALSE"), E23) -> 108 | G23: 36 | H23: =IF(G23="", _xlfn.XLOOKUP(C23, 'Cost Averages'!$D$4:$D$103,'Cost Averages'!$E$4:$E$103, "FALSE"),G23) -> 36 | L23: Dissatisfied | M23: CP-2582 | N23: Corporate & Professional | O23: 11.428576 | P23: =CHAR(64+(YEAR(A23)-2014)) -> F | Q23: =YEAR(A23) -> 2020 | R23: =IF(P23=CHAR(64 + (YEAR(A23) - 2014)), 0, 1) -> 0
A24: 44093.491 | B24: 20-3125 | C24: P001 | D24: 14 | E24: 108 | F24: =IF(E24="",_xlfn.XLOOKUP(C24,'Price Averages'!$D$4:$D$103,'Price Averages'!$E$4:$E$103, "FALSE"), E24) -> 108 | G24: 36 | H24: =IF(G24="", _xlfn.XLOOKUP(C24, 'Cost Averages'!$D$4:$D$103,'Cost Averages'!$E$4:$E$103, "FALSE"),G24) -> 36 | L24: Dissatisfied | M24: FE-6470 | N24: Facilities & Services | O24: 10.43486 | P24: =CHAR(64+(YEAR(A24)-2014)) -> F | Q24: =YEAR(A24) -> 2020 | R24: =IF(P24=CHAR(64 + (YEAR(A24) - 2014)), 0, 1) -> 0
A25: 44091.755 | B25: 20-3569 | C25: P001 | D25: 14 | E25: 108 | F25: =IF(E25="",_xlfn.XLOOKUP(C25,'Price Averages'!$D$4:$D$103,'Price Averages'!$E$4:$E$103, "FALSE"), E25) -> 108 | G25: 36 | H25: =IF(G25="", _xlfn.XLOOKUP(C25, 'Cost Averages'!$D$4:$D$103,'Cost Averages'!$E$4:$E$103, "FALSE"),G25) -> 36 | L25: Satisfied | M25: HS-7997 | N25: Healthcare & Safety | O25: 16.148993 | P25: =CHAR(64+(YEAR(A25)-2014)) -> F | Q25: =YEAR(A25) -> 2020 | R25: =IF(P25=CHAR(64 + (YEAR(A25) - 2014)), 0, 1) -> 0
A26: 44310 | B26: 21-4373 | C26: P001 | D26: 14 | E26: 108 | F26: =IF(E26="",_xlfn.XLOOKUP(C26,'Price Averages'!$D$4:$D$103,'Price Averages'!$E$4:$E$103, "FALSE"), E26) -> 108 | H26: =IF(G26="", _xlfn.XLOOKUP(C26, 'Cost Averages'!$D$4:$D$103,'Cost Averages'!$E$4:$E$103, "FALSE"),G26) -> 36 | L26: Neither | M26: HS-7136 | N26: Healthcare & Safety | O26: 13.267192 | P26: =CHAR(64+(YEAR(A26)-2014)) -> G | Q26: =YEAR(A26) -> 2021 | R26: =IF(P26=CHAR(64 + (YEAR(A26) - 2014)), 0, 1) -> 0
A27: 44323 | B27: 21-4978 | C27: P001 | D27: 14 | E27: 108 | F27: =IF(E27="",_xlfn.XLOOKUP(C27,'Price Averages'!$D$4:$D$103,'Price Averages'!$E$4:$E$103, "FALSE"), E27) -> 108 | G27: 36 | H27: =IF(G27="", _xlfn.XLOOKUP(C27, 'Cost Averages'!$D$4:$D$103,'Cost Averages'!$E$4:$E$103, "FALSE"),G27) -> 36 | L27: Dissatisfied | M27: CP-2264 | N27: Corporate & Professional | O27: 6.2214891 | P27: =CHAR(64+(YEAR(A27)-2014)) -> G | Q27: =YEAR(A27) -> 2021 | R27: =IF(P27=CHAR(64 + (YEAR(A27) - 2014)), 0, 1) -> 0
A28: 43732.056 | B28: 19-2971 | C28: P001 | D28: 15 | F28: =IF(E28="",_xlfn.XLOOKUP(C28,'Price Averages'!$D$4:$D$103,'Price Averages'!$E$4:$E$103, "FALSE"), E28) -> 108 | G28: 36 | H28: =IF(G28="", _xlfn.XLOOKUP(C28, 'Cost Averages'!$D$4:$D$103,'Cost Averages'!$E$4:$E$103, "FALSE"),G28) -> 36 | L28: Neither | M28: SR-9797 | N28: Sports & Recreation | O28: 11.406234 | P28: =CHAR(64+(YEAR(A28)-2014)) -> E | Q28: =YEAR(A28) -> 2019 | R28: =IF(P28=CHAR(64 + (YEAR(A28) - 2014)), 0, 1) -> 0
A29: 44236.738 | B29: 21-1654 | C29: P001 | D29: 15 | E29: 108 | F29: =IF(E29="",_xlfn.XLOOKUP(C29,'Price Averages'!$D$4:$D$103,'Price Averages'!$E$4:$E$103, "FALSE"), E29) -> 108 | G29: 36 | H29: =IF(G29="", _xlfn.XLOOKUP(C29, 'Cost Averages'!$D$4:$D$103,'Cost Averages'!$E$4:$E$103, "FALSE"),G29) -> 36 | L29: Satisfied | M29: CP-2251 | N29: Corporate & Professional | O29: 11.003497 | P29: =CHAR(64+(YEAR(A29)-2014)) -> G | Q29: =YEAR(A29) -> 2021 | R29: =IF(P29=CHAR(64 + (YEAR(A29) - 2014)), 0, 1) -> 0
A30: 44118 | B30: 20-3242 | C30: P001 | D30: 16 | E30: 108 | F30: =IF(E30="",_xlfn.XLOOKUP(C30,'Price Averages'!$D$4:$D$103,'Price Averages'!$E$4:$E$103, "FALSE"), E30) -> 108 | G30: 36 | H30: =IF(G30="", _xlfn.XLOOKUP(C30, 'Cost Averages'!$D$4:$D$103,'Cost Averages'!$E$4:$E$103, "FALSE"),G30) -> 36 | L30: Neither | M30: CP-2582 | N30: Corporate & Professional | O30: 11.428576 | P30: =CHAR(64+(YEAR(A30)-2014)) -> F | Q30: =YEAR(A30) -> 2020 | R30: =IF(P30=CHAR(64 + (YEAR(A30) - 2014)), 0, 1) -> 0
A31: 44248.776 | B31: 21-2007 | C31: P001 | D31: 16 | E31: 108 | F31: =IF(E31="",_xlfn.XLOOKUP(C31,'Price Averages'!$D$4:$D$103,'Price Averages'!$E$4:$E$103, "FALSE"), E31) -> 108 | G31: 36 | H31: =IF(G31="", _xlfn.XLOOKUP(C31, 'Cost Averages'!$D$4:$D$103,'Cost Averages'!$E$4:$E$103, "FALSE"),G31) -> 36 | L31: Neither | M31: EE-4361 | N31: Education | O31: 14.760829 | P31: =CHAR(64+(YEAR(A31)-2014)) -> G | Q31: =YEAR(A31) -> 2021 | R31: =IF(P31=CHAR(64 + (YEAR(A31) - 2014)), 0, 1) -> 0
A32: 44132.833 | B32: 20-1567 | C32: P001 | D32: 17 | E32: 108 | F32: =IF(E32="",_xlfn.XLOOKUP(C32,'Price Averages'!$D$4:$D$103,'Price Averages'!$E$4:$E$103, "FALSE"), E32) -> 108 | G32: 36 | H32: =IF(G32="", _xlfn.XLOOKUP(C32, 'Cost Averages'!$D$4:$D$103,'Cost Averages'!$E$4:$E$103, "FALSE"),G32) -> 36 | L32: Neither | M32: EE-4400 | N32: Education | O32: 9.4239783 | P32: =CHAR(64+(YEAR(A32)-2014)) -> F | Q32: =YEAR(A32) -> 2020 | R32: =IF(P32=CHAR(64 + (YEAR(A32) - 2014)), 0, 1) -> 0
A33: 44223 | B33: 21-2675 | C33: P001 | D33: 17 | E33: 108 | F33: =IF(E33="",_xlfn.XLOOKUP(C33,'Price Averages'!$D$4:$D$103,'Price Averages'!$E$4:$E$103, "FALSE"), E33) -> 108 | G33: 36 | H33: =IF(G33="", _xlfn.XLOOKUP(C33, 'Cost Averages'!$D$4:$D$103,'Cost Averages'!$E$4:$E$103, "FALSE"),G33) -> 36 | L33: Neither | M33: HS-7129 | N33: Healthcare & Safety | O33: 10.112766 | P33: =CHAR(64+(YEAR(A33)-2014)) -> G | Q33: =YEAR(A33) -> 2021 | R33: =IF(P33=CHAR(64 + (YEAR(A33) - 2014)), 0, 1) -> 0
A34: 44742 | B34: 22-4161 | C34: P001 | D34: 17 | E34: 108 | F34: =IF(E34="",_xlfn.XLOOKUP(C34,'Price Averages'!$D$4:$D$103,'Price Averages'!$E$4:$E$103, "FALSE"), E34) -> 108 | G34: 36 | H34: =IF(G34="", _xlfn.XLOOKUP(C34, 'Cost Averages'!$D$4:$D$103,'Cost Averages'!$E$4:$E$103, "FALSE"),G34) -> 36 | L34: Neither | M34: CG-1701 | N34: Community & Government | O34: 12.954912 | P34: =CHAR(64+(YEAR(A34)-2014)) -> H | Q34: =YEAR(A34) -> 2022 | R34: =IF(P34=CHAR(64 + (YEAR(A34) - 2014)), 0, 1) -> 0
A35: 43036.146 | B35: 17-4686 | C35: P001 | D35: 18 | E35: 108 | F35: =IF(E35="",_xlfn.XLOOKUP(C35,'Price Averages'!$D$4:$D$103,'Price Averages'!$E$4:$E$103, "FALSE"), E35) -> 108 | G35: 36 | H35: =IF(G35="", _xlfn.XLOOKUP(C35, 'Cost Averages'!$D$4:$D$103,'Cost Averages'!$E$4:$E$103, "FALSE"),G35) -> 36 | L35: Satisfied | M35: FE-621 | N35: Facilities & Services | O35: 11.410471 | P35: =CHAR(64+(YEAR(A35)-2014)) -> C | Q35: =YEAR(A35) -> 2017 | R35: =IF(P35=CHAR(64 + (YEAR(A35) - 2014)), 0, 1) -> 0
A36: 43803.684 | B36: 19-2379 | C36: P001 | D36: 18 | E36: 108 | F36: =IF(E36="",_xlfn.XLOOKUP(C36,'Price Averages'!$D$4:$D$103,'Price Averages'!$E$4:$E$103, "FALSE"), E36) -> 108 | G36: 36 | H36: =IF(G36="", _xlfn.XLOOKUP(C36, 'Cost Averages'!$D$4:$D$103,'Cost Averages'!$E$4:$E$103, "FALSE"),G36) -> 36 | L36: Neither | M36: HS-7741 | N36: Healthcare & Safety | O36: 10.962309 | P36: =CHAR(64+(YEAR(A36)-2014)) -> E | Q36: =YEAR(A36) -> 2019 | R36: =IF(P36=CHAR(64 + (YEAR(A36) - 2014)), 0, 1) -> 0
A37: 43776.075 | B37: 19-4544 | C37: P001 | D37: 18 | E37: 108 | F37: =IF(E37="",_xlfn.XLOOKUP(C37,'Price Averages'!$D$4:$D$103,'Price Averages'!$E$4:$E$103, "FALSE"), E37) -> 108 | H37: =IF(G37="", _xlfn.XLOOKUP(C37, 'Cost Averages'!$D$4:$D$103,'Cost Averages'!$E$4:$E$103, "FALSE"),G37) -> 36 | L37: Neither | M37: CT-3342 | N37: Creative & Technology | O37: 11.394777 | P37: =CHAR(64+(YEAR(A37)-2014)) -> E | Q37: =YEAR(A37) -> 2019 | R37: =IF(P37=CHAR(64 + (YEAR(A37) - 2014)), 0, 1) -> 0
A38: 44251 | B38: 21-1634 | C38: P001 | D38: 18 | E38: 108 | F38: =IF(E38="",_xlfn.XLOOKUP(C38,'Price Averages'!$D$4:$D$103,'Price Averages'!$E$4:$E$103, "FALSE"), E38) -> 108 | G38: 36 | H38: =IF(G38="", _xlfn.XLOOKUP(C38, 'Cost Averages'!$D$4:$D$103,'Cost Averages'!$E$4:$E$103, "FALSE"),G38) -> 36 | L38: Neither | M38: CP-2430 | N38: Corporate & Professional | O38: 11.274865 | P38: =CHAR(64+(YEAR(A38)-2014)) -> G | Q38: =YEAR(A38) -> 2021 | R38: =IF(P38=CHAR(64 + (YEAR(A38) - 2014)), 0, 1) -> 0
A39: 43474.506 | B39: 19-1153 | C39: P001 | D39: 19 | E39: 108 | F39: =IF(E39="",_xlfn.XLOOKUP(C39,'Price Averages'!$D$4:$D$103,'Price Averages'!$E$4:$E$103, "FALSE"), E39) -> 108 | G39: 36 | H39: =IF(G39="", _xlfn.XLOOKUP(C39, 'Cost Averages'!$D$4:$D$103,'Cost Averages'!$E$4:$E$103, "FALSE"),G39) -> 36 | L39: Neither | M39: CT-3105 | N39: Creative & Technology | O39: 13.827196 | P39: =CHAR(64+(YEAR(A39)-2014)) -> E | Q39: =YEAR(A39) -> 2019 | R39: =IF(P39=CHAR(64 + (YEAR(A39) - 2014)), 0, 1) -> 0
A40: 43652.429 | B40: 19-3938 | C40: P001 | D40: 19 | F40: =IF(E40="",_xlfn.XLOOKUP(C40,'Price Averages'!$D$4:$D$103,'Price Averages'!$E$4:$E$103, "FALSE"), E40) -> 108 | G40: 36 | H40: =IF(G40="", _xlfn.XLOOKUP(C40, 'Cost Averages'!$D$4:$D$103,'Cost Averages'!$E$4:$E$103, "FALSE"),G40) -> 36 | L40: Satisfied | M40: EE-4869 | N40: Education | O40: 14.687858 | P40: =CHAR(64+(YEAR(A40)-2014)) -> E | Q40: =YEAR(A40) -> 2019 | R40: =IF(P40=CHAR(64 + (YEAR(A40) - 2014)), 0, 1) -> 0
A41: 44080 | B41: 20-1444 | C41: P001 | D41: 20 | E41: 108 | F41: =IF(E41="",_xlfn.XLOOKUP(C41,'Price Averages'!$D$4:$D$103,'Price Averages'!$E$4:$E$103, "FALSE"), E41) -> 108 | G41: 36 | H41: =IF(G41="", _xlfn.XLOOKUP(C41, 'Cost Averages'!$D$4:$D$103,'Cost Averages'!$E$4:$E$103, "FALSE"),G41) -> 36 | L41: Neither | M41: FE-6752 | N41: Facilities & Services | O41: 10.966283 | P41: =CHAR(64+(YEAR(A41)-2014)) -> F | Q41: =YEAR(A41) -> 2020 | R41: =IF(P41=CHAR(64 + (YEAR(A41) - 2014)), 0, 1) -> 0
A42: 43849.733 | B42: 20-1482 | C42: P001 | E42: 108 | F42: =IF(E42="",_xlfn.XLOOKUP(C42,'Price Averages'!$D$4:$D$103,'Price Averages'!$E$4:$E$103, "FALSE"), E42) -> 108 | G42: 36 | H42: =IF(G42="", _xlfn.XLOOKUP(C42, 'Cost Averages'!$D$4:$D$103,'Cost Averages'!$E$4:$E$103, "FALSE"),G42) -> 36 | L42: Satisfied | M42: SR-9223 | N42: Sports & Recreation | O42: 9.458618 | P42: =CHAR(64+(YEAR(A42)-2014)) -> F | Q42: =YEAR(A42) -> 2020 | R42: =IF(P42=CHAR(64 + (YEAR(A42) - 2014)), 0, 1) -> 0
A43: 44196.153 | B43: 20-3799 | C43: P002 | D43: 1 | E43: 144 | F43: =IF(E43="",_xlfn.XLOOKUP(C43,'Price Averages'!$D$4:$D$103,'Price Averages'!$E$4:$E$103, "FALSE"), E43) -> 144 | G43: 36 | H43: =IF(G43="", _xlfn.XLOOKUP(C43, 'Cost Averages'!$D$4:$D$103,'Cost Averages'!$E$4:$E$103, "FALSE"),G43) -> 36 | L43: Neither | M43: CT-3174 | N43: Creative & Technology | O43: 15.187892 | P43: =CHAR(64+(YEAR(A43)-2014)) -> F | Q43: =YEAR(A43) -> 2020 | R43: =IF(P43=CHAR(64 + (YEAR(A43) - 2014)), 0, 1) -> 0
A44: 43185.702 | B44: 18-2011 | C44: P002 | D44: 2 | E44: 144 | F44: =IF(E44="",_xlfn.XLOOKUP(C44,'Price Averages'!$D$4:$D$103,'Price Averages'!$E$4:$E$103, "FALSE"), E44) -> 144 | G44: 36 | H44: =IF(G44="", _xlfn.XLOOKUP(C44, 'Cost Averages'!$D$4:$D$103,'Cost Averages'!$E$4:$E$103, "FALSE"),G44) -> 36 | L44: Satisfied | M44: SR-955 | N44: Sports & Recreation | O44: 12.072415 | P44: =CHAR(64+(YEAR(A44)-2014)) -> D | Q44: =YEAR(A44) -> 2018 | R44: =IF(P44=CHAR(64 + (YEAR(A44) - 2014)), 0, 1) -> 0
